Workbook

Sheet 說明
B1: 美元 AI 相關公司債監控（Bloomberg Excel Add-in）
B2: 用途：追蹤 AI 主流發行人的美元債，計算 Carry、Value、Momentum、股票動能四個因子，產出加碼／減碼研究清單。方法見 repo 的 credit-quant.md。
B3: 本活頁簿只是研究工具，訊號不構成交易建議；實際交易請依公司授權與內控流程。
B5: ■ 工作表
B6: 說明：本頁。
B7: 參數：評價日、權重、門檻、評等對照表。
B8: 發行人：24 家 AI 相關公司（超大型雲端、半導體、伺服器／網通、軟體、資料中心、AI 雲端），含股票、財報、CDS 與債券彙總。
B9: 債券：債券清單與所有計算（每列一檔，最多 400 檔）。
B10: 排行：綜合分數前 20／後 20 名，以及「分類 × 評等」的平均 OAS。
B11: 分群統計：評等曲線、發行人曲線、各因子的平均與標準差（自動計算，債券表查表引用）。
B12: 搜尋：用 BSRCH 從 SRCH 儲存的搜尋抓債券清單。
B14: ■ 使用步驟
... B49: • 每月把「債券」表另存一份歷史快照，累積後用 repo 中的 credit_quant Python 範例做回測。

Sheet 參數
A1: 參數設定
A2: 黃底藍字為可調整的參數。
A4: 評價日 | B4: =TODAY() | C4: 預設為今天；要回看特定日期可改成固定日期
A5: 1 個月前 | B5: =EDATE(B4,-1) | C5: 動能與 OAS 變化的比較日期
A6: 3 個月前 | B6: =EDATE(B4,-3)
A7: 6 個月前 | B7: =EDATE(B4,-6)
A9: Carry 分群最少檔數 | B9: 5 | C9: 「評等 × 天期」分群不足此檔數時，改用評等分群
A10: 發行人曲線最少檔數 | B10: 3 | C10: 同一發行人至少幾檔才擬合發行人曲線
A11: 評等曲線最少檔數 | B11: 5 | C11: 同一評等分群至少幾檔才擬合評等曲線
A13: 權重：Carry | B13: 1 | C13: 綜合分數 = 各 z 分數依權重加權平均
A14: 權重：Value | B14: 1
A15: 權重：Momentum（債券） | B15: 0.5
A16: 權重：股票動能 | B16: 0.5 | C16: 投資等級債的動能以股票訊號為主
A18: 加碼候選門檻（百分位 ≤） | B18: 0.2 | C18: 評等分群內綜合分數前 20%
A19: 減碼候選門檻（百分位 >） | B19: 0.8 | C19: 評等分群內綜合分數後 20%
A22: 評等對照表
A23: 評等（BB_COMPOSITE） | B23: 評等分數 | C23: 評等分群
A24: AAA | B24: 1 | C24: AA以上
A25: AA+ | B25: 2 | C25: AA以上
A26: AA | B26: 3 | C26: AA以上
A27: AA- | B27: 4 | C27: AA以上
A28: A+ | B28: 5 | C28: A
A29: A | B29: 6 | C29: A
A30: A- | B30: 7 | C30: A
A31: BBB+ | B31: 8 | C31: BBB
A32: BBB | B32: 9 | C32: BBB
A33: BBB- | B33: 10 | C33: BBB
A34: BB+ | B34: 11 | C34: HY
A35: BB | B35: 12 | C35: HY
... A45: D | B45: 22 | C45: HY
A46: 評等分數：1 = AAA，數字越大評等越低。對照表以外的評等（例如 NR）不列入計算。

Sheet 發行人
A1: 發行人：AI 相關主流公司
A2: A–E 欄可自行增刪（黃底）。D 欄要和債券的 TICKER 一致才能對應；標「請確認」的請在終端機用 DES 查發債主體代碼。財報欄位以美元覆寫 (EQY_FUND_CRNCY=USD)，單位為百萬美元。
A3: 彭博欄位 → | F3: CUR_MKT_CAP | G3: CHG_PCT_6M | H3: VOLATILITY_90D | I3: SALES_REV_TURN | J3: CAPITAL_EXPEND | K3: CF_FREE_CASH_FLOW | L3: SHORT_AND_LONG_TERM_DEBT | M3: NET_DEBT | N3: EBITDA | O3: CDS_SPREAD_TICKER_5Y | P3: PX_LAST
A4: 分類 | B4: 公司 | C4: 股票代碼 | D4: 債券 Ticker | E4: 備註 | F4: 市值 (百萬 USD) | G4: 股價 6M 報酬 (%) | H4: 90 天 波動度 (%) | I4: 營收 | J4: 資本支出 | K4: 自由現金流 | L4: 總負債 | M4: 淨負債 | N4: EBITDA | O4: CDS 5Y 代碼 | P4: CDS 5Y (bp) | Q4: 淨負債 / EBITDA (x) | R4: 資本支出 / 營收 | S4: 自由現金流 / 總負債 | T4: 債券檔數 | U4: 流通在外合計 (百萬 USD) | V4: 加權平均 OAS (bp) | W4: 加權平均 DTS | X4: 平均 綜合分數 | Y4: 加碼候選 檔數 | Z4: 減碼候選 檔數
A5: 超大型雲端 | B5: Microsoft | C5: MSFT US Equity | D5: MSFT | E5: AAA 級，發債量少 | F5: =IF($C5="","",BDP($C5,F$3)) | G5: =IF($C5="","",BDP($C5,G$3)) | H5: =IF($C5="","",BDP($C5,H$3)) | I5: =IF($C5="","",BDP($C5,I$3,"EQY_FUND_CRNCY","USD")) | J5: =IF($C5="","",BDP($C5,J$3,"EQY_FUND_CRNCY","USD")) | K5: =IF($C5="","",BDP($C5,K$3,"EQY_FUND_CRNCY","USD")) | L5: =IF($C5="","",BDP($C5,L$3,"EQY_FUND_CRNCY","USD")) | M5: =IF($C5="","",BDP($C5,M$3,"EQY_FUND_CRNCY","USD")) | N5: =IF($C5="","",BDP($C5,N$3,"EQY_FUND_CRNCY","USD")) | O5: =IF($C5="","",BDP($C5,O$3)) | P5: =IF(LEFT($O5,1)="#","",IF($O5="","",BDP($O5,P$3))) | Q5: =IF(AND(ISNUMBER($M5),ISNUMBER($N5)),IF($N5>0,$M5/$N5,""),"") | R5: =IF(AND(ISNUMBER($J5),ISNUMBER($I5)),IF($I5>0,ABS($J5)/$I5,""),"") | S5: =IF(AND(ISNUMBER($K5),ISNUMBER($L5)),IF($L5>0,$K5/$L5,""),"") | T5: =IF($D5="","",COUNTIFS('債券'!$B$5:$B$404,$D5,'債券'!$Y$5:$Y$404,1)) | U5: =IF($D5="","",SUMPRODUCT(('債券'!$B$5:$B$404=$D5)*('債券'!$Y$5:$Y$404=1)*'債券'!$AV$5:$AV$404)/1E6) | V5: =IF($D5="","",IF(SUMPRODUCT(('債券'!$B$5:$B$404=$D5)*('債券'!$Y$5:$Y$404=1)*'債券'!$AV$5:$AV$404)>0,SUMPRODUCT(('債券'!$B$5:$B$404=$D5)*('債券'!$Y$5:$Y$404=1)*'債券'!$AV$5:$AV$404*'債券'!$AT$5:$AT$404)/SUMPRODUCT(('債券'!$B$5:$B$404=$D5)*('債券'!$Y$5:$Y$404=1)*'債券'!$AV$5:$AV$404),"")) | W5: =IF($D5="","",IF(SUMPRODUCT(('債券'!$B$5:$B$404=$D5)*('債券'!$Y$5:$Y$404=1)*'債券'!$AV$5:$AV$404)>0,SUMPRODUCT(('債券'!$B$5:$B$404=$D5)*('債券'!$Y$5:$Y$404=1)*'債券'!$AV$5:$AV$404*'債券'!$AW$5:$AW$404)/SUMPRODUCT(('債券'!$B$5:$B$404=$D5)*('債券'!$Y$5:$Y$404=1)*'債券'!$AV$5:$AV$404),"")) | X5: =IF($D5="","",IFERROR(AVERAGEIFS('債券'!$AQ$5:$AQ$404,'債券'!$B$5:$B$404,$D5,'債券'!$Y$5:$Y$404,1),"")) | Y5: =IF($D5="","",COUNTIFS('債券'!$B$5:$B$404,$D5,'債券'!$AS$5:$AS$404,"加碼候選")) | Z5: =IF($D5="","",COUNTIFS('債券'!$B$5:$B$404,$D5,'債券'!$AS$5:$AS$404,"減碼候選"))
A6: 超大型雲端 | B6: Alphabet | C6: GOOGL US Equity | D6: GOOGL | E6: AI 資本支出擴大後恢復發債 | F6: =IF($C6="","",BDP($C6,F$3)) | G6: =IF($C6="","",BDP($C6,G$3)) | H6: =IF($C6="","",BDP($C6,H$3)) | I6: =IF($C6="","",BDP($C6,I$3,"EQY_FUND_CRNCY","USD")) | J6: =IF($C6="","",BDP($C6,J$3,"EQY_FUND_CRNCY","USD")) | K6: =IF($C6="","",BDP($C6,K$3,"EQY_FUND_CRNCY","USD")) | L6: =IF($C6="","",BDP($C6,L$3,"EQY_FUND_CRNCY","USD")) | M6: =IF($C6="","",BDP($C6,M$3,"EQY_FUND_CRNCY","USD")) | N6: =IF($C6="","",BDP($C6,N$3,"EQY_FUND_CRNCY","USD")) | O6: =IF($C6="","",BDP($C6,O$3)) | P6: =IF(LEFT($O6,1)="#","",IF($O6="","",BDP($O6,P$3))) | Q6: =IF(AND(ISNUMBER($M6),ISNUMBER($N6)),IF($N6>0,$M6/$N6,""),"") | R6: =IF(AND(ISNUMBER($J6),ISNUMBER($I6)),IF($I6>0,ABS($J6)/$I6,""),"") | S6: =IF(AND(ISNUMBER($K6),ISNUMBER($L6)),IF($L6>0,$K6/$L6,""),"") | T6: =IF($D6="","",COUNTIFS('債券'!$B$5:$B$404,$D6,'債券'!$Y$5:$Y$404,1)) | U6: =IF($D6="","",SUMPRODUCT(('債券'!$B$5:$B$404=$D6)*('債券'!$Y$5:$Y$404=1)*'債券'!$AV$5:$AV$404)/1E6) | V6: =IF($D6="","",IF(SUMPRODUCT(('債券'!$B$5:$B$404=$D6)*('債券'!$Y$5:$Y$404=1)*'債券'!$AV$5:$AV$404)>0,SUMPRODUCT(('債券'!$B$5:$B$404=$D6)*('債券'!$Y$5:$Y$404=1)*'債券'!$AV$5:$AV$404*'債券'!$AT$5:$AT$404)/SUMPRODUCT(('債券'!$B$5:$B$404=$D6)*('債券'!$Y$5:$Y$404=1)*'債券'!$AV$5:$AV$404),"")) | W6: =IF($D6="","",IF(SUMPRODUCT(('債券'!$B$5:$B$404=$D6)*('債券'!$Y$5:$Y$404=1)*'債券'!$AV$5:$AV$404)>0,SUMPRODUCT(('債券'!$B$5:$B$404=$D6)*('債券'!$Y$5:$Y$404=1)*'債券'!$AV$5:$AV$404*'債券'!$AW$5:$AW$404)/SUMPRODUCT(('債券'!$B$5:$B$404=$D6)*('債券'!$Y$5:$Y$404=1)*'債券'!$AV$5:$AV$404),"")) | X6: =IF($D6="","",IFERROR(AVERAGEIFS('債券'!$AQ$5:$AQ$404,'債券'!$B$5:$B$404,$D6,'債券'!$Y$5:$Y$404,1),"")) | Y6: =IF($D6="","",COUNTIFS('債券'!$B$5:$B$404,$D6,'債券'!$AS$5:$AS$404,"加碼候選")) | Z6: =IF($D6="","",COUNTIFS('債券'!$B$5:$B$404,$D6,'債券'!$AS$5:$AS$404,"減碼候選"))
A7: 超大型雲端 | B7: Amazon | C7: AMZN US Equity | D7: AMZN | F7: =IF($C7="","",BDP($C7,F$3)) | G7: =IF($C7="","",BDP($C7,G$3)) | H7: =IF($C7="","",BDP($C7,H$3)) | I7: =IF($C7="","",BDP($C7,I$3,"EQY_FUND_CRNCY","USD")) | J7: =IF($C7="","",BDP($C7,J$3,"EQY_FUND_CRNCY","USD")) | K7: =IF($C7="","",BDP($C7,K$3,"EQY_FUND_CRNCY","USD")) | L7: =IF($C7="","",BDP($C7,L$3,"EQY_FUND_CRNCY","USD")) | M7: =IF($C7="","",BDP($C7,M$3,"EQY_FUND_CRNCY","USD")) | N7: =IF($C7="","",BDP($C7,N$3,"EQY_FUND_CRNCY","USD")) | O7: =IF($C7="","",BDP($C7,O$3)) | P7: =IF(LEFT($O7,1)="#","",IF($O7="","",BDP($O7,P$3))) | Q7: =IF(AND(ISNUMBER($M7),ISNUMBER($N7)),IF($N7>0,$M7/$N7,""),"") | R7: =IF(AND(ISNUMBER($J7),ISNUMBER($I7)),IF($I7>0,ABS($J7)/$I7,""),"") | S7: =IF(AND(ISNUMBER($K7),ISNUMBER($L7)),IF($L7>0,$K7/$L7,""),"") | T7: =IF($D7="","",COUNTIFS('債券'!$B$5:$B$404,$D7,'債券'!$Y$5:$Y$404,1)) | U7: =IF($D7="","",SUMPRODUCT(('債券'!$B$5:$B$404=$D7)*('債券'!$Y$5:$Y$404=1)*'債券'!$AV$5:$AV$404)/1E6) | V7: =IF($D7="","",IF(SUMPRODUCT(('債券'!$B$5:$B$404=$D7)*('債券'!$Y$5:$Y$404=1)*'債券'!$AV$5:$AV$404)>0,SUMPRODUCT(('債券'!$B$5:$B$404=$D7)*('債券'!$Y$5:$Y$404=1)*'債券'!$AV$5:$AV$404*'債券'!$AT$5:$AT$404)/SUMPRODUCT(('債券'!$B$5:$B$404=$D7)*('債券'!$Y$5:$Y$404=1)*'債券'!$AV$5:$AV$404),"")) | W7: =IF($D7="","",IF(SUMPRODUCT(('債券'!$B$5:$B$404=$D7)*('債券'!$Y$5:$Y$404=1)*'債券'!$AV$5:$AV$404)>0,SUMPRODUCT(('債券'!$B$5:$B$404=$D7)*('債券'!$Y$5:$Y$404=1)*'債券'!$AV$5:$AV$404*'債券'!$AW$5:$AW$404)/SUMPRODUCT(('債券'!$B$5:$B$404=$D7)*('債券'!$Y$5:$Y$404=1)*'債券'!$AV$5:$AV$404),"")) | X7: =IF($D7="","",IFERROR(AVERAGEIFS('債券'!$AQ$5:$AQ$404,'債券'!$B$5:$B$404,$D7,'債券'!$Y$5:$Y$404,1),"")) | Y7: =IF($D7="","",COUNTIFS('債券'!$B$5:$B$404,$D7,'債券'!$AS$5:$AS$404,"加碼候選")) | Z7: =IF($D7="","",COUNTIFS('債券'!$B$5:$B$404,$D7,'債券'!$AS$5:$AS$404,"減碼候選"))
A8: 超大型雲端 | B8: Meta Platforms | C8: META US Equity | D8: META | E8: 大量發債支應資料中心；另有表外 SPV 融資 | F8: =IF($C8="","",BDP($C8,F$3)) | G8: =IF($C8="","",BDP($C8,G$3)) | H8: =IF($C8="","",BDP($C8,H$3)) | I8: =IF($C8="","",BDP($C8,I$3,"EQY_FUND_CRNCY","USD")) | J8: =IF($C8="","",BDP($C8,J$3,"EQY_FUND_CRNCY","USD")) | K8: =IF($C8="","",BDP($C8,K$3,"EQY_FUND_CRNCY","USD")) | L8: =IF($C8="","",BDP($C8,L$3,"EQY_FUND_CRNCY","USD")) | M8: =IF($C8="","",BDP($C8,M$3,"EQY_FUND_CRNCY","USD")) | N8: =IF($C8="","",BDP($C8,N$3,"EQY_FUND_CRNCY","USD")) | O8: =IF($C8="","",BDP($C8,O$3)) | P8: =IF(LEFT($O8,1)="#","",IF($O8="","",BDP($O8,P$3))) | Q8: =IF(AND(ISNUMBER($M8),ISNUMBER($N8)),IF($N8>0,$M8/$N8,""),"") | R8: =IF(AND(ISNUMBER($J8),ISNUMBER($I8)),IF($I8>0,ABS($J8)/$I8,""),"") | S8: =IF(AND(ISNUMBER($K8),ISNUMBER($L8)),IF($L8>0,$K8/$L8,""),"") | T8: =IF($D8="","",COUNTIFS('債券'!$B$5:$B$404,$D8,'債券'!$Y$5:$Y$404,1)) | U8: =IF($D8="","",SUMPRODUCT(('債券'!$B$5:$B$404=$D8)*('債券'!$Y$5:$Y$404=1)*'債券'!$AV$5:$AV$404)/1E6) | V8: =IF($D8="","",IF(SUMPRODUCT(('債券'!$B$5:$B$404=$D8)*('債券'!$Y$5:$Y$404=1)*'債券'!$AV$5:$AV$404)>0,SUMPRODUCT(('債券'!$B$5:$B$404=$D8)*('債券'!$Y$5:$Y$404=1)*'債券'!$AV$5:$AV$404*'債券'!$AT$5:$AT$404)/SUMPRODUCT(('債券'!$B$5:$B$404=$D8)*('債券'!$Y$5:$Y$404=1)*'債券'!$AV$5:$AV$404),"")) | W8: =IF($D8="","",IF(SUMPRODUCT(('債券'!$B$5:$B$404=$D8)*('債券'!$Y$5:$Y$404=1)*'債券'!$AV$5:$AV$404)>0,SUMPRODUCT(('債券'!$B$5:$B$404=$D8)*('債券'!$Y$5:$Y$404=1)*'債券'!$AV$5:$AV$404*'債券'!$AW$5:$AW$404)/SUMPRODUCT(('債券'!$B$5:$B$404=$D8)*('債券'!$Y$5:$Y$404=1)*'債券'!$AV$5:$AV$404),"")) | X8: =IF($D8="","",IFERROR(AVERAGEIFS('債券'!$AQ$5:$AQ$404,'債券'!$B$5:$B$404,$D8,'債券'!$Y$5:$Y$404,1),"")) | Y8: =IF($D8="","",COUNTIFS('債券'!$B$5:$B$404,$D8,'債券'!$AS$5:$AS$404,"加碼候選")) | Z8: =IF($D8="","",COUNTIFS('債券'!$B$5:$B$404,$D8,'債券'!$AS$5:$AS$404,"減碼候選"))
A9: 超大型雲端 | B9: Oracle | C9: ORCL US Equity | D9: ORCL | E9: 槓桿高、AI 資本支出靠舉債，留意評等與 CDS | F9: =IF($C9="","",BDP($C9,F$3)) | G9: =IF($C9="","",BDP($C9,G$3)) | H9: =IF($C9="","",BDP($C9,H$3)) | I9: =IF($C9="","",BDP($C9,I$3,"EQY_FUND_CRNCY","USD")) | J9: =IF($C9="","",BDP($C9,J$3,"EQY_FUND_CRNCY","USD")) | K9: =IF($C9="","",BDP($C9,K$3,"EQY_FUND_CRNCY","USD")) | L9: =IF($C9="","",BDP($C9,L$3,"EQY_FUND_CRNCY","USD")) | M9: =IF($C9="","",BDP($C9,M$3,"EQY_FUND_CRNCY","USD")) | N9: =IF($C9="","",BDP($C9,N$3,"EQY_FUND_CRNCY","USD")) | O9: =IF($C9="","",BDP($C9,O$3)) | P9: =IF(LEFT($O9,1)="#","",IF($O9="","",BDP($O9,P$3))) | Q9: =IF(AND(ISNUMBER($M9),ISNUMBER($N9)),IF($N9>0,$M9/$N9,""),"") | R9: =IF(AND(ISNUMBER($J9),ISNUMBER($I9)),IF($I9>0,ABS($J9)/$I9,""),"") | S9: =IF(AND(ISNUMBER($K9),ISNUMBER($L9)),IF($L9>0,$K9/$L9,""),"") | T9: =IF($D9="","",COUNTIFS('債券'!$B$5:$B$404,$D9,'債券'!$Y$5:$Y$404,1)) | U9: =IF($D9="","",SUMPRODUCT(('債券'!$B$5:$B$404=$D9)*('債券'!$Y$5:$Y$404=1)*'債券'!$AV$5:$AV$404)/1E6) | V9: =IF($D9="","",IF(SUMPRODUCT(('債券'!$B$5:$B$404=$D9)*('債券'!$Y$5:$Y$404=1)*'債券'!$AV$5:$AV$404)>0,SUMPRODUCT(('債券'!$B$5:$B$404=$D9)*('債券'!$Y$5:$Y$404=1)*'債券'!$AV$5:$AV$404*'債券'!$AT$5:$AT$404)/SUMPRODUCT(('債券'!$B$5:$B$404=$D9)*('債券'!$Y$5:$Y$404=1)*'債券'!$AV$5:$AV$404),"")) | W9: =IF($D9="","",IF(SUMPRODUCT(('債券'!$B$5:$B$404=$D9)*('債券'!$Y$5:$Y$404=1)*'債券'!$AV$5:$AV$404)>0,SUMPRODUCT(('債券'!$B$5:$B$404=$D9)*('債券'!$Y$5:$Y$404=1)*'債券'!$AV$5:$AV$404*'債券'!$AW$5:$AW$404)/SUMPRODUCT(('債券'!$B$5:$B$404=$D9)*('債券'!$Y$5:$Y$404=1)*'債券'!$AV$5:$AV$404),"")) | X9: =IF($D9="","",IFERROR(AVERAGEIFS('債券'!$AQ$5:$AQ$404,'債券'!$B$5:$B$404,$D9,'債券'!$Y$5:$Y$404,1),"")) | Y9: =IF($D9="","",COUNTIFS('債券'!$B$5:$B$404,$D9,'債券'!$AS$5:$AS$404,"加碼候選")) | Z9: =IF($D9="","",COUNTIFS('債券'!$B$5:$B$404,$D9,'債券'!$AS$5:$AS$404,"減碼候選"))
A10: 大型科技 | B10: Apple | C10: AAPL US Equity | D10: AAPL | F10: =IF($C10="","",BDP($C10,F$3)) | G10: =IF($C10="","",BDP($C10,G$3)) | H10: =IF($C10="","",BDP($C10,H$3)) | I10: =IF($C10="","",BDP($C10,I$3,"EQY_FUND_CRNCY","USD")) | J10: =IF($C10="","",BDP($C10,J$3,"EQY_FUND_CRNCY","USD")) | K10: =IF($C10="","",BDP($C10,K$3,"EQY_FUND_CRNCY","USD")) | L10: =IF($C10="","",BDP($C10,L$3,"EQY_FUND_CRNCY","USD")) | M10: =IF($C10="","",BDP($C10,M$3,"EQY_FUND_CRNCY","USD")) | N10: =IF($C10="","",BDP($C10,N$3,"EQY_FUND_CRNCY","USD")) | O10: =IF($C10="","",BDP($C10,O$3)) | P10: =IF(LEFT($O10,1)="#","",IF($O10="","",BDP($O10,P$3))) | Q10: =IF(AND(ISNUMBER($M10),ISNUMBER($N10)),IF($N10>0,$M10/$N10,""),"") | R10: =IF(AND(ISNUMBER($J10),ISNUMBER($I10)),IF($I10>0,ABS($J10)/$I10,""),"") | S10: =IF(AND(ISNUMBER($K10),ISNUMBER($L10)),IF($L10>0,$K10/$L10,""),"") | T10: =IF($D10="","",COUNTIFS('債券'!$B$5:$B$404,$D10,'債券'!$Y$5:$Y$404,1)) | U10: =IF($D10="","",SUMPRODUCT(('債券'!$B$5:$B$404=$D10)*('債券'!$Y$5:$Y$404=1)*'債券'!$AV$5:$AV$404)/1E6) | V10: =IF($D10="","",IF(SUMPRODUCT(('債券'!$B$5:$B$404=$D10)*('債券'!$Y$5:$Y$404=1)*'債券'!$AV$5:$AV$404)>0,SUMPRODUCT(('債券'!$B$5:$B$404=$D10)*('債券'!$Y$5:$Y$404=1)*'債券'!$AV$5:$AV$404*'債券'!$AT$5:$AT$404)/SUMPRODUCT(('債券'!$B$5:$B$404=$D10)*('債券'!$Y$5:$Y$404=1)*'債券'!$AV$5:$AV$404),"")) | W10: =IF($D10="","",IF(SUMPRODUCT(('債券'!$B$5:$B$404=$D10)*('債券'!$Y$5:$Y$404=1)*'債券'!$AV$5:$AV$404)>0,SUMPRODUCT(('債券'!$B$5:$B$404=$D10)*('債券'!$Y$5:$Y$404=1)*'債券'!$AV$5:$AV$404*'債券'!$AW$5:$AW$404)/SUMPRODUCT(('債券'!$B$5:$B$404=$D10)*('債券'!$Y$5:$Y$404=1)*'債券'!$AV$5:$AV$404),"")) | X10: =IF($D10="","",IFERROR(AVERAGEIFS('債券'!$AQ$5:$AQ$404,'債券'!$B$5:$B$404,$D10,'債券'!$Y$5:$Y$404,1),"")) | Y10: =IF($D10="","",COUNTIFS('債券'!$B$5:$B$404,$D10,'債券'!$AS$5:$AS$404,"加碼候選")) | Z10: =IF($D10="","",COUNTIFS('債券'!$B$5:$B$404,$D10,'債券'!$AS$5:$AS$404,"減碼候選"))
A11: 大型科技 | B11: IBM | C11: IBM US Equity | D11: IBM | F11: =IF($C11="","",BDP($C11,F$3)) | G11: =IF($C11="","",BDP($C11,G$3)) | H11: =IF($C11="","",BDP($C11,H$3)) | I11: =IF($C11="","",BDP($C11,I$3,"EQY_FUND_CRNCY","USD")) | J11: =IF($C11="","",BDP($C11,J$3,"EQY_FUND_CRNCY","USD")) | K11: =IF($C11="","",BDP($C11,K$3,"EQY_FUND_CRNCY","USD")) | L11: =IF($C11="","",BDP($C11,L$3,"EQY_FUND_CRNCY","USD")) | M11: =IF($C11="","",BDP($C11,M$3,"EQY_FUND_CRNCY","USD")) | N11: =IF($C11="","",BDP($C11,N$3,"EQY_FUND_CRNCY","USD")) | O11: =IF($C11="","",BDP($C11,O$3)) | P11: =IF(LEFT($O11,1)="#","",IF($O11="","",BDP($O11,P$3))) | Q11: =IF(AND(ISNUMBER($M11),ISNUMBER($N11)),IF($N11>0,$M11/$N11,""),"") | R11: =IF(AND(ISNUMBER($J11),ISNUMBER($I11)),IF($I11>0,ABS($J11)/$I11,""),"") | S11: =IF(AND(ISNUMBER($K11),ISNUMBER($L11)),IF($L11>0,$K11/$L11,""),"") | T11: =IF($D11="","",COUNTIFS('債券'!$B$5:$B$404,$D11,'債券'!$Y$5:$Y$404,1)) | U11: =IF($D11="","",SUMPRODUCT(('債券'!$B$5:$B$404=$D11)*('債券'!$Y$5:$Y$404=1)*'債券'!$AV$5:$AV$404)/1E6) | V11: =IF($D11="","",IF(SUMPRODUCT(('債券'!$B$5:$B$404=$D11)*('債券'!$Y$5:$Y$404=1)*'債券'!$AV$5:$AV$404)>0,SUMPRODUCT(('債券'!$B$5:$B$404=$D11)*('債券'!$Y$5:$Y$404=1)*'債券'!$AV$5:$AV$404*'債券'!$AT$5:$AT$404)/SUMPRODUCT(('債券'!$B$5:$B$404=$D11)*('債券'!$Y$5:$Y$404=1)*'債券'!$AV$5:$AV$404),"")) | W11: =IF($D11="","",IF(SUMPRODUCT(('債券'!$B$5:$B$404=$D11)*('債券'!$Y$5:$Y$404=1)*'債券'!$AV$5:$AV$404)>0,SUMPRODUCT(('債券'!$B$5:$B$404=$D11)*('債券'!$Y$5:$Y$404=1)*'債券'!$AV$5:$AV$404*'債券'!$AW$5:$AW$404)/SUMPRODUCT(('債券'!$B$5:$B$404=$D11)*('債券'!$Y$5:$Y$404=1)*'債券'!$AV$5:$AV$404),"")) | X11: =IF($D11="","",IFERROR(AVERAGEIFS('債券'!$AQ$5:$AQ$404,'債券'!$B$5:$B$404,$D11,'債券'!$Y$5:$Y$404,1),"")) | Y11: =IF($D11="","",COUNTIFS('債券'!$B$5:$B$404,$D11,'債券'!$AS$5:$AS$404,"加碼候選")) | Z11: =IF($D11="","",COUNTIFS('債券'!$B$5:$B$404,$D11,'債券'!$AS$5:$AS$404,"減碼候選"))
A12: 半導體 | B12: NVIDIA | C12: NVDA US Equity | D12: NVDA | E12: 淨現金，流通債券少 | F12: =IF($C12="","",BDP($C12,F$3)) | G12: =IF($C12="","",BDP($C12,G$3)) | H12: =IF($C12="","",BDP($C12,H$3)) | I12: =IF($C12="","",BDP($C12,I$3,"EQY_FUND_CRNCY","USD")) | J12: =IF($C12="","",BDP($C12,J$3,"EQY_FUND_CRNCY","USD")) | K12: =IF($C12="","",BDP($C12,K$3,"EQY_FUND_CRNCY","USD")) | L12: =IF($C12="","",BDP($C12,L$3,"EQY_FUND_CRNCY","USD")) | M12: =IF($C12="","",BDP($C12,M$3,"EQY_FUND_CRNCY","USD")) | N12: =IF($C12="","",BDP($C12,N$3,"EQY_FUND_CRNCY","USD")) | O12: =IF($C12="","",BDP($C12,O$3)) | P12: =IF(LEFT($O12,1)="#","",IF($O12="","",BDP($O12,P$3))) | Q12: =IF(AND(ISNUMBER($M12),ISNUMBER($N12)),IF($N12>0,$M12/$N12,""),"") | R12: =IF(AND(ISNUMBER($J12),ISNUMBER($I12)),IF($I12>0,ABS($J12)/$I12,""),"") | S12: =IF(AND(ISNUMBER($K12),ISNUMBER($L12)),IF($L12>0,$K12/$L12,""),"") | T12: =IF($D12="","",COUNTIFS('債券'!$B$5:$B$404,$D12,'債券'!$Y$5:$Y$404,1)) | U12: =IF($D12="","",SUMPRODUCT(('債券'!$B$5:$B$404=$D12)*('債券'!$Y$5:$Y$404=1)*'債券'!$AV$5:$AV$404)/1E6) | V12: =IF($D12="","",IF(SUMPRODUCT(('債券'!$B$5:$B$404=$D12)*('債券'!$Y$5:$Y$404=1)*'債券'!$AV$5:$AV$404)>0,SUMPRODUCT(('債券'!$B$5:$B$404=$D12)*('債券'!$Y$5:$Y$404=1)*'債券'!$AV$5:$AV$404*'債券'!$AT$5:$AT$404)/SUMPRODUCT(('債券'!$B$5:$B$404=$D12)*('債券'!$Y$5:$Y$404=1)*'債券'!$AV$5:$AV$404),"")) | W12: =IF($D12="","",IF(SUMPRODUCT(('債券'!$B$5:$B$404=$D12)*('債券'!$Y$5:$Y$404=1)*'債券'!$AV$5:$AV$404)>0,SUMPRODUCT(('債券'!$B$5:$B$404=$D12)*('債券'!$Y$5:$Y$404=1)*'債券'!$AV$5:$AV$404*'債券'!$AW$5:$AW$404)/SUMPRODUCT(('債券'!$B$5:$B$404=$D12)*('債券'!$Y$5:$Y$404=1)*'債券'!$AV$5:$AV$404),"")) | X12: =IF($D12="","",IFERROR(AVERAGEIFS('債券'!$AQ$5:$AQ$404,'債券'!$B$5:$B$404,$D12,'債券'!$Y$5:$Y$404,1),"")) | Y12: =IF($D12="","",COUNTIFS('債券'!$B$5:$B$404,$D12,'債券'!$AS$5:$AS$404,"加碼候選")) | Z12: =IF($D12="","",COUNTIFS('債券'!$B$5:$B$404,$D12,'債券'!$AS$5:$AS$404,"減碼候選"))
A13: 半導體 | B13: Broadcom | C13: AVGO US Equity | D13: AVGO | E13: 併購融資，發債量大 | F13: =IF($C13="","",BDP($C13,F$3)) | G13: =IF($C13="","",BDP($C13,G$3)) | H13: =IF($C13="","",BDP($C13,H$3)) | I13: =IF($C13="","",BDP($C13,I$3,"EQY_FUND_CRNCY","USD")) | J13: =IF($C13="","",BDP($C13,J$3,"EQY_FUND_CRNCY","USD")) | K13: =IF($C13="","",BDP($C13,K$3,"EQY_FUND_CRNCY","USD")) | L13: =IF($C13="","",BDP($C13,L$3,"EQY_FUND_CRNCY","USD")) | M13: =IF($C13="","",BDP($C13,M$3,"EQY_FUND_CRNCY","USD")) | N13: =IF($C13="","",BDP($C13,N$3,"EQY_FUND_CRNCY","USD")) | O13: =IF($C13="","",BDP($C13,O$3)) | P13: =IF(LEFT($O13,1)="#","",IF($O13="","",BDP($O13,P$3))) | Q13: =IF(AND(ISNUMBER($M13),ISNUMBER($N13)),IF($N13>0,$M13/$N13,""),"") | R13: =IF(AND(ISNUMBER($J13),ISNUMBER($I13)),IF($I13>0,ABS($J13)/$I13,""),"") | S13: =IF(AND(ISNUMBER($K13),ISNUMBER($L13)),IF($L13>0,$K13/$L13,""),"") | T13: =IF($D13="","",COUNTIFS('債券'!$B$5:$B$404,$D13,'債券'!$Y$5:$Y$404,1)) | U13: =IF($D13="","",SUMPRODUCT(('債券'!$B$5:$B$404=$D13)*('債券'!$Y$5:$Y$404=1)*'債券'!$AV$5:$AV$404)/1E6) | V13: =IF($D13="","",IF(SUMPRODUCT(('債券'!$B$5:$B$404=$D13)*('債券'!$Y$5:$Y$404=1)*'債券'!$AV$5:$AV$404)>0,SUMPRODUCT(('債券'!$B$5:$B$404=$D13)*('債券'!$Y$5:$Y$404=1)*'債券'!$AV$5:$AV$404*'債券'!$AT$5:$AT$404)/SUMPRODUCT(('債券'!$B$5:$B$404=$D13)*('債券'!$Y$5:$Y$404=1)*'債券'!$AV$5:$AV$404),"")) | W13: =IF($D13="","",IF(SUMPRODUCT(('債券'!$B$5:$B$404=$D13)*('債券'!$Y$5:$Y$404=1)*'債券'!$AV$5:$AV$404)>0,SUMPRODUCT(('債券'!$B$5:$B$404=$D13)*('債券'!$Y$5:$Y$404=1)*'債券'!$AV$5:$AV$404*'債券'!$AW$5:$AW$404)/SUMPRODUCT(('債券'!$B$5:$B$404=$D13)*('債券'!$Y$5:$Y$404=1)*'債券'!$AV$5:$AV$404),"")) | X13: =IF($D13="","",IFERROR(AVERAGEIFS('債券'!$AQ$5:$AQ$404,'債券'!$B$5:$B$404,$D13,'債券'!$Y$5:$Y$404,1),"")) | Y13: =IF($D13="","",COUNTIFS('債券'!$B$5:$B$404,$D13,'債券'!$AS$5:$AS$404,"加碼候選")) | Z13: =IF($D13="","",COUNTIFS('債券'!$B$5:$B$404,$D13,'債券'!$AS$5:$AS$404,"減碼候選"))
A14: 半導體 | B14: AMD | C14: AMD US Equity | D14: AMD | F14: =IF($C14="","",BDP($C14,F$3)) | G14: =IF($C14="","",BDP($C14,G$3)) | H14: =IF($C14="","",BDP($C14,H$3)) | I14: =IF($C14="","",BDP($C14,I$3,"EQY_FUND_CRNCY","USD")) | J14: =IF($C14="","",BDP($C14,J$3,"EQY_FUND_CRNCY","USD")) | K14: =IF($C14="","",BDP($C14,K$3,"EQY_FUND_CRNCY","USD")) | L14: =IF($C14="","",BDP($C14,L$3,"EQY_FUND_CRNCY","USD")) | M14: =IF($C14="","",BDP($C14,M$3,"EQY_FUND_CRNCY","USD")) | N14: =IF($C14="","",BDP($C14,N$3,"EQY_FUND_CRNCY","USD")) | O14: =IF($C14="","",BDP($C14,O$3)) | P14: =IF(LEFT($O14,1)="#","",IF($O14="","",BDP($O14,P$3))) | Q14: =IF(AND(ISNUMBER($M14),ISNUMBER($N14)),IF($N14>0,$M14/$N14,""),"") | R14: =IF(AND(ISNUMBER($J14),ISNUMBER($I14)),IF($I14>0,ABS($J14)/$I14,""),"") | S14: =IF(AND(ISNUMBER($K14),ISNUMBER($L14)),IF($L14>0,$K14/$L14,""),"") | T14: =IF($D14="","",COUNTIFS('債券'!$B$5:$B$404,$D14,'債券'!$Y$5:$Y$404,1)) | U14: =IF($D14="","",SUMPRODUCT(('債券'!$B$5:$B$404=$D14)*('債券'!$Y$5:$Y$404=1)*'債券'!$AV$5:$AV$404)/1E6) | V14: =IF($D14="","",IF(SUMPRODUCT(('債券'!$B$5:$B$404=$D14)*('債券'!$Y$5:$Y$404=1)*'債券'!$AV$5:$AV$404)>0,SUMPRODUCT(('債券'!$B$5:$B$404=$D14)*('債券'!$Y$5:$Y$404=1)*'債券'!$AV$5:$AV$404*'債券'!$AT$5:$AT$404)/SUMPRODUCT(('債券'!$B$5:$B$404=$D14)*('債券'!$Y$5:$Y$404=1)*'債券'!$AV$5:$AV$404),"")) | W14: =IF($D14="","",IF(SUMPRODUCT(('債券'!$B$5:$B$404=$D14)*('債券'!$Y$5:$Y$404=1)*'債券'!$AV$5:$AV$404)>0,SUMPRODUCT(('債券'!$B$5:$B$404=$D14)*('債券'!$Y$5:$Y$404=1)*'債券'!$AV$5:$AV$404*'債券'!$AW$5:$AW$404)/SUMPRODUCT(('債券'!$B$5:$B$404=$D14)*('債券'!$Y$5:$Y$404=1)*'債券'!$AV$5:$AV$404),"")) | X14: =IF($D14="","",IFERROR(AVERAGEIFS('債券'!$AQ$5:$AQ$404,'債券'!$B$5:$B$404,$D14,'債券'!$Y$5:$Y$404,1),"")) | Y14: =IF($D14="","",COUNTIFS('債券'!$B$5:$B$404,$D14,'債券'!$AS$5:$AS$404,"加碼候選")) | Z14: =IF($D14="","",COUNTIFS('債券'!$B$5:$B$404,$D14,'債券'!$AS$5:$AS$404,"減碼候選"))
A15: 半導體 | B15: Intel | C15: INTC US Equity | D15: INTC | E15: 評等下調壓力 | F15: =IF($C15="","",BDP($C15,F$3)) | G15: =IF($C15="","",BDP($C15,G$3)) | H15: =IF($C15="","",BDP($C15,H$3)) | I15: =IF($C15="","",BDP($C15,I$3,"EQY_FUND_CRNCY","USD")) | J15: =IF($C15="","",BDP($C15,J$3,"EQY_FUND_CRNCY","USD")) | K15: =IF($C15="","",BDP($C15,K$3,"EQY_FUND_CRNCY","USD")) | L15: =IF($C15="","",BDP($C15,L$3,"EQY_FUND_CRNCY","USD")) | M15: =IF($C15="","",BDP($C15,M$3,"EQY_FUND_CRNCY","USD")) | N15: =IF($C15="","",BDP($C15,N$3,"EQY_FUND_CRNCY","USD")) | O15: =IF($C15="","",BDP($C15,O$3)) | P15: =IF(LEFT($O15,1)="#","",IF($O15="","",BDP($O15,P$3))) | Q15: =IF(AND(ISNUMBER($M15),ISNUMBER($N15)),IF($N15>0,$M15/$N15,""),"") | R15: =IF(AND(ISNUMBER($J15),ISNUMBER($I15)),IF($I15>0,ABS($J15)/$I15,""),"") | S15: =IF(AND(ISNUMBER($K15),ISNUMBER($L15)),IF($L15>0,$K15/$L15,""),"") | T15: =IF($D15="","",COUNTIFS('債券'!$B$5:$B$404,$D15,'債券'!$Y$5:$Y$404,1)) | U15: =IF($D15="","",SUMPRODUCT(('債券'!$B$5:$B$404=$D15)*('債券'!$Y$5:$Y$404=1)*'債券'!$AV$5:$AV$404)/1E6) | V15: =IF($D15="","",IF(SUMPRODUCT(('債券'!$B$5:$B$404=$D15)*('債券'!$Y$5:$Y$404=1)*'債券'!$AV$5:$AV$404)>0,SUMPRODUCT(('債券'!$B$5:$B$404=$D15)*('債券'!$Y$5:$Y$404=1)*'債券'!$AV$5:$AV$404*'債券'!$AT$5:$AT$404)/SUMPRODUCT(('債券'!$B$5:$B$404=$D15)*('債券'!$Y$5:$Y$404=1)*'債券'!$AV$5:$AV$404),"")) | W15: =IF($D15="","",IF(SUMPRODUCT(('債券'!$B$5:$B$404=$D15)*('債券'!$Y$5:$Y$404=1)*'債券'!$AV$5:$AV$404)>0,SUMPRODUCT(('債券'!$B$5:$B$404=$D15)*('債券'!$Y$5:$Y$404=1)*'債券'!$AV$5:$AV$404*'債券'!$AW$5:$AW$404)/SUMPRODUCT(('債券'!$B$5:$B$404=$D15)*('債券'!$Y$5:$Y$404=1)*'債券'!$AV$5:$AV$404),"")) | X15: =IF($D15="","",IFERROR(AVERAGEIFS('債券'!$AQ$5:$AQ$404,'債券'!$B$5:$B$404,$D15,'債券'!$Y$5:$Y$404,1),"")) | Y15: =IF($D15="","",COUNTIFS('債券'!$B$5:$B$404,$D15,'債券'!$AS$5:$AS$404,"加碼候選")) | Z15: =IF($D15="","",COUNTIFS('債券'!$B$5:$B$404,$D15,'債券'!$AS$5:$AS$404,"減碼候選"))
A16: 半導體 | B16: Qualcomm | C16: QCOM US Equity | D16: QCOM | F16: =IF($C16="","",BDP($C16,F$3)) | G16: =IF($C16="","",BDP($C16,G$3)) | H16: =IF($C16="","",BDP($C16,H$3)) | I16: =IF($C16="","",BDP($C16,I$3,"EQY_FUND_CRNCY","USD")) | J16: =IF($C16="","",BDP($C16,J$3,"EQY_FUND_CRNCY","USD")) | K16: =IF($C16="","",BDP($C16,K$3,"EQY_FUND_CRNCY","USD")) | L16: =IF($C16="","",BDP($C16,L$3,"EQY_FUND_CRNCY","USD")) | M16: =IF($C16="","",BDP($C16,M$3,"EQY_FUND_CRNCY","USD")) | N16: =IF($C16="","",BDP($C16,N$3,"EQY_FUND_CRNCY","USD")) | O16: =IF($C16="","",BDP($C16,O$3)) | P16: =IF(LEFT($O16,1)="#","",IF($O16="","",BDP($O16,P$3))) | Q16: =IF(AND(ISNUMBER($M16),ISNUMBER($N16)),IF($N16>0,$M16/$N16,""),"") | R16: =IF(AND(ISNUMBER($J16),ISNUMBER($I16)),IF($I16>0,ABS($J16)/$I16,""),"") | S16: =IF(AND(ISNUMBER($K16),ISNUMBER($L16)),IF($L16>0,$K16/$L16,""),"") | T16: =IF($D16="","",COUNTIFS('債券'!$B$5:$B$404,$D16,'債券'!$Y$5:$Y$404,1)) | U16: =IF($D16="","",SUMPRODUCT(('債券'!$B$5:$B$404=$D16)*('債券'!$Y$5:$Y$404=1)*'債券'!$AV$5:$AV$404)/1E6) | V16: =IF($D16="","",IF(SUMPRODUCT(('債券'!$B$5:$B$404=$D16)*('債券'!$Y$5:$Y$404=1)*'債券'!$AV$5:$AV$404)>0,SUMPRODUCT(('債券'!$B$5:$B$404=$D16)*('債券'!$Y$5:$Y$404=1)*'債券'!$AV$5:$AV$404*'債券'!$AT$5:$AT$404)/SUMPRODUCT(('債券'!$B$5:$B$404=$D16)*('債券'!$Y$5:$Y$404=1)*'債券'!$AV$5:$AV$404),"")) | W16: =IF($D16="","",IF(SUMPRODUCT(('債券'!$B$5:$B$404=$D16)*('債券'!$Y$5:$Y$404=1)*'債券'!$AV$5:$AV$404)>0,SUMPRODUCT(('債券'!$B$5:$B$404=$D16)*('債券'!$Y$5:$Y$404=1)*'債券'!$AV$5:$AV$404*'債券'!$AW$5:$AW$404)/SUMPRODUCT(('債券'!$B$5:$B$404=$D16)*('債券'!$Y$5:$Y$404=1)*'債券'!$AV$5:$AV$404),"")) | X16: =IF($D16="","",IFERROR(AVERAGEIFS('債券'!$AQ$5:$AQ$404,'債券'!$B$5:$B$404,$D16,'債券'!$Y$5:$Y$404,1),"")) | Y16: =IF($D16="","",COUNTIFS('債券'!$B$5:$B$404,$D16,'債券'!$AS$5:$AS$404,"加碼候選")) | Z16: =IF($D16="","",COUNTIFS('債券'!$B$5:$B$404,$D16,'債券'!$AS$5:$AS$404,"減碼候選"))
A17: 半導體 | B17: Micron | C17: MU US Equity | D17: MU | E17: HBM 記憶體，景氣循環 | F17: =IF($C17="","",BDP($C17,F$3)) | G17: =IF($C17="","",BDP($C17,G$3)) | H17: =IF($C17="","",BDP($C17,H$3)) | I17: =IF($C17="","",BDP($C17,I$3,"EQY_FUND_CRNCY","USD")) | J17: =IF($C17="","",BDP($C17,J$3,"EQY_FUND_CRNCY","USD")) | K17: =IF($C17="","",BDP($C17,K$3,"EQY_FUND_CRNCY","USD")) | L17: =IF($C17="","",BDP($C17,L$3,"EQY_FUND_CRNCY","USD")) | M17: =IF($C17="","",BDP($C17,M$3,"EQY_FUND_CRNCY","USD")) | N17: =IF($C17="","",BDP($C17,N$3,"EQY_FUND_CRNCY","USD")) | O17: =IF($C17="","",BDP($C17,O$3)) | P17: =IF(LEFT($O17,1)="#","",IF($O17="","",BDP($O17,P$3))) | Q17: =IF(AND(ISNUMBER($M17),ISNUMBER($N17)),IF($N17>0,$M17/$N17,""),"") | R17: =IF(AND(ISNUMBER($J17),ISNUMBER($I17)),IF($I17>0,ABS($J17)/$I17,""),"") | S17: =IF(AND(ISNUMBER($K17),ISNUMBER($L17)),IF($L17>0,$K17/$L17,""),"") | T17: =IF($D17="","",COUNTIFS('債券'!$B$5:$B$404,$D17,'債券'!$Y$5:$Y$404,1)) | U17: =IF($D17="","",SUMPRODUCT(('債券'!$B$5:$B$404=$D17)*('債券'!$Y$5:$Y$404=1)*'債券'!$AV$5:$AV$404)/1E6) | V17: =IF($D17="","",IF(SUMPRODUCT(('債券'!$B$5:$B$404=$D17)*('債券'!$Y$5:$Y$404=1)*'債券'!$AV$5:$AV$404)>0,SUMPRODUCT(('債券'!$B$5:$B$404=$D17)*('債券'!$Y$5:$Y$404=1)*'債券'!$AV$5:$AV$404*'債券'!$AT$5:$AT$404)/SUMPRODUCT(('債券'!$B$5:$B$404=$D17)*('債券'!$Y$5:$Y$404=1)*'債券'!$AV$5:$AV$404),"")) | W17: =IF($D17="","",IF(SUMPRODUCT(('債券'!$B$5:$B$404=$D17)*('債券'!$Y$5:$Y$404=1)*'債券'!$AV$5:$AV$404)>0,SUMPRODUCT(('債券'!$B$5:$B$404=$D17)*('債券'!$Y$5:$Y$404=1)*'債券'!$AV$5:$AV$404*'債券'!$AW$5:$AW$404)/SUMPRODUCT(('債券'!$B$5:$B$404=$D17)*('債券'!$Y$5:$Y$404=1)*'債券'!$AV$5:$AV$404),"")) | X17: =IF($D17="","",IFERROR(AVERAGEIFS('債券'!$AQ$5:$AQ$404,'債券'!$B$5:$B$404,$D17,'債券'!$Y$5:$Y$404,1),"")) | Y17: =IF($D17="","",COUNTIFS('債券'!$B$5:$B$404,$D17,'債券'!$AS$5:$AS$404,"加碼候選")) | Z17: =IF($D17="","",COUNTIFS('債券'!$B$5:$B$404,$D17,'債券'!$AS$5:$AS$404,"減碼候選"))
A18: 半導體 | B18: Marvell | C18: MRVL US Equity | D18: MRVL | F18: =IF($C18="","",BDP($C18,F$3)) | G18: =IF($C18="","",BDP($C18,G$3)) | H18: =IF($C18="","",BDP($C18,H$3)) | I18: =IF($C18="","",BDP($C18,I$3,"EQY_FUND_CRNCY","USD")) | J18: =IF($C18="","",BDP($C18,J$3,"EQY_FUND_CRNCY","USD")) | K18: =IF($C18="","",BDP($C18,K$3,"EQY_FUND_CRNCY","USD")) | L18: =IF($C18="","",BDP($C18,L$3,"EQY_FUND_CRNCY","USD")) | M18: =IF($C18="","",BDP($C18,M$3,"EQY_FUND_CRNCY","USD")) | N18: =IF($C18="","",BDP($C18,N$3,"EQY_FUND_CRNCY","USD")) | O18: =IF($C18="","",BDP($C18,O$3)) | P18: =IF(LEFT($O18,1)="#","",IF($O18="","",BDP($O18,P$3))) | Q18: =IF(AND(ISNUMBER($M18),ISNUMBER($N18)),IF($N18>0,$M18/$N18,""),"") | R18: =IF(AND(ISNUMBER($J18),ISNUMBER($I18)),IF($I18>0,ABS($J18)/$I18,""),"") | S18: =IF(AND(ISNUMBER($K18),ISNUMBER($L18)),IF($L18>0,$K18/$L18,""),"") | T18: =IF($D18="","",COUNTIFS('債券'!$B$5:$B$404,$D18,'債券'!$Y$5:$Y$404,1)) | U18: =IF($D18="","",SUMPRODUCT(('債券'!$B$5:$B$404=$D18)*('債券'!$Y$5:$Y$404=1)*'債券'!$AV$5:$AV$404)/1E6) | V18: =IF($D18="","",IF(SUMPRODUCT(('債券'!$B$5:$B$404=$D18)*('債券'!$Y$5:$Y$404=1)*'債券'!$AV$5:$AV$404)>0,SUMPRODUCT(('債券'!$B$5:$B$404=$D18)*('債券'!$Y$5:$Y$404=1)*'債券'!$AV$5:$AV$404*'債券'!$AT$5:$AT$404)/SUMPRODUCT(('債券'!$B$5:$B$404=$D18)*('債券'!$Y$5:$Y$404=1)*'債券'!$AV$5:$AV$404),"")) | W18: =IF($D18="","",IF(SUMPRODUCT(('債券'!$B$5:$B$404=$D18)*('債券'!$Y$5:$Y$404=1)*'債券'!$AV$5:$AV$404)>0,SUMPRODUCT(('債券'!$B$5:$B$404=$D18)*('債券'!$Y$5:$Y$404=1)*'債券'!$AV$5:$AV$404*'債券'!$AW$5:$AW$404)/SUMPRODUCT(('債券'!$B$5:$B$404=$D18)*('債券'!$Y$5:$Y$404=1)*'債券'!$AV$5:$AV$404),"")) | X18: =IF($D18="","",IFERROR(AVERAGEIFS('債券'!$AQ$5:$AQ$404,'債券'!$B$5:$B$404,$D18,'債券'!$Y$5:$Y$404,1),"")) | Y18: =IF($D18="","",COUNTIFS('債券'!$B$5:$B$404,$D18,'債券'!$AS$5:$AS$404,"加碼候選")) | Z18: =IF($D18="","",COUNTIFS('債券'!$B$5:$B$404,$D18,'債券'!$AS$5:$AS$404,"減碼候選"))
A19: 半導體 | B19: Applied Materials | C19: AMAT US Equity | D19: AMAT | E19: 半導體設備 | F19: =IF($C19="","",BDP($C19,F$3)) | G19: =IF($C19="","",BDP($C19,G$3)) | H19: =IF($C19="","",BDP($C19,H$3)) | I19: =IF($C19="","",BDP($C19,I$3,"EQY_FUND_CRNCY","USD")) | J19: =IF($C19="","",BDP($C19,J$3,"EQY_FUND_CRNCY","USD")) | K19: =IF($C19="","",BDP($C19,K$3,"EQY_FUND_CRNCY","USD")) | L19: =IF($C19="","",BDP($C19,L$3,"EQY_FUND_CRNCY","USD")) | M19: =IF($C19="","",BDP($C19,M$3,"EQY_FUND_CRNCY","USD")) | N19: =IF($C19="","",BDP($C19,N$3,"EQY_FUND_CRNCY","USD")) | O19: =IF($C19="","",BDP($C19,O$3)) | P19: =IF(LEFT($O19,1)="#","",IF($O19="","",BDP($O19,P$3))) | Q19: =IF(AND(ISNUMBER($M19),ISNUMBER($N19)),IF($N19>0,$M19/$N19,""),"") | R19: =IF(AND(ISNUMBER($J19),ISNUMBER($I19)),IF($I19>0,ABS($J19)/$I19,""),"") | S19: =IF(AND(ISNUMBER($K19),ISNUMBER($L19)),IF($L19>0,$K19/$L19,""),"") | T19: =IF($D19="","",COUNTIFS('債券'!$B$5:$B$404,$D19,'債券'!$Y$5:$Y$404,1)) | U19: =IF($D19="","",SUMPRODUCT(('債券'!$B$5:$B$404=$D19)*('債券'!$Y$5:$Y$404=1)*'債券'!$AV$5:$AV$404)/1E6) | V19: =IF($D19="","",IF(SUMPRODUCT(('債券'!$B$5:$B$404=$D19)*('債券'!$Y$5:$Y$404=1)*'債券'!$AV$5:$AV$404)>0,SUMPRODUCT(('債券'!$B$5:$B$404=$D19)*('債券'!$Y$5:$Y$404=1)*'債券'!$AV$5:$AV$404*'債券'!$AT$5:$AT$404)/SUMPRODUCT(('債券'!$B$5:$B$404=$D19)*('債券'!$Y$5:$Y$404=1)*'債券'!$AV$5:$AV$404),"")) | W19: =IF($D19="","",IF(SUMPRODUCT(('債券'!$B$5:$B$404=$D19)*('債券'!$Y$5:$Y$404=1)*'債券'!$AV$5:$AV$404)>0,SUMPRODUCT(('債券'!$B$5:$B$404=$D19)*('債券'!$Y$5:$Y$404=1)*'債券'!$AV$5:$AV$404*'債券'!$AW$5:$AW$404)/SUMPRODUCT(('債券'!$B$5:$B$404=$D19)*('債券'!$Y$5:$Y$404=1)*'債券'!$AV$5:$AV$404),"")) | X19: =IF($D19="","",IFERROR(AVERAGEIFS('債券'!$AQ$5:$AQ$404,'債券'!$B$5:$B$404,$D19,'債券'!$Y$5:$Y$404,1),"")) | Y19: =IF($D19="","",COUNTIFS('債券'!$B$5:$B$404,$D19,'債券'!$AS$5:$AS$404,"加碼候選")) | Z19: =IF($D19="","",COUNTIFS('債券'!$B$5:$B$404,$D19,'債券'!$AS$5:$AS$404,"減碼候選"))
A20: 半導體 | B20: TSMC | C20: 2330 TT Equity | D20: 請確認 | E20: 美元債由海外子公司發行，財報為台幣（已用美元覆寫） | F20: =IF($C20="","",BDP($C20,F$3)) | G20: =IF($C20="","",BDP($C20,G$3)) | H20: =IF($C20="","",BDP($C20,H$3)) | I20: =IF($C20="","",BDP($C20,I$3,"EQY_FUND_CRNCY","USD")) | J20: =IF($C20="","",BDP($C20,J$3,"EQY_FUND_CRNCY","USD")) | K20: =IF($C20="","",BDP($C20,K$3,"EQY_FUND_CRNCY","USD")) | L20: =IF($C20="","",BDP($C20,L$3,"EQY_FUND_CRNCY","USD")) | M20: =IF($C20="","",BDP($C20,M$3,"EQY_FUND_CRNCY","USD")) | N20: =IF($C20="","",BDP($C20,N$3,"EQY_FUND_CRNCY","USD")) | O20: =IF($C20="","",BDP($C20,O$3)) | P20: =IF(LEFT($O20,1)="#","",IF($O20="","",BDP($O20,P$3))) | Q20: =IF(AND(ISNUMBER($M20),ISNUMBER($N20)),IF($N20>0,$M20/$N20,""),"") | R20: =IF(AND(ISNUMBER($J20),ISNUMBER($I20)),IF($I20>0,ABS($J20)/$I20,""),"") | S20: =IF(AND(ISNUMBER($K20),ISNUMBER($L20)),IF($L20>0,$K20/$L20,""),"") | T20: =IF($D20="","",COUNTIFS('債券'!$B$5:$B$404,$D20,'債券'!$Y$5:$Y$404,1)) | U20: =IF($D20="","",SUMPRODUCT(('債券'!$B$5:$B$404=$D20)*('債券'!$Y$5:$Y$404=1)*'債券'!$AV$5:$AV$404)/1E6) | V20: =IF($D20="","",IF(SUMPRODUCT(('債券'!$B$5:$B$404=$D20)*('債券'!$Y$5:$Y$404=1)*'債券'!$AV$5:$AV$404)>0,SUMPRODUCT(('債券'!$B$5:$B$404=$D20)*('債券'!$Y$5:$Y$404=1)*'債券'!$AV$5:$AV$404*'債券'!$AT$5:$AT$404)/SUMPRODUCT(('債券'!$B$5:$B$404=$D20)*('債券'!$Y$5:$Y$404=1)*'債券'!$AV$5:$AV$404),"")) | W20: =IF($D20="","",IF(SUMPRODUCT(('債券'!$B$5:$B$404=$D20)*('債券'!$Y$5:$Y$404=1)*'債券'!$AV$5:$AV$404)>0,SUMPRODUCT(('債券'!$B$5:$B$404=$D20)*('債券'!$Y$5:$Y$404=1)*'債券'!$AV$5:$AV$404*'債券'!$AW$5:$AW$404)/SUMPRODUCT(('債券'!$B$5:$B$404=$D20)*('債券'!$Y$5:$Y$404=1)*'債券'!$AV$5:$AV$404),"")) | X20: =IF($D20="","",IFERROR(AVERAGEIFS('債券'!$AQ$5:$AQ$404,'債券'!$B$5:$B$404,$D20,'債券'!$Y$5:$Y$404,1),"")) | Y20: =IF($D20="","",COUNTIFS('債券'!$B$5:$B$404,$D20,'債券'!$AS$5:$AS$404,"加碼候選")) | Z20: =IF($D20="","",COUNTIFS('債券'!$B$5:$B$404,$D20,'債券'!$AS$5:$AS$404,"減碼候選"))
A21: 半導體 | B21: SK hynix | C21: 000660 KS Equity | D21: 請確認 | E21: 財報為韓元（已用美元覆寫） | F21: =IF($C21="","",BDP($C21,F$3)) | G21: =IF($C21="","",BDP($C21,G$3)) | H21: =IF($C21="","",BDP($C21,H$3)) | I21: =IF($C21="","",BDP($C21,I$3,"EQY_FUND_CRNCY","USD")) | J21: =IF($C21="","",BDP($C21,J$3,"EQY_FUND_CRNCY","USD")) | K21: =IF($C21="","",BDP($C21,K$3,"EQY_FUND_CRNCY","USD")) | L21: =IF($C21="","",BDP($C21,L$3,"EQY_FUND_CRNCY","USD")) | M21: =IF($C21="","",BDP($C21,M$3,"EQY_FUND_CRNCY","USD")) | N21: =IF($C21="","",BDP($C21,N$3,"EQY_FUND_CRNCY","USD")) | O21: =IF($C21="","",BDP($C21,O$3)) | P21: =IF(LEFT($O21,1)="#","",IF($O21="","",BDP($O21,P$3))) | Q21: =IF(AND(ISNUMBER($M21),ISNUMBER($N21)),IF($N21>0,$M21/$N21,""),"") | R21: =IF(AND(ISNUMBER($J21),ISNUMBER($I21)),IF($I21>0,ABS($J21)/$I21,""),"") | S21: =IF(AND(ISNUMBER($K21),ISNUMBER($L21)),IF($L21>0,$K21/$L21,""),"") | T21: =IF($D21="","",COUNTIFS('債券'!$B$5:$B$404,$D21,'債券'!$Y$5:$Y$404,1)) | U21: =IF($D21="","",SUMPRODUCT(('債券'!$B$5:$B$404=$D21)*('債券'!$Y$5:$Y$404=1)*'債券'!$AV$5:$AV$404)/1E6) | V21: =IF($D21="","",IF(SUMPRODUCT(('債券'!$B$5:$B$404=$D21)*('債券'!$Y$5:$Y$404=1)*'債券'!$AV$5:$AV$404)>0,SUMPRODUCT(('債券'!$B$5:$B$404=$D21)*('債券'!$Y$5:$Y$404=1)*'債券'!$AV$5:$AV$404*'債券'!$AT$5:$AT$404)/SUMPRODUCT(('債券'!$B$5:$B$404=$D21)*('債券'!$Y$5:$Y$404=1)*'債券'!$AV$5:$AV$404),"")) | W21: =IF($D21="","",IF(SUMPRODUCT(('債券'!$B$5:$B$404=$D21)*('債券'!$Y$5:$Y$404=1)*'債券'!$AV$5:$AV$404)>0,SUMPRODUCT(('債券'!$B$5:$B$404=$D21)*('債券'!$Y$5:$Y$404=1)*'債券'!$AV$5:$AV$404*'債券'!$AW$5:$AW$404)/SUMPRODUCT(('債券'!$B$5:$B$404=$D21)*('債券'!$Y$5:$Y$404=1)*'債券'!$AV$5:$AV$404),"")) | X21: =IF($D21="","",IFERROR(AVERAGEIFS('債券'!$AQ$5:$AQ$404,'債券'!$B$5:$B$404,$D21,'債券'!$Y$5:$Y$404,1),"")) | Y21: =IF($D21="","",COUNTIFS('債券'!$B$5:$B$404,$D21,'債券'!$AS$5:$AS$404,"加碼候選")) | Z21: =IF($D21="","",COUNTIFS('債券'!$B$5:$B$404,$D21,'債券'!$AS$5:$AS$404,"減碼候選"))
A22: 伺服器／網通 | B22: Cisco | C22: CSCO US Equity | D22: CSCO | F22: =IF($C22="","",BDP($C22,F$3)) | G22: =IF($C22="","",BDP($C22,G$3)) | H22: =IF($C22="","",BDP($C22,H$3)) | I22: =IF($C22="","",BDP($C22,I$3,"EQY_FUND_CRNCY","USD")) | J22: =IF($C22="","",BDP($C22,J$3,"EQY_FUND_CRNCY","USD")) | K22: =IF($C22="","",BDP($C22,K$3,"EQY_FUND_CRNCY","USD")) | L22: =IF($C22="","",BDP($C22,L$3,"EQY_FUND_CRNCY","USD")) | M22: =IF($C22="","",BDP($C22,M$3,"EQY_FUND_CRNCY","USD")) | N22: =IF($C22="","",BDP($C22,N$3,"EQY_FUND_CRNCY","USD")) | O22: =IF($C22="","",BDP($C22,O$3)) | P22: =IF(LEFT($O22,1)="#","",IF($O22="","",BDP($O22,P$3))) | Q22: =IF(AND(ISNUMBER($M22),ISNUMBER($N22)),IF($N22>0,$M22/$N22,""),"") | R22: =IF(AND(ISNUMBER($J22),ISNUMBER($I22)),IF($I22>0,ABS($J22)/$I22,""),"") | S22: =IF(AND(ISNUMBER($K22),ISNUMBER($L22)),IF($L22>0,$K22/$L22,""),"") | T22: =IF($D22="","",COUNTIFS('債券'!$B$5:$B$404,$D22,'債券'!$Y$5:$Y$404,1)) | U22: =IF($D22="","",SUMPRODUCT(('債券'!$B$5:$B$404=$D22)*('債券'!$Y$5:$Y$404=1)*'債券'!$AV$5:$AV$404)/1E6) | V22: =IF($D22="","",IF(SUMPRODUCT(('債券'!$B$5:$B$404=$D22)*('債券'!$Y$5:$Y$404=1)*'債券'!$AV$5:$AV$404)>0,SUMPRODUCT(('債券'!$B$5:$B$404=$D22)*('債券'!$Y$5:$Y$404=1)*'債券'!$AV$5:$AV$404*'債券'!$AT$5:$AT$404)/SUMPRODUCT(('債券'!$B$5:$B$404=$D22)*('債券'!$Y$5:$Y$404=1)*'債券'!$AV$5:$AV$404),"")) | W22: =IF($D22="","",IF(SUMPRODUCT(('債券'!$B$5:$B$404=$D22)*('債券'!$Y$5:$Y$404=1)*'債券'!$AV$5:$AV$404)>0,SUMPRODUCT(('債券'!$B$5:$B$404=$D22)*('債券'!$Y$5:$Y$404=1)*'債券'!$AV$5:$AV$404*'債券'!$AW$5:$AW$404)/SUMPRODUCT(('債券'!$B$5:$B$404=$D22)*('債券'!$Y$5:$Y$404=1)*'債券'!$AV$5:$AV$404),"")) | X22: =IF($D22="","",IFERROR(AVERAGEIFS('債券'!$AQ$5:$AQ$404,'債券'!$B$5:$B$404,$D22,'債券'!$Y$5:$Y$404,1),"")) | Y22: =IF($D22="","",COUNTIFS('債券'!$B$5:$B$404,$D22,'債券'!$AS$5:$AS$404,"加碼候選")) | Z22: =IF($D22="","",COUNTIFS('債券'!$B$5:$B$404,$D22,'債券'!$AS$5:$AS$404,"減碼候選"))
A23: 伺服器／網通 | B23: Dell Technologies | C23: DELL US Equity | D23: DELL | E23: AI 伺服器 | F23: =IF($C23="","",BDP($C23,F$3)) | G23: =IF($C23="","",BDP($C23,G$3)) | H23: =IF($C23="","",BDP($C23,H$3)) | I23: =IF($C23="","",BDP($C23,I$3,"EQY_FUND_CRNCY","USD")) | J23: =IF($C23="","",BDP($C23,J$3,"EQY_FUND_CRNCY","USD")) | K23: =IF($C23="","",BDP($C23,K$3,"EQY_FUND_CRNCY","USD")) | L23: =IF($C23="","",BDP($C23,L$3,"EQY_FUND_CRNCY","USD")) | M23: =IF($C23="","",BDP($C23,M$3,"EQY_FUND_CRNCY","USD")) | N23: =IF($C23="","",BDP($C23,N$3,"EQY_FUND_CRNCY","USD")) | O23: =IF($C23="","",BDP($C23,O$3)) | P23: =IF(LEFT($O23,1)="#","",IF($O23="","",BDP($O23,P$3))) | Q23: =IF(AND(ISNUMBER($M23),ISNUMBER($N23)),IF($N23>0,$M23/$N23,""),"") | R23: =IF(AND(ISNUMBER($J23),ISNUMBER($I23)),IF($I23>0,ABS($J23)/$I23,""),"") | S23: =IF(AND(ISNUMBER($K23),ISNUMBER($L23)),IF($L23>0,$K23/$L23,""),"") | T23: =IF($D23="","",COUNTIFS('債券'!$B$5:$B$404,$D23,'債券'!$Y$5:$Y$404,1)) | U23: =IF($D23="","",SUMPRODUCT(('債券'!$B$5:$B$404=$D23)*('債券'!$Y$5:$Y$404=1)*'債券'!$AV$5:$AV$404)/1E6) | V23: =IF($D23="","",IF(SUMPRODUCT(('債券'!$B$5:$B$404=$D23)*('債券'!$Y$5:$Y$404=1)*'債券'!$AV$5:$AV$404)>0,SUMPRODUCT(('債券'!$B$5:$B$404=$D23)*('債券'!$Y$5:$Y$404=1)*'債券'!$AV$5:$AV$404*'債券'!$AT$5:$AT$404)/SUMPRODUCT(('債券'!$B$5:$B$404=$D23)*('債券'!$Y$5:$Y$404=1)*'債券'!$AV$5:$AV$404),"")) | W23: =IF($D23="","",IF(SUMPRODUCT(('債券'!$B$5:$B$404=$D23)*('債券'!$Y$5:$Y$404=1)*'債券'!$AV$5:$AV$404)>0,SUMPRODUCT(('債券'!$B$5:$B$404=$D23)*('債券'!$Y$5:$Y$404=1)*'債券'!$AV$5:$AV$404*'債券'!$AW$5:$AW$404)/SUMPRODUCT(('債券'!$B$5:$B$404=$D23)*('債券'!$Y$5:$Y$404=1)*'債券'!$AV$5:$AV$404),"")) | X23: =IF($D23="","",IFERROR(AVERAGEIFS('債券'!$AQ$5:$AQ$404,'債券'!$B$5:$B$404,$D23,'債券'!$Y$5:$Y$404,1),"")) | Y23: =IF($D23="","",COUNTIFS('債券'!$B$5:$B$404,$D23,'債券'!$AS$5:$AS$404,"加碼候選")) | Z23: =IF($D23="","",COUNTIFS('債券'!$B$5:$B$404,$D23,'債券'!$AS$5:$AS$404,"減碼候選"))
A24: 伺服器／網通 | B24: Hewlett Packard Enterprise | C24: HPE US Equity | D24: HPE | F24: =IF($C24="","",BDP($C24,F$3)) | G24: =IF($C24="","",BDP($C24,G$3)) | H24: =IF($C24="","",BDP($C24,H$3)) | I24: =IF($C24="","",BDP($C24,I$3,"EQY_FUND_CRNCY","USD")) | J24: =IF($C24="","",BDP($C24,J$3,"EQY_FUND_CRNCY","USD")) | K24: =IF($C24="","",BDP($C24,K$3,"EQY_FUND_CRNCY","USD")) | L24: =IF($C24="","",BDP($C24,L$3,"EQY_FUND_CRNCY","USD")) | M24: =IF($C24="","",BDP($C24,M$3,"EQY_FUND_CRNCY","USD")) | N24: =IF($C24="","",BDP($C24,N$3,"EQY_FUND_CRNCY","USD")) | O24: =IF($C24="","",BDP($C24,O$3)) | P24: =IF(LEFT($O24,1)="#","",IF($O24="","",BDP($O24,P$3))) | Q24: =IF(AND(ISNUMBER($M24),ISNUMBER($N24)),IF($N24>0,$M24/$N24,""),"") | R24: =IF(AND(ISNUMBER($J24),ISNUMBER($I24)),IF($I24>0,ABS($J24)/$I24,""),"") | S24: =IF(AND(ISNUMBER($K24),ISNUMBER($L24)),IF($L24>0,$K24/$L24,""),"") | T24: =IF($D24="","",COUNTIFS('債券'!$B$5:$B$404,$D24,'債券'!$Y$5:$Y$404,1)) | U24: =IF($D24="","",SUMPRODUCT(('債券'!$B$5:$B$404=$D24)*('債券'!$Y$5:$Y$404=1)*'債券'!$AV$5:$AV$404)/1E6) | V24: =IF($D24="","",IF(SUMPRODUCT(('債券'!$B$5:$B$404=$D24)*('債券'!$Y$5:$Y$404=1)*'債券'!$AV$5:$AV$404)>0,SUMPRODUCT(('債券'!$B$5:$B$404=$D24)*('債券'!$Y$5:$Y$404=1)*'債券'!$AV$5:$AV$404*'債券'!$AT$5:$AT$404)/SUMPRODUCT(('債券'!$B$5:$B$404=$D24)*('債券'!$Y$5:$Y$404=1)*'債券'!$AV$5:$AV$404),"")) | W24: =IF($D24="","",IF(SUMPRODUCT(('債券'!$B$5:$B$404=$D24)*('債券'!$Y$5:$Y$404=1)*'債券'!$AV$5:$AV$404)>0,SUMPRODUCT(('債券'!$B$5:$B$404=$D24)*('債券'!$Y$5:$Y$404=1)*'債券'!$AV$5:$AV$404*'債券'!$AW$5:$AW$404)/SUMPRODUCT(('債券'!$B$5:$B$404=$D24)*('債券'!$Y$5:$Y$404=1)*'債券'!$AV$5:$AV$404),"")) | X24: =IF($D24="","",IFERROR(AVERAGEIFS('債券'!$AQ$5:$AQ$404,'債券'!$B$5:$B$404,$D24,'債券'!$Y$5:$Y$404,1),"")) | Y24: =IF($D24="","",COUNTIFS('債券'!$B$5:$B$404,$D24,'債券'!$AS$5:$AS$404,"加碼候選")) | Z24: =IF($D24="","",COUNTIFS('債券'!$B$5:$B$404,$D24,'債券'!$AS$5:$AS$404,"減碼候選"))
A25: 軟體 | B25: Salesforce | C25: CRM US Equity | D25: CRM | F25: =IF($C25="","",BDP($C25,F$3)) | G25: =IF($C25="","",BDP($C25,G$3)) | H25: =IF($C25="","",BDP($C25,H$3)) | I25: =IF($C25="","",BDP($C25,I$3,"EQY_FUND_CRNCY","USD")) | J25: =IF($C25="","",BDP($C25,J$3,"EQY_FUND_CRNCY","USD")) | K25: =IF($C25="","",BDP($C25,K$3,"EQY_FUND_CRNCY","USD")) | L25: =IF($C25="","",BDP($C25,L$3,"EQY_FUND_CRNCY","USD")) | M25: =IF($C25="","",BDP($C25,M$3,"EQY_FUND_CRNCY","USD")) | N25: =IF($C25="","",BDP($C25,N$3,"EQY_FUND_CRNCY","USD")) | O25: =IF($C25="","",BDP($C25,O$3)) | P25: =IF(LEFT($O25,1)="#","",IF($O25="","",BDP($O25,P$3))) | Q25: =IF(AND(ISNUMBER($M25),ISNUMBER($N25)),IF($N25>0,$M25/$N25,""),"") | R25: =IF(AND(ISNUMBER($J25),ISNUMBER($I25)),IF($I25>0,ABS($J25)/$I25,""),"") | S25: =IF(AND(ISNUMBER($K25),ISNUMBER($L25)),IF($L25>0,$K25/$L25,""),"") | T25: =IF($D25="","",COUNTIFS('債券'!$B$5:$B$404,$D25,'債券'!$Y$5:$Y$404,1)) | U25: =IF($D25="","",SUMPRODUCT(('債券'!$B$5:$B$404=$D25)*('債券'!$Y$5:$Y$404=1)*'債券'!$AV$5:$AV$404)/1E6) | V25: =IF($D25="","",IF(SUMPRODUCT(('債券'!$B$5:$B$404=$D25)*('債券'!$Y$5:$Y$404=1)*'債券'!$AV$5:$AV$404)>0,SUMPRODUCT(('債券'!$B$5:$B$404=$D25)*('債券'!$Y$5:$Y$404=1)*'債券'!$AV$5:$AV$404*'債券'!$AT$5:$AT$404)/SUMPRODUCT(('債券'!$B$5:$B$404=$D25)*('債券'!$Y$5:$Y$404=1)*'債券'!$AV$5:$AV$404),"")) | W25: =IF($D25="","",IF(SUMPRODUCT(('債券'!$B$5:$B$404=$D25)*('債券'!$Y$5:$Y$404=1)*'債券'!$AV$5:$AV$404)>0,SUMPRODUCT(('債券'!$B$5:$B$404=$D25)*('債券'!$Y$5:$Y$404=1)*'債券'!$AV$5:$AV$404*'債券'!$AW$5:$AW$404)/SUMPRODUCT(('債券'!$B$5:$B$404=$D25)*('債券'!$Y$5:$Y$404=1)*'債券'!$AV$5:$AV$404),"")) | X25: =IF($D25="","",IFERROR(AVERAGEIFS('債券'!$AQ$5:$AQ$404,'債券'!$B$5:$B$404,$D25,'債券'!$Y$5:$Y$404,1),"")) | Y25: =IF($D25="","",COUNTIFS('債券'!$B$5:$B$404,$D25,'債券'!$AS$5:$AS$404,"加碼候選")) | Z25: =IF($D25="","",COUNTIFS('債券'!$B$5:$B$404,$D25,'債券'!$AS$5:$AS$404,"減碼候選"))
A26: 資料中心 | B26: Equinix | C26: EQIX US Equity | D26: EQIX | E26: REIT | F26: =IF($C26="","",BDP($C26,F$3)) | G26: =IF($C26="","",BDP($C26,G$3)) | H26: =IF($C26="","",BDP($C26,H$3)) | I26: =IF($C26="","",BDP($C26,I$3,"EQY_FUND_CRNCY","USD")) | J26: =IF($C26="","",BDP($C26,J$3,"EQY_FUND_CRNCY","USD")) | K26: =IF($C26="","",BDP($C26,K$3,"EQY_FUND_CRNCY","USD")) | L26: =IF($C26="","",BDP($C26,L$3,"EQY_FUND_CRNCY","USD")) | M26: =IF($C26="","",BDP($C26,M$3,"EQY_FUND_CRNCY","USD")) | N26: =IF($C26="","",BDP($C26,N$3,"EQY_FUND_CRNCY","USD")) | O26: =IF($C26="","",BDP($C26,O$3)) | P26: =IF(LEFT($O26,1)="#","",IF($O26="","",BDP($O26,P$3))) | Q26: =IF(AND(ISNUMBER($M26),ISNUMBER($N26)),IF($N26>0,$M26/$N26,""),"") | R26: =IF(AND(ISNUMBER($J26),ISNUMBER($I26)),IF($I26>0,ABS($J26)/$I26,""),"") | S26: =IF(AND(ISNUMBER($K26),ISNUMBER($L26)),IF($L26>0,$K26/$L26,""),"") | T26: =IF($D26="","",COUNTIFS('債券'!$B$5:$B$404,$D26,'債券'!$Y$5:$Y$404,1)) | U26: =IF($D26="","",SUMPRODUCT(('債券'!$B$5:$B$404=$D26)*('債券'!$Y$5:$Y$404=1)*'債券'!$AV$5:$AV$404)/1E6) | V26: =IF($D26="","",IF(SUMPRODUCT(('債券'!$B$5:$B$404=$D26)*('債券'!$Y$5:$Y$404=1)*'債券'!$AV$5:$AV$404)>0,SUMPRODUCT(('債券'!$B$5:$B$404=$D26)*('債券'!$Y$5:$Y$404=1)*'債券'!$AV$5:$AV$404*'債券'!$AT$5:$AT$404)/SUMPRODUCT(('債券'!$B$5:$B$404=$D26)*('債券'!$Y$5:$Y$404=1)*'債券'!$AV$5:$AV$404),"")) | W26: =IF($D26="","",IF(SUMPRODUCT(('債券'!$B$5:$B$404=$D26)*('債券'!$Y$5:$Y$404=1)*'債券'!$AV$5:$AV$404)>0,SUMPRODUCT(('債券'!$B$5:$B$404=$D26)*('債券'!$Y$5:$Y$404=1)*'債券'!$AV$5:$AV$404*'債券'!$AW$5:$AW$404)/SUMPRODUCT(('債券'!$B$5:$B$404=$D26)*('債券'!$Y$5:$Y$404=1)*'債券'!$AV$5:$AV$404),"")) | X26: =IF($D26="","",IFERROR(AVERAGEIFS('債券'!$AQ$5:$AQ$404,'債券'!$B$5:$B$404,$D26,'債券'!$Y$5:$Y$404,1),"")) | Y26: =IF($D26="","",COUNTIFS('債券'!$B$5:$B$404,$D26,'債券'!$AS$5:$AS$404,"加碼候選")) | Z26: =IF($D26="","",COUNTIFS('債券'!$B$5:$B$404,$D26,'債券'!$AS$5:$AS$404,"減碼候選"))
A27: 資料中心 | B27: Digital Realty | C27: DLR US Equity | D27: DLR | E27: REIT | F27: =IF($C27="","",BDP($C27,F$3)) | G27: =IF($C27="","",BDP($C27,G$3)) | H27: =IF($C27="","",BDP($C27,H$3)) | I27: =IF($C27="","",BDP($C27,I$3,"EQY_FUND_CRNCY","USD")) | J27: =IF($C27="","",BDP($C27,J$3,"EQY_FUND_CRNCY","USD")) | K27: =IF($C27="","",BDP($C27,K$3,"EQY_FUND_CRNCY","USD")) | L27: =IF($C27="","",BDP($C27,L$3,"EQY_FUND_CRNCY","USD")) | M27: =IF($C27="","",BDP($C27,M$3,"EQY_FUND_CRNCY","USD")) | N27: =IF($C27="","",BDP($C27,N$3,"EQY_FUND_CRNCY","USD")) | O27: =IF($C27="","",BDP($C27,O$3)) | P27: =IF(LEFT($O27,1)="#","",IF($O27="","",BDP($O27,P$3))) | Q27: =IF(AND(ISNUMBER($M27),ISNUMBER($N27)),IF($N27>0,$M27/$N27,""),"") | R27: =IF(AND(ISNUMBER($J27),ISNUMBER($I27)),IF($I27>0,ABS($J27)/$I27,""),"") | S27: =IF(AND(ISNUMBER($K27),ISNUMBER($L27)),IF($L27>0,$K27/$L27,""),"") | T27: =IF($D27="","",COUNTIFS('債券'!$B$5:$B$404,$D27,'債券'!$Y$5:$Y$404,1)) | U27: =IF($D27="","",SUMPRODUCT(('債券'!$B$5:$B$404=$D27)*('債券'!$Y$5:$Y$404=1)*'債券'!$AV$5:$AV$404)/1E6) | V27: =IF($D27="","",IF(SUMPRODUCT(('債券'!$B$5:$B$404=$D27)*('債券'!$Y$5:$Y$404=1)*'債券'!$AV$5:$AV$404)>0,SUMPRODUCT(('債券'!$B$5:$B$404=$D27)*('債券'!$Y$5:$Y$404=1)*'債券'!$AV$5:$AV$404*'債券'!$AT$5:$AT$404)/SUMPRODUCT(('債券'!$B$5:$B$404=$D27)*('債券'!$Y$5:$Y$404=1)*'債券'!$AV$5:$AV$404),"")) | W27: =IF($D27="","",IF(SUMPRODUCT(('債券'!$B$5:$B$404=$D27)*('債券'!$Y$5:$Y$404=1)*'債券'!$AV$5:$AV$404)>0,SUMPRODUCT(('債券'!$B$5:$B$404=$D27)*('債券'!$Y$5:$Y$404=1)*'債券'!$AV$5:$AV$404*'債券'!$AW$5:$AW$404)/SUMPRODUCT(('債券'!$B$5:$B$404=$D27)*('債券'!$Y$5:$Y$404=1)*'債券'!$AV$5:$AV$404),"")) | X27: =IF($D27="","",IFERROR(AVERAGEIFS('債券'!$AQ$5:$AQ$404,'債券'!$B$5:$B$404,$D27,'債券'!$Y$5:$Y$404,1),"")) | Y27: =IF($D27="","",COUNTIFS('債券'!$B$5:$B$404,$D27,'債券'!$AS$5:$AS$404,"加碼候選")) | Z27: =IF($D27="","",COUNTIFS('債券'!$B$5:$B$404,$D27,'債券'!$AS$5:$AS$404,"減碼候選"))
A28: AI 雲端（高收益） | B28: CoreWeave | C28: CRWV US Equity | D28: 請確認 | E28: 高收益，債務以 GPU 擔保融資為主 | F28: =IF($C28="","",BDP($C28,F$3)) | G28: =IF($C28="","",BDP($C28,G$3)) | H28: =IF($C28="","",BDP($C28,H$3)) | I28: =IF($C28="","",BDP($C28,I$3,"EQY_FUND_CRNCY","USD")) | J28: =IF($C28="","",BDP($C28,J$3,"EQY_FUND_CRNCY","USD")) | K28: =IF($C28="","",BDP($C28,K$3,"EQY_FUND_CRNCY","USD")) | L28: =IF($C28="","",BDP($C28,L$3,"EQY_FUND_CRNCY","USD")) | M28: =IF($C28="","",BDP($C28,M$3,"EQY_FUND_CRNCY","USD")) | N28: =IF($C28="","",BDP($C28,N$3,"EQY_FUND_CRNCY","USD")) | O28: =IF($C28="","",BDP($C28,O$3)) | P28: =IF(LEFT($O28,1)="#","",IF($O28="","",BDP($O28,P$3))) | Q28: =IF(AND(ISNUMBER($M28),ISNUMBER($N28)),IF($N28>0,$M28/$N28,""),"") | R28: =IF(AND(ISNUMBER($J28),ISNUMBER($I28)),IF($I28>0,ABS($J28)/$I28,""),"") | S28: =IF(AND(ISNUMBER($K28),ISNUMBER($L28)),IF($L28>0,$K28/$L28,""),"") | T28: =IF($D28="","",COUNTIFS('債券'!$B$5:$B$404,$D28,'債券'!$Y$5:$Y$404,1)) | U28: =IF($D28="","",SUMPRODUCT(('債券'!$B$5:$B$404=$D28)*('債券'!$Y$5:$Y$404=1)*'債券'!$AV$5:$AV$404)/1E6) | V28: =IF($D28="","",IF(SUMPRODUCT(('債券'!$B$5:$B$404=$D28)*('債券'!$Y$5:$Y$404=1)*'債券'!$AV$5:$AV$404)>0,SUMPRODUCT(('債券'!$B$5:$B$404=$D28)*('債券'!$Y$5:$Y$404=1)*'債券'!$AV$5:$AV$404*'債券'!$AT$5:$AT$404)/SUMPRODUCT(('債券'!$B$5:$B$404=$D28)*('債券'!$Y$5:$Y$404=1)*'債券'!$AV$5:$AV$404),"")) | W28: =IF($D28="","",IF(SUMPRODUCT(('債券'!$B$5:$B$404=$D28)*('債券'!$Y$5:$Y$404=1)*'債券'!$AV$5:$AV$404)>0,SUMPRODUCT(('債券'!$B$5:$B$404=$D28)*('債券'!$Y$5:$Y$404=1)*'債券'!$AV$5:$AV$404*'債券'!$AW$5:$AW$404)/SUMPRODUCT(('債券'!$B$5:$B$404=$D28)*('債券'!$Y$5:$Y$404=1)*'債券'!$AV$5:$AV$404),"")) | X28: =IF($D28="","",IFERROR(AVERAGEIFS('債券'!$AQ$5:$AQ$404,'債券'!$B$5:$B$404,$D28,'債券'!$Y$5:$Y$404,1),"")) | Y28: =IF($D28="","",COUNTIFS('債券'!$B$5:$B$404,$D28,'債券'!$AS$5:$AS$404,"加碼候選")) | Z28: =IF($D28="","",COUNTIFS('債券'!$B$5:$B$404,$D28,'債券'!$AS$5:$AS$404,"減碼候選"))
F29: =IF($C29="","",BDP($C29,F$3)) | G29: =IF($C29="","",BDP($C29,G$3)) | H29: =IF($C29="","",BDP($C29,H$3)) | I29: =IF($C29="","",BDP($C29,I$3,"EQY_FUND_CRNCY","USD")) | J29: =IF($C29="","",BDP($C29,J$3,"EQY_FUND_CRNCY","USD")) | K29: =IF($C29="","",BDP($C29,K$3,"EQY_FUND_CRNCY","USD")) | L29: =IF($C29="","",BDP($C29,L$3,"EQY_FUND_CRNCY","USD")) | M29: =IF($C29="","",BDP($C29,M$3,"EQY_FUND_CRNCY","USD")) | N29: =IF($C29="","",BDP($C29,N$3,"EQY_FUND_CRNCY","USD")) | O29: =IF($C29="","",BDP($C29,O$3)) | P29: =IF(LEFT($O29,1)="#","",IF($O29="","",BDP($O29,P$3))) | Q29: =IF(AND(ISNUMBER($M29),ISNUMBER($N29)),IF($N29>0,$M29/$N29,""),"") | R29: =IF(AND(ISNUMBER($J29),ISNUMBER($I29)),IF($I29>0,ABS($J29)/$I29,""),"") | S29: =IF(AND(ISNUMBER($K29),ISNUMBER($L29)),IF($L29>0,$K29/$L29,""),"") | T29: =IF($D29="","",COUNTIFS('債券'!$B$5:$B$404,$D29,'債券'!$Y$5:$Y$404,1)) | U29: =IF($D29="","",SUMPRODUCT(('債券'!$B$5:$B$404=$D29)*('債券'!$Y$5:$Y$404=1)*'債券'!$AV$5:$AV$404)/1E6) | V29: =IF($D29="","",IF(SUMPRODUCT(('債券'!$B$5:$B$404=$D29)*('債券'!$Y$5:$Y$404=1)*'債券'!$AV$5:$AV$404)>0,SUMPRODUCT(('債券'!$B$5:$B$404=$D29)*('債券'!$Y$5:$Y$404=1)*'債券'!$AV$5:$AV$404*'債券'!$AT$5:$AT$404)/SUMPRODUCT(('債券'!$B$5:$B$404=$D29)*('債券'!$Y$5:$Y$404=1)*'債券'!$AV$5:$AV$404),"")) | W29: =IF($D29="","",IF(SUMPRODUCT(('債券'!$B$5:$B$404=$D29)*('債券'!$Y$5:$Y$404=1)*'債券'!$AV$5:$AV$404)>0,SUMPRODUCT(('債券'!$B$5:$B$404=$D29)*('債券'!$Y$5:$Y$404=1)*'債券'!$AV$5:$AV$404*'債券'!$AW$5:$AW$404)/SUMPRODUCT(('債券'!$B$5:$B$404=$D29)*('債券'!$Y$5:$Y$404=1)*'債券'!$AV$5:$AV$404),"")) | X29: =IF($D29="","",IFERROR(AVERAGEIFS('債券'!$AQ$5:$AQ$404,'債券'!$B$5:$B$404,$D29,'債券'!$Y$5:$Y$404,1),"")) | Y29: =IF($D29="","",COUNTIFS('債券'!$B$5:$B$404,$D29,'債券'!$AS$5:$AS$404,"加碼候選")) | Z29: =IF($D29="","",COUNTIFS('債券'!$B$5:$B$404,$D29,'債券'!$AS$5:$AS$404,"減碼候選"))
F30: =IF($C30="","",BDP($C30,F$3)) | G30: =IF($C30="","",BDP($C30,G$3)) | H30: =IF($C30="","",BDP($C30,H$3)) | I30: =IF($C30="","",BDP($C30,I$3,"EQY_FUND_CRNCY","USD")) | J30: =IF($C30="","",BDP($C30,J$3,"EQY_FUND_CRNCY","USD")) | K30: =IF($C30="","",BDP($C30,K$3,"EQY_FUND_CRNCY","USD")) | L30: =IF($C30="","",BDP($C30,L$3,"EQY_FUND_CRNCY","USD")) | M30: =IF($C30="","",BDP($C30,M$3,"EQY_FUND_CRNCY","USD")) | N30: =IF($C30="","",BDP($C30,N$3,"EQY_FUND_CRNCY","USD")) | O30: =IF($C30="","",BDP($C30,O$3)) | P30: =IF(LEFT($O30,1)="#","",IF($O30="","",BDP($O30,P$3))) | Q30: =IF(AND(ISNUMBER($M30),ISNUMBER($N30)),IF($N30>0,$M30/$N30,""),"") | R30: =IF(AND(ISNUMBER($J30),ISNUMBER($I30)),IF($I30>0,ABS($J30)/$I30,""),"") | S30: =IF(AND(ISNUMBER($K30),ISNUMBER($L30)),IF($L30>0,$K30/$L30,""),"") | T30: =IF($D30="","",COUNTIFS('債券'!$B$5:$B$404,$D30,'債券'!$Y$5:$Y$404,1)) | U30: =IF($D30="","",SUMPRODUCT(('債券'!$B$5:$B$404=$D30)*('債券'!$Y$5:$Y$404=1)*'債券'!$AV$5:$AV$404)/1E6) | V30: =IF($D30="","",IF(SUMPRODUCT(('債券'!$B$5:$B$404=$D30)*('債券'!$Y$5:$Y$404=1)*'債券'!$AV$5:$AV$404)>0,SUMPRODUCT(('債券'!$B$5:$B$404=$D30)*('債券'!$Y$5:$Y$404=1)*'債券'!$AV$5:$AV$404*'債券'!$AT$5:$AT$404)/SUMPRODUCT(('債券'!$B$5:$B$404=$D30)*('債券'!$Y$5:$Y$404=1)*'債券'!$AV$5:$AV$404),"")) | W30: =IF($D30="","",IF(SUMPRODUCT(('債券'!$B$5:$B$404=$D30)*('債券'!$Y$5:$Y$404=1)*'債券'!$AV$5:$AV$404)>0,SUMPRODUCT(('債券'!$B$5:$B$404=$D30)*('債券'!$Y$5:$Y$404=1)*'債券'!$AV$5:$AV$404*'債券'!$AW$5:$AW$404)/SUMPRODUCT(('債券'!$B$5:$B$404=$D30)*('債券'!$Y$5:$Y$404=1)*'債券'!$AV$5:$AV$404),"")) | X30: =IF($D30="","",IFERROR(AVERAGEIFS('債券'!$AQ$5:$AQ$404,'債券'!$B$5:$B$404,$D30,'債券'!$Y$5:$Y$404,1),"")) | Y30: =IF($D30="","",COUNTIFS('債券'!$B$5:$B$404,$D30,'債券'!$AS$5:$AS$404,"加碼候選")) | Z30: =IF($D30="","",COUNTIFS('債券'!$B$5:$B$404,$D30,'債券'!$AS$5:$AS$404,"減碼候選"))
F31: =IF($C31="","",BDP($C31,F$3)) | G31: =IF($C31="","",BDP($C31,G$3)) | H31: =IF($C31="","",BDP($C31,H$3)) | I31: =IF($C31="","",BDP($C31,I$3,"EQY_FUND_CRNCY","USD")) | J31: =IF($C31="","",BDP($C31,J$3,"EQY_FUND_CRNCY","USD")) | K31: =IF($C31="","",BDP($C31,K$3,"EQY_FUND_CRNCY","USD")) | L31: =IF($C31="","",BDP($C31,L$3,"EQY_FUND_CRNCY","USD")) | M31: =IF($C31="","",BDP($C31,M$3,"EQY_FUND_CRNCY","USD")) | N31: =IF($C31="","",BDP($C31,N$3,"EQY_FUND_CRNCY","USD")) | O31: =IF($C31="","",BDP($C31,O$3)) | P31: =IF(LEFT($O31,1)="#","",IF($O31="","",BDP($O31,P$3))) | Q31: =IF(AND(ISNUMBER($M31),ISNUMBER($N31)),IF($N31>0,$M31/$N31,""),"") | R31: =IF(AND(ISNUMBER($J31),ISNUMBER($I31)),IF($I31>0,ABS($J31)/$I31,""),"") | S31: =IF(AND(ISNUMBER($K31),ISNUMBER($L31)),IF($L31>0,$K31/$L31,""),"") | T31: =IF($D31="","",COUNTIFS('債券'!$B$5:$B$404,$D31,'債券'!$Y$5:$Y$404,1)) | U31: =IF($D31="","",SUMPRODUCT(('債券'!$B$5:$B$404=$D31)*('債券'!$Y$5:$Y$404=1)*'債券'!$AV$5:$AV$404)/1E6) | V31: =IF($D31="","",IF(SUMPRODUCT(('債券'!$B$5:$B$404=$D31)*('債券'!$Y$5:$Y$404=1)*'債券'!$AV$5:$AV$404)>0,SUMPRODUCT(('債券'!$B$5:$B$404=$D31)*('債券'!$Y$5:$Y$404=1)*'債券'!$AV$5:$AV$404*'債券'!$AT$5:$AT$404)/SUMPRODUCT(('債券'!$B$5:$B$404=$D31)*('債券'!$Y$5:$Y$404=1)*'債券'!$AV$5:$AV$404),"")) | W31: =IF($D31="","",IF(SUMPRODUCT(('債券'!$B$5:$B$404=$D31)*('債券'!$Y$5:$Y$404=1)*'債券'!$AV$5:$AV$404)>0,SUMPRODUCT(('債券'!$B$5:$B$404=$D31)*('債券'!$Y$5:$Y$404=1)*'債券'!$AV$5:$AV$404*'債券'!$AW$5:$AW$404)/SUMPRODUCT(('債券'!$B$5:$B$404=$D31)*('債券'!$Y$5:$Y$404=1)*'債券'!$AV$5:$AV$404),"")) | X31: =IF($D31="","",IFERROR(AVERAGEIFS('債券'!$AQ$5:$AQ$404,'債券'!$B$5:$B$404,$D31,'債券'!$Y$5:$Y$404,1),"")) | Y31: =IF($D31="","",COUNTIFS('債券'!$B$5:$B$404,$D31,'債券'!$AS$5:$AS$404,"加碼候選")) | Z31: =IF($D31="","",COUNTIFS('債券'!$B$5:$B$404,$D31,'債券'!$AS$5:$AS$404,"減碼候選"))
F32: =IF($C32="","",BDP($C32,F$3)) | G32: =IF($C32="","",BDP($C32,G$3)) | H32: =IF($C32="","",BDP($C32,H$3)) | I32: =IF($C32="","",BDP($C32,I$3,"EQY_FUND_CRNCY","USD")) | J32: =IF($C32="","",BDP($C32,J$3,"EQY_FUND_CRNCY","USD")) | K32: =IF($C32="","",BDP($C32,K$3,"EQY_FUND_CRNCY","USD")) | L32: =IF($C32="","",BDP($C32,L$3,"EQY_FUND_CRNCY","USD")) | M32: =IF($C32="","",BDP($C32,M$3,"EQY_FUND_CRNCY","USD")) | N32: =IF($C32="","",BDP($C32,N$3,"EQY_FUND_CRNCY","USD")) | O32: =IF($C32="","",BDP($C32,O$3)) | P32: =IF(LEFT($O32,1)="#","",IF($O32="","",BDP($O32,P$3))) | Q32: =IF(AND(ISNUMBER($M32),ISNUMBER($N32)),IF($N32>0,$M32/$N32,""),"") | R32: =IF(AND(ISNUMBER($J32),ISNUMBER($I32)),IF($I32>0,ABS($J32)/$I32,""),"") | S32: =IF(AND(ISNUMBER($K32),ISNUMBER($L32)),IF($L32>0,$K32/$L32,""),"") | T32: =IF($D32="","",COUNTIFS('債券'!$B$5:$B$404,$D32,'債券'!$Y$5:$Y$404,1)) | U32: =IF($D32="","",SUMPRODUCT(('債券'!$B$5:$B$404=$D32)*('債券'!$Y$5:$Y$404=1)*'債券'!$AV$5:$AV$404)/1E6) | V32: =IF($D32="","",IF(SUMPRODUCT(('債券'!$B$5:$B$404=$D32)*('債券'!$Y$5:$Y$404=1)*'債券'!$AV$5:$AV$404)>0,SUMPRODUCT(('債券'!$B$5:$B$404=$D32)*('債券'!$Y$5:$Y$404=1)*'債券'!$AV$5:$AV$404*'債券'!$AT$5:$AT$404)/SUMPRODUCT(('債券'!$B$5:$B$404=$D32)*('債券'!$Y$5:$Y$404=1)*'債券'!$AV$5:$AV$404),"")) | W32: =IF($D32="","",IF(SUMPRODUCT(('債券'!$B$5:$B$404=$D32)*('債券'!$Y$5:$Y$404=1)*'債券'!$AV$5:$AV$404)>0,SUMPRODUCT(('債券'!$B$5:$B$404=$D32)*('債券'!$Y$5:$Y$404=1)*'債券'!$AV$5:$AV$404*'債券'!$AW$5:$AW$404)/SUMPRODUCT(('債券'!$B$5:$B$404=$D32)*('債券'!$Y$5:$Y$404=1)*'債券'!$AV$5:$AV$404),"")) | X32: =IF($D32="","",IFERROR(AVERAGEIFS('債券'!$AQ$5:$AQ$404,'債券'!$B$5:$B$404,$D32,'債券'!$Y$5:$Y$404,1),"")) | Y32: =IF($D32="","",COUNTIFS('債券'!$B$5:$B$404,$D32,'債券'!$AS$5:$AS$404,"加碼候選")) | Z32: =IF($D32="","",COUNTIFS('債券'!$B$5:$B$404,$D32,'債券'!$AS$5:$AS$404,"減碼候選"))
F33: =IF($C33="","",BDP($C33,F$3)) | G33: =IF($C33="","",BDP($C33,G$3)) | H33: =IF($C33="","",BDP($C33,H$3)) | I33: =IF($C33="","",BDP($C33,I$3,"EQY_FUND_CRNCY","USD")) | J33: =IF($C33="","",BDP($C33,J$3,"EQY_FUND_CRNCY","USD")) | K33: =IF($C33="","",BDP($C33,K$3,"EQY_FUND_CRNCY","USD")) | L33: =IF($C33="","",BDP($C33,L$3,"EQY_FUND_CRNCY","USD")) | M33: =IF($C33="","",BDP($C33,M$3,"EQY_FUND_CRNCY","USD")) | N33: =IF($C33="","",BDP($C33,N$3,"EQY_FUND_CRNCY","USD")) | O33: =IF($C33="","",BDP($C33,O$3)) | P33: =IF(LEFT($O33,1)="#","",IF($O33="","",BDP($O33,P$3))) | Q33: =IF(AND(ISNUMBER($M33),ISNUMBER($N33)),IF($N33>0,$M33/$N33,""),"") | R33: =IF(AND(ISNUMBER($J33),ISNUMBER($I33)),IF($I33>0,ABS($J33)/$I33,""),"") | S33: =IF(AND(ISNUMBER($K33),ISNUMBER($L33)),IF($L33>0,$K33/$L33,""),"") | T33: =IF($D33="","",COUNTIFS('債券'!$B$5:$B$404,$D33,'債券'!$Y$5:$Y$404,1)) | U33: =IF($D33="","",SUMPRODUCT(('債券'!$B$5:$B$404=$D33)*('債券'!$Y$5:$Y$404=1)*'債券'!$AV$5:$AV$404)/1E6) | V33: =IF($D33="","",IF(SUMPRODUCT(('債券'!$B$5:$B$404=$D33)*('債券'!$Y$5:$Y$404=1)*'債券'!$AV$5:$AV$404)>0,SUMPRODUCT(('債券'!$B$5:$B$404=$D33)*('債券'!$Y$5:$Y$404=1)*'債券'!$AV$5:$AV$404*'債券'!$AT$5:$AT$404)/SUMPRODUCT(('債券'!$B$5:$B$404=$D33)*('債券'!$Y$5:$Y$404=1)*'債券'!$AV$5:$AV$404),"")) | W33: =IF($D33="","",IF(SUMPRODUCT(('債券'!$B$5:$B$404=$D33)*('債券'!$Y$5:$Y$404=1)*'債券'!$AV$5:$AV$404)>0,SUMPRODUCT(('債券'!$B$5:$B$404=$D33)*('債券'!$Y$5:$Y$404=1)*'債券'!$AV$5:$AV$404*'債券'!$AW$5:$AW$404)/SUMPRODUCT(('債券'!$B$5:$B$404=$D33)*('債券'!$Y$5:$Y$404=1)*'債券'!$AV$5:$AV$404),"")) | X33: =IF($D33="","",IFERROR(AVERAGEIFS('債券'!$AQ$5:$AQ$404,'債券'!$B$5:$B$404,$D33,'債券'!$Y$5:$Y$404,1),"")) | Y33: =IF($D33="","",COUNTIFS('債券'!$B$5:$B$404,$D33,'債券'!$AS$5:$AS$404,"加碼候選")) | Z33: =IF($D33="","",COUNTIFS('債券'!$B$5:$B$404,$D33,'債券'!$AS$5:$AS$404,"減碼候選"))
F34: =IF($C34="","",BDP($C34,F$3)) | G34: =IF($C34="","",BDP($C34,G$3)) | H34: =IF($C34="","",BDP($C34,H$3)) | I34: =IF($C34="","",BDP($C34,I$3,"EQY_FUND_CRNCY","USD")) | J34: =IF($C34="","",BDP($C34,J$3,"EQY_FUND_CRNCY","USD")) | K34: =IF($C34="","",BDP($C34,K$3,"EQY_FUND_CRNCY","USD")) | L34: =IF($C34="","",BDP($C34,L$3,"EQY_FUND_CRNCY","USD")) | M34: =IF($C34="","",BDP($C34,M$3,"EQY_FUND_CRNCY","USD")) | N34: =IF($C34="","",BDP($C34,N$3,"EQY_FUND_CRNCY","USD")) | O34: =IF($C34="","",BDP($C34,O$3)) | P34: =IF(LEFT($O34,1)="#","",IF($O34="","",BDP($O34,P$3))) | Q34: =IF(AND(ISNUMBER($M34),ISNUMBER($N34)),IF($N34>0,$M34/$N34,""),"") | R34: =IF(AND(ISNUMBER($J34),ISNUMBER($I34)),IF($I34>0,ABS($J34)/$I34,""),"") | S34: =IF(AND(ISNUMBER($K34),ISNUMBER($L34)),IF($L34>0,$K34/$L34,""),"") | T34: =IF($D34="","",COUNTIFS('債券'!$B$5:$B$404,$D34,'債券'!$Y$5:$Y$404,1)) | U34: =IF($D34="","",SUMPRODUCT(('債券'!$B$5:$B$404=$D34)*('債券'!$Y$5:$Y$404=1)*'債券'!$AV$5:$AV$404)/1E6) | V34: =IF($D34="","",IF(SUMPRODUCT(('債券'!$B$5:$B$404=$D34)*('債券'!$Y$5:$Y$404=1)*'債券'!$AV$5:$AV$404)>0,SUMPRODUCT(('債券'!$B$5:$B$404=$D34)*('債券'!$Y$5:$Y$404=1)*'債券'!$AV$5:$AV$404*'債券'!$AT$5:$AT$404)/SUMPRODUCT(('債券'!$B$5:$B$404=$D34)*('債券'!$Y$5:$Y$404=1)*'債券'!$AV$5:$AV$404),"")) | W34: =IF($D34="","",IF(SUMPRODUCT(('債券'!$B$5:$B$404=$D34)*('債券'!$Y$5:$Y$404=1)*'債券'!$AV$5:$AV$404)>0,SUMPRODUCT(('債券'!$B$5:$B$404=$D34)*('債券'!$Y$5:$Y$404=1)*'債券'!$AV$5:$AV$404*'債券'!$AW$5:$AW$404)/SUMPRODUCT(('債券'!$B$5:$B$404=$D34)*('債券'!$Y$5:$Y$404=1)*'債券'!$AV$5:$AV$404),"")) | X34: =IF($D34="","",IFERROR(AVERAGEIFS('債券'!$AQ$5:$AQ$404,'債券'!$B$5:$B$404,$D34,'債券'!$Y$5:$Y$404,1),"")) | Y34: =IF($D34="","",COUNTIFS('債券'!$B$5:$B$404,$D34,'債券'!$AS$5:$AS$404,"加碼候選")) | Z34: =IF($D34="","",COUNTIFS('債券'!$B$5:$B$404,$D34,'債券'!$AS$5:$AS$404,"減碼候選"))
F35: =IF($C35="","",BDP($C35,F$3)) | G35: =IF($C35="","",BDP($C35,G$3)) | H35: =IF($C35="","",BDP($C35,H$3)) | I35: =IF($C35="","",BDP($C35,I$3,"EQY_FUND_CRNCY","USD")) | J35: =IF($C35="","",BDP($C35,J$3,"EQY_FUND_CRNCY","USD")) | K35: =IF($C35="","",BDP($C35,K$3,"EQY_FUND_CRNCY","USD")) | L35: =IF($C35="","",BDP($C35,L$3,"EQY_FUND_CRNCY","USD")) | M35: =IF($C35="","",BDP($C35,M$3,"EQY_FUND_CRNCY","USD")) | N35: =IF($C35="","",BDP($C35,N$3,"EQY_FUND_CRNCY","USD")) | O35: =IF($C35="","",BDP($C35,O$3)) | P35: =IF(LEFT($O35,1)="#","",IF($O35="","",BDP($O35,P$3))) | Q35: =IF(AND(ISNUMBER($M35),ISNUMBER($N35)),IF($N35>0,$M35/$N35,""),"") | R35: =IF(AND(ISNUMBER($J35),ISNUMBER($I35)),IF($I35>0,ABS($J35)/$I35,""),"") | S35: =IF(AND(ISNUMBER($K35),ISNUMBER($L35)),IF($L35>0,$K35/$L35,""),"") | T35: =IF($D35="","",COUNTIFS('債券'!$B$5:$B$404,$D35,'債券'!$Y$5:$Y$404,1)) | U35: =IF($D35="","",SUMPRODUCT(('債券'!$B$5:$B$404=$D35)*('債券'!$Y$5:$Y$404=1)*'債券'!$AV$5:$AV$404)/1E6) | V35: =IF($D35="","",IF(SUMPRODUCT(('債券'!$B$5:$B$404=$D35)*('債券'!$Y$5:$Y$404=1)*'債券'!$AV$5:$AV$404)>0,SUMPRODUCT(('債券'!$B$5:$B$404=$D35)*('債券'!$Y$5:$Y$404=1)*'債券'!$AV$5:$AV$404*'債券'!$AT$5:$AT$404)/SUMPRODUCT(('債券'!$B$5:$B$404=$D35)*('債券'!$Y$5:$Y$404=1)*'債券'!$AV$5:$AV$404),"")) | W35: =IF($D35="","",IF(SUMPRODUCT(('債券'!$B$5:$B$404=$D35)*('債券'!$Y$5:$Y$404=1)*'債券'!$AV$5:$AV$404)>0,SUMPRODUCT(('債券'!$B$5:$B$404=$D35)*('債券'!$Y$5:$Y$404=1)*'債券'!$AV$5:$AV$404*'債券'!$AW$5:$AW$404)/SUMPRODUCT(('債券'!$B$5:$B$404=$D35)*('債券'!$Y$5:$Y$404=1)*'債券'!$AV$5:$AV$404),"")) | X35: =IF($D35="","",IFERROR(AVERAGEIFS('債券'!$AQ$5:$AQ$404,'債券'!$B$5:$B$404,$D35,'債券'!$Y$5:$Y$404,1),"")) | Y35: =IF($D35="","",COUNTIFS('債券'!$B$5:$B$404,$D35,'債券'!$AS$5:$AS$404,"加碼候選")) | Z35: =IF($D35="","",COUNTIFS('債券'!$B$5:$B$404,$D35,'債券'!$AS$5:$AS$404,"減碼候選"))
F36: =IF($C36="","",BDP($C36,F$3)) | G36: =IF($C36="","",BDP($C36,G$3)) | H36: =IF($C36="","",BDP($C36,H$3)) | I36: =IF($C36="","",BDP($C36,I$3,"EQY_FUND_CRNCY","USD")) | J36: =IF($C36="","",BDP($C36,J$3,"EQY_FUND_CRNCY","USD")) | K36: =IF($C36="","",BDP($C36,K$3,"EQY_FUND_CRNCY","USD")) | L36: =IF($C36="","",BDP($C36,L$3,"EQY_FUND_CRNCY","USD")) | M36: =IF($C36="","",BDP($C36,M$3,"EQY_FUND_CRNCY","USD")) | N36: =IF($C36="","",BDP($C36,N$3,"EQY_FUND_CRNCY","USD")) | O36: =IF($C36="","",BDP($C36,O$3)) | P36: =IF(LEFT($O36,1)="#","",IF($O36="","",BDP($O36,P$3))) | Q36: =IF(AND(ISNUMBER($M36),ISNUMBER($N36)),IF($N36>0,$M36/$N36,""),"") | R36: =IF(AND(ISNUMBER($J36),ISNUMBER($I36)),IF($I36>0,ABS($J36)/$I36,""),"") | S36: =IF(AND(ISNUMBER($K36),ISNUMBER($L36)),IF($L36>0,$K36/$L36,""),"") | T36: =IF($D36="","",COUNTIFS('債券'!$B$5:$B$404,$D36,'債券'!$Y$5:$Y$404,1)) | U36: =IF($D36="","",SUMPRODUCT(('債券'!$B$5:$B$404=$D36)*('債券'!$Y$5:$Y$404=1)*'債券'!$AV$5:$AV$404)/1E6) | V36: =IF($D36="","",IF(SUMPRODUCT(('債券'!$B$5:$B$404=$D36)*('債券'!$Y$5:$Y$404=1)*'債券'!$AV$5:$AV$404)>0,SUMPRODUCT(('債券'!$B$5:$B$404=$D36)*('債券'!$Y$5:$Y$404=1)*'債券'!$AV$5:$AV$404*'債券'!$AT$5:$AT$404)/SUMPRODUCT(('債券'!$B$5:$B$404=$D36)*('債券'!$Y$5:$Y$404=1)*'債券'!$AV$5:$AV$404),"")) | W36: =IF($D36="","",IF(SUMPRODUCT(('債券'!$B$5:$B$404=$D36)*('債券'!$Y$5:$Y$404=1)*'債券'!$AV$5:$AV$404)>0,SUMPRODUCT(('債券'!$B$5:$B$404=$D36)*('債券'!$Y$5:$Y$404=1)*'債券'!$AV$5:$AV$404*'債券'!$AW$5:$AW$404)/SUMPRODUCT(('債券'!$B$5:$B$404=$D36)*('債券'!$Y$5:$Y$404=1)*'債券'!$AV$5:$AV$404),"")) | X36: =IF($D36="","",IFERROR(AVERAGEIFS('債券'!$AQ$5:$AQ$404,'債券'!$B$5:$B$404,$D36,'債券'!$Y$5:$Y$404,1),"")) | Y36: =IF($D36="","",COUNTIFS('債券'!$B$5:$B$404,$D36,'債券'!$AS$5:$AS$404,"加碼候選")) | Z36: =IF($D36="","",COUNTIFS('債券'!$B$5:$B$404,$D36,'債券'!$AS$5:$AS$404,"減碼候選"))
F37: =IF($C37="","",BDP($C37,F$3)) | G37: =IF($C37="","",BDP($C37,G$3)) | H37: =IF($C37="","",BDP($C37,H$3)) | I37: =IF($C37="","",BDP($C37,I$3,"EQY_FUND_CRNCY","USD")) | J37: =IF($C37="","",BDP($C37,J$3,"EQY_FUND_CRNCY","USD")) | K37: =IF($C37="","",BDP($C37,K$3,"EQY_FUND_CRNCY","USD")) | L37: =IF($C37="","",BDP($C37,L$3,"EQY_FUND_CRNCY","USD")) | M37: =IF($C37="","",BDP($C37,M$3,"EQY_FUND_CRNCY","USD")) | N37: =IF($C37="","",BDP($C37,N$3,"EQY_FUND_CRNCY","USD")) | O37: =IF($C37="","",BDP($C37,O$3)) | P37: =IF(LEFT($O37,1)="#","",IF($O37="","",BDP($O37,P$3))) | Q37: =IF(AND(ISNUMBER($M37),ISNUMBER($N37)),IF($N37>0,$M37/$N37,""),"") | R37: =IF(AND(ISNUMBER($J37),ISNUMBER($I37)),IF($I37>0,ABS($J37)/$I37,""),"") | S37: =IF(AND(ISNUMBER($K37),ISNUMBER($L37)),IF($L37>0,$K37/$L37,""),"") | T37: =IF($D37="","",COUNTIFS('債券'!$B$5:$B$404,$D37,'債券'!$Y$5:$Y$404,1)) | U37: =IF($D37="","",SUMPRODUCT(('債券'!$B$5:$B$404=$D37)*('債券'!$Y$5:$Y$404=1)*'債券'!$AV$5:$AV$404)/1E6) | V37: =IF($D37="","",IF(SUMPRODUCT(('債券'!$B$5:$B$404=$D37)*('債券'!$Y$5:$Y$404=1)*'債券'!$AV$5:$AV$404)>0,SUMPRODUCT(('債券'!$B$5:$B$404=$D37)*('債券'!$Y$5:$Y$404=1)*'債券'!$AV$5:$AV$404*'債券'!$AT$5:$AT$404)/SUMPRODUCT(('債券'!$B$5:$B$404=$D37)*('債券'!$Y$5:$Y$404=1)*'債券'!$AV$5:$AV$404),"")) | W37: =IF($D37="","",IF(SUMPRODUCT(('債券'!$B$5:$B$404=$D37)*('債券'!$Y$5:$Y$404=1)*'債券'!$AV$5:$AV$404)>0,SUMPRODUCT(('債券'!$B$5:$B$404=$D37)*('債券'!$Y$5:$Y$404=1)*'債券'!$AV$5:$AV$404*'債券'!$AW$5:$AW$404)/SUMPRODUCT(('債券'!$B$5:$B$404=$D37)*('債券'!$Y$5:$Y$404=1)*'債券'!$AV$5:$AV$404),"")) | X37: =IF($D37="","",IFERROR(AVERAGEIFS('債券'!$AQ$5:$AQ$404,'債券'!$B$5:$B$404,$D37,'債券'!$Y$5:$Y$404,1),"")) | Y37: =IF($D37="","",COUNTIFS('債券'!$B$5:$B$404,$D37,'債券'!$AS$5:$AS$404,"加碼候選")) | Z37: =IF($D37="","",COUNTIFS('債券'!$B$5:$B$404,$D37,'債券'!$AS$5:$AS$404,"減碼候選"))
F38: =IF($C38="","",BDP($C38,F$3)) | G38: =IF($C38="","",BDP($C38,G$3)) | H38: =IF($C38="","",BDP($C38,H$3)) | I38: =IF($C38="","",BDP($C38,I$3,"EQY_FUND_CRNCY","USD")) | J38: =IF($C38="","",BDP($C38,J$3,"EQY_FUND_CRNCY","USD")) | K38: =IF($C38="","",BDP($C38,K$3,"EQY_FUND_CRNCY","USD")) | L38: =IF($C38="","",BDP($C38,L$3,"EQY_FUND_CRNCY","USD")) | M38: =IF($C38="","",BDP($C38,M$3,"EQY_FUND_CRNCY","USD")) | N38: =IF($C38="","",BDP($C38,N$3,"EQY_FUND_CRNCY","USD")) | O38: =IF($C38="","",BDP($C38,O$3)) | P38: =IF(LEFT($O38,1)="#","",IF($O38="","",BDP($O38,P$3))) | Q38: =IF(AND(ISNUMBER($M38),ISNUMBER($N38)),IF($N38>0,$M38/$N38,""),"") | R38: =IF(AND(ISNUMBER($J38),ISNUMBER($I38)),IF($I38>0,ABS($J38)/$I38,""),"") | S38: =IF(AND(ISNUMBER($K38),ISNUMBER($L38)),IF($L38>0,$K38/$L38,""),"") | T38: =IF($D38="","",COUNTIFS('債券'!$B$5:$B$404,$D38,'債券'!$Y$5:$Y$404,1)) | U38: =IF($D38="","",SUMPRODUCT(('債券'!$B$5:$B$404=$D38)*('債券'!$Y$5:$Y$404=1)*'債券'!$AV$5:$AV$404)/1E6) | V38: =IF($D38="","",IF(SUMPRODUCT(('債券'!$B$5:$B$404=$D38)*('債券'!$Y$5:$Y$404=1)*'債券'!$AV$5:$AV$404)>0,SUMPRODUCT(('債券'!$B$5:$B$404=$D38)*('債券'!$Y$5:$Y$404=1)*'債券'!$AV$5:$AV$404*'債券'!$AT$5:$AT$404)/SUMPRODUCT(('債券'!$B$5:$B$404=$D38)*('債券'!$Y$5:$Y$404=1)*'債券'!$AV$5:$AV$404),"")) | W38: =IF($D38="","",IF(SUMPRODUCT(('債券'!$B$5:$B$404=$D38)*('債券'!$Y$5:$Y$404=1)*'債券'!$AV$5:$AV$404)>0,SUMPRODUCT(('債券'!$B$5:$B$404=$D38)*('債券'!$Y$5:$Y$404=1)*'債券'!$AV$5:$AV$404*'債券'!$AW$5:$AW$404)/SUMPRODUCT(('債券'!$B$5:$B$404=$D38)*('債券'!$Y$5:$Y$404=1)*'債券'!$AV$5:$AV$404),"")) | X38: =IF($D38="","",IFERROR(AVERAGEIFS('債券'!$AQ$5:$AQ$404,'債券'!$B$5:$B$404,$D38,'債券'!$Y$5:$Y$404,1),"")) | Y38: =IF($D38="","",COUNTIFS('債券'!$B$5:$B$404,$D38,'債券'!$AS$5:$AS$404,"加碼候選")) | Z38: =IF($D38="","",COUNTIFS('債券'!$B$5:$B$404,$D38,'債券'!$AS$5:$AS$404,"減碼候選"))
F39: =IF($C39="","",BDP($C39,F$3)) | G39: =IF($C39="","",BDP($C39,G$3)) | H39: =IF($C39="","",BDP($C39,H$3)) | I39: =IF($C39="","",BDP($C39,I$3,"EQY_FUND_CRNCY","USD")) | J39: =IF($C39="","",BDP($C39,J$3,"EQY_FUND_CRNCY","USD")) | K39: =IF($C39="","",BDP($C39,K$3,"EQY_FUND_CRNCY","USD")) | L39: =IF($C39="","",BDP($C39,L$3,"EQY_FUND_CRNCY","USD")) | M39: =IF($C39="","",BDP($C39,M$3,"EQY_FUND_CRNCY","USD")) | N39: =IF($C39="","",BDP($C39,N$3,"EQY_FUND_CRNCY","USD")) | O39: =IF($C39="","",BDP($C39,O$3)) | P39: =IF(LEFT($O39,1)="#","",IF($O39="","",BDP($O39,P$3))) | Q39: =IF(AND(ISNUMBER($M39),ISNUMBER($N39)),IF($N39>0,$M39/$N39,""),"") | R39: =IF(AND(ISNUMBER($J39),ISNUMBER($I39)),IF($I39>0,ABS($J39)/$I39,""),"") | S39: =IF(AND(ISNUMBER($K39),ISNUMBER($L39)),IF($L39>0,$K39/$L39,""),"") | T39: =IF($D39="","",COUNTIFS('債券'!$B$5:$B$404,$D39,'債券'!$Y$5:$Y$404,1)) | U39: =IF($D39="","",SUMPRODUCT(('債券'!$B$5:$B$404=$D39)*('債券'!$Y$5:$Y$404=1)*'債券'!$AV$5:$AV$404)/1E6) | V39: =IF($D39="","",IF(SUMPRODUCT(('債券'!$B$5:$B$404=$D39)*('債券'!$Y$5:$Y$404=1)*'債券'!$AV$5:$AV$404)>0,SUMPRODUCT(('債券'!$B$5:$B$404=$D39)*('債券'!$Y$5:$Y$404=1)*'債券'!$AV$5:$AV$404*'債券'!$AT$5:$AT$404)/SUMPRODUCT(('債券'!$B$5:$B$404=$D39)*('債券'!$Y$5:$Y$404=1)*'債券'!$AV$5:$AV$404),"")) | W39: =IF($D39="","",IF(SUMPRODUCT(('債券'!$B$5:$B$404=$D39)*('債券'!$Y$5:$Y$404=1)*'債券'!$AV$5:$AV$404)>0,SUMPRODUCT(('債券'!$B$5:$B$404=$D39)*('債券'!$Y$5:$Y$404=1)*'債券'!$AV$5:$AV$404*'債券'!$AW$5:$AW$404)/SUMPRODUCT(('債券'!$B$5:$B$404=$D39)*('債券'!$Y$5:$Y$404=1)*'債券'!$AV$5:$AV$404),"")) | X39: =IF($D39="","",IFERROR(AVERAGEIFS('債券'!$AQ$5:$AQ$404,'債券'!$B$5:$B$404,$D39,'債券'!$Y$5:$Y$404,1),"")) | Y39: =IF($D39="","",COUNTIFS('債券'!$B$5:$B$404,$D39,'債券'!$AS$5:$AS$404,"加碼候選")) | Z39: =IF($D39="","",COUNTIFS('債券'!$B$5:$B$404,$D39,'債券'!$AS$5:$AS$404,"減碼候選"))
F40: =IF($C40="","",BDP($C40,F$3)) | G40: =IF($C40="","",BDP($C40,G$3)) | H40: =IF($C40="","",BDP($C40,H$3)) | I40: =IF($C40="","",BDP($C40,I$3,"EQY_FUND_CRNCY","USD")) | J40: =IF($C40="","",BDP($C40,J$3,"EQY_FUND_CRNCY","USD")) | K40: =IF($C40="","",BDP($C40,K$3,"EQY_FUND_CRNCY","USD")) | L40: =IF($C40="","",BDP($C40,L$3,"EQY_FUND_CRNCY","USD")) | M40: =IF($C40="","",BDP($C40,M$3,"EQY_FUND_CRNCY","USD")) | N40: =IF($C40="","",BDP($C40,N$3,"EQY_FUND_CRNCY","USD")) | O40: =IF($C40="","",BDP($C40,O$3)) | P40: =IF(LEFT($O40,1)="#","",IF($O40="","",BDP($O40,P$3))) | Q40: =IF(AND(ISNUMBER($M40),ISNUMBER($N40)),IF($N40>0,$M40/$N40,""),"") | R40: =IF(AND(ISNUMBER($J40),ISNUMBER($I40)),IF($I40>0,ABS($J40)/$I40,""),"") | S40: =IF(AND(ISNUMBER($K40),ISNUMBER($L40)),IF($L40>0,$K40/$L40,""),"") | T40: =IF($D40="","",COUNTIFS('債券'!$B$5:$B$404,$D40,'債券'!$Y$5:$Y$404,1)) | U40: =IF($D40="","",SUMPRODUCT(('債券'!$B$5:$B$404=$D40)*('債券'!$Y$5:$Y$404=1)*'債券'!$AV$5:$AV$404)/1E6) | V40: =IF($D40="","",IF(SUMPRODUCT(('債券'!$B$5:$B$404=$D40)*('債券'!$Y$5:$Y$404=1)*'債券'!$AV$5:$AV$404)>0,SUMPRODUCT(('債券'!$B$5:$B$404=$D40)*('債券'!$Y$5:$Y$404=1)*'債券'!$AV$5:$AV$404*'債券'!$AT$5:$AT$404)/SUMPRODUCT(('債券'!$B$5:$B$404=$D40)*('債券'!$Y$5:$Y$404=1)*'債券'!$AV$5:$AV$404),"")) | W40: =IF($D40="","",IF(SUMPRODUCT(('債券'!$B$5:$B$404=$D40)*('債券'!$Y$5:$Y$404=1)*'債券'!$AV$5:$AV$404)>0,SUMPRODUCT(('債券'!$B$5:$B$404=$D40)*('債券'!$Y$5:$Y$404=1)*'債券'!$AV$5:$AV$404*'債券'!$AW$5:$AW$404)/SUMPRODUCT(('債券'!$B$5:$B$404=$D40)*('債券'!$Y$5:$Y$404=1)*'債券'!$AV$5:$AV$404),"")) | X40: =IF($D40="","",IFERROR(AVERAGEIFS('債券'!$AQ$5:$AQ$404,'債券'!$B$5:$B$404,$D40,'債券'!$Y$5:$Y$404,1),"")) | Y40: =IF($D40="","",COUNTIFS('債券'!$B$5:$B$404,$D40,'債券'!$AS$5:$AS$404,"加碼候選")) | Z40: =IF($D40="","",COUNTIFS('債券'!$B$5:$B$404,$D40,'債券'!$AS$5:$AS$404,"減碼候選"))
... F44: =IF($C44="","",BDP($C44,F$3)) | G44: =IF($C44="","",BDP($C44,G$3)) | H44: =IF($C44="","",BDP($C44,H$3)) | I44: =IF($C44="","",BDP($C44,I$3,"EQY_FUND_CRNCY","USD")) | J44: =IF($C44="","",BDP($C44,J$3,"EQY_FUND_CRNCY","USD")) | K44: =IF($C44="","",BDP($C44,K$3,"EQY_FUND_CRNCY","USD")) | L44: =IF($C44="","",BDP($C44,L$3,"EQY_FUND_CRNCY","USD")) | M44: =IF($C44="","",BDP($C44,M$3,"EQY_FUND_CRNCY","USD")) | N44: =IF($C44="","",BDP($C44,N$3,"EQY_FUND_CRNCY","USD")) | O44: =IF($C44="","",BDP($C44,O$3)) | P44: =IF(LEFT($O44,1)="#","",IF($O44="","",BDP($O44,P$3))) | Q44: =IF(AND(ISNUMBER($M44),ISNUMBER($N44)),IF($N44>0,$M44/$N44,""),"") | R44: =IF(AND(ISNUMBER($J44),ISNUMBER($I44)),IF($I44>0,ABS($J44)/$I44,""),"") | S44: =IF(AND(ISNUMBER($K44),ISNUMBER($L44)),IF($L44>0,$K44/$L44,""),"") | T44: =IF($D44="","",COUNTIFS('債券'!$B$5:$B$404,$D44,'債券'!$Y$5:$Y$404,1)) | U44: =IF($D44="","",SUMPRODUCT(('債券'!$B$5:$B$404=$D44)*('債券'!$Y$5:$Y$404=1)*'債券'!$AV$5:$AV$404)/1E6) | V44: =IF($D44="","",IF(SUMPRODUCT(('債券'!$B$5:$B$404=$D44)*('債券'!$Y$5:$Y$404=1)*'債券'!$AV$5:$AV$404)>0,SUMPRODUCT(('債券'!$B$5:$B$404=$D44)*('債券'!$Y$5:$Y$404=1)*'債券'!$AV$5:$AV$404*'債券'!$AT$5:$AT$404)/SUMPRODUCT(('債券'!$B$5:$B$404=$D44)*('債券'!$Y$5:$Y$404=1)*'債券'!$AV$5:$AV$404),"")) | W44: =IF($D44="","",IF(SUMPRODUCT(('債券'!$B$5:$B$404=$D44)*('債券'!$Y$5:$Y$404=1)*'債券'!$AV$5:$AV$404)>0,SUMPRODUCT(('債券'!$B$5:$B$404=$D44)*('債券'!$Y$5:$Y$404=1)*'債券'!$AV$5:$AV$404*'債券'!$AW$5:$AW$404)/SUMPRODUCT(('債券'!$B$5:$B$404=$D44)*('債券'!$Y$5:$Y$404=1)*'債券'!$AV$5:$AV$404),"")) | X44: =IF($D44="","",IFERROR(AVERAGEIFS('債券'!$AQ$5:$AQ$404,'債券'!$B$5:$B$404,$D44,'債券'!$Y$5:$Y$404,1),"")) | Y44: =IF($D44="","",COUNTIFS('債券'!$B$5:$B$404,$D44,'債券'!$AS$5:$AS$404,"加碼候選")) | Z44: =IF($D44="","",COUNTIFS('債券'!$B$5:$B$404,$D44,'債券'!$AS$5:$AS$404,"減碼候選"))

Sheet 債券
A1: 美元公司債：AI 相關發行人
A2: A 欄貼上債券代碼（見「說明」）。第 3 列黃底是彭博欄位代碼，可依 FLDS 查詢結果修改。灰色標題為輔助欄，請勿刪除。
A3: 彭博欄位 → | B3: TICKER | C3: SECURITY_DES | D3: CPN | E3: MATURITY | F3: AMT_OUTSTANDING | G3: BB_COMPOSITE | H3: RTG_SP | I3: RTG_MOODY | J3: PAYMENT_RANK | K3: MTY_TYP | L3: PX_MID | M3: YLD_YTM_MID | N3: OAS_SPREAD_MID | O3: DUR_ADJ_MID | P3: BDH（同 OAS 欄位） | Q3: BDH（同 OAS 欄位） | R3: BDH（同 OAS 欄位）
A4: 債券代碼 （ISIN 或彭博代碼） | B4: 發行人代碼 | C4: 債券簡稱 | D4: 票息 (%) | E4: 到期日 | F4: 流通在外 (USD) | G4: 彭博綜合評等 | H4: S&P | I4: Moody's | J4: 求償順位 | K4: 到期型態 | L4: 價格 (Mid) | M4: 殖利率 (%) | N4: OAS (bp) | O4: 利差存續期間 | P4: OAS 1 個月前 | Q4: OAS 3 個月前 | R4: OAS 6 個月前 | S4: 分類 | T4: 股票 6M 報酬 (%) | U4: 剩餘年限 | V4: 天期分群 | W4: 評等分數 | X4: 評等分群 | Y4: 有效 (1/0) | Z4: DTS | AA4: 3M OAS 變化 (bp) | AB4: 動能：6M→1M 超額報酬 (bp) | AC4: Carry 組內檔數 | AD4: Carry 組平均 OAS | AE4: Carry 組標準差 | AF4: Carry z | AG4: 發行人 檔數 | AH4: 發行人曲線 擬合 OAS | AI4: 相對發行人 曲線 (bp) | AJ4: 評等曲線 擬合 OAS | AK4: 相對評等 曲線 (bp) | AL4: Value： 相對便宜 % | AM4: Value z | AN4: 動能 ÷ DTS (×100) | AO4: Momentum z | AP4: 股票動能 z | AQ4: 綜合分數 | AR4: 評等分群內 排名百分位 | AS4: 訊號 | AT4: 輔助 OAS | AU4: 輔助 ln(存續) | AV4: 輔助 流通在外 | AW4: 輔助 DTS | AX4: 輔助 Value | AY4: 輔助 Value 有效 | AZ4: 輔助 動能 | BA4: 輔助 動能有效 | BB4: 輔助 股票 | BC4: 輔助 股票有效 | BD4: 輔助 排序（高） | BE4: 輔助 排序（低）
B5: =IF($A5="","",BDP($A5,B$3)) | C5: =IF($A5="","",BDP($A5,C$3)) | D5: =IF($A5="","",BDP($A5,D$3)) | E5: =IF($A5="","",BDP($A5,E$3)) | F5: =IF($A5="","",BDP($A5,F$3)) | G5: =IF($A5="","",BDP($A5,G$3)) | H5: =IF($A5="","",BDP($A5,H$3)) | I5: =IF($A5="","",BDP($A5,I$3)) | ... O5: =IF($A5="","",BDP($A5,O$3)) | P5: =IF($A5="","",BDH($A5,$N$3,'參數'!$B$5,'參數'!$B$5,"Days=A","Fill=P","Dates=H")) | Q5: =IF($A5="","",BDH($A5,$N$3,'參數'!$B$6,'參數'!$B$6,"Days=A","Fill=P","Dates=H")) | R5: =IF($A5="","",BDH($A5,$N$3,'參數'!$B$7,'參數'!$B$7,"Days=A","Fill=P","Dates=H")) | S5: =IF($A5="","",IFERROR(INDEX('發行人'!$A$5:$A$44,MATCH(B5,'發行人'!$D$5:$D$44,0)),"未對應")) | T5: =IF($A5="","",IFERROR(INDEX('發行人'!$G$5:$G$44,MATCH(B5,'發行人'!$D$5:$D$44,0))+0,"")) | U5: =IF(ISNUMBER(E5),YEARFRAC('參數'!$B$4,E5),"") | V5: =IF(U5="","",IF(U5<3,"1-3y",IF(U5<5,"3-5y",IF(U5<7,"5-7y",IF(U5<10,"7-10y","10y+"))))) | W5: =IF($A5="","",IFERROR(INDEX('參數'!$B$24:$B$45,MATCH(G5,'參數'!$A$24:$A$45,0)),"")) | X5: =IF($A5="","",IFERROR(INDEX('參數'!$C$24:$C$45,MATCH(G5,'參數'!$A$24:$A$45,0)),"")) | Y5: =IF(AND(ISNUMBER(N5),ISNUMBER(O5),ISNUMBER(U5)),IF(AND(O5>0,X5<>""),1,0),0) | Z5: =IF(Y5=1,O5*N5,"") | AA5: =IF(Y5=1,IF(ISNUMBER(Q5),N5-Q5,""),"") | AB5: =IF(Y5=1,IF(AND(ISNUMBER(P5),ISNUMBER(R5)),R5*5/12-O5*(P5-R5),""),"") | AC5: =IF(Y5=1,COUNTIFS($X$5:$X$404,X5,$V$5:$V$404,V5,$Y$5:$Y$404,1),"") | AD5: =IF(Y5=1,IFERROR(IF(AC5>='參數'!$B$9,INDEX('分群統計'!$G$13:$K$16,MATCH(X5,'分群統計'!$A$13:$A$16,0),MATCH(V5,'分群統計'!$G$12:$K$12,0)),INDEX('分群統計'!$I$5:$I$8,MATCH(X5,'分群統計'!$A$5:$A$8,0))),""),"") | AE5: =IF(Y5=1,IFERROR(IF(AC5>='參數'!$B$9,INDEX('分群統計'!$L$13:$P$16,MATCH(X5,'分群統計'!$A$13:$A$16,0),MATCH(V5,'分群統計'!$L$12:$P$12,0)),INDEX('分群統計'!$J$5:$J$8,MATCH(X5,'分群統計'!$A$5:$A$8,0))),""),"") | AF5: =IF(ISNUMBER(AE5),IF(AE5>0,MAX(-3,MIN(3,(N5-AD5)/AE5)),0),"") | AG5: =IF(Y5=1,COUNTIFS($B$5:$B$404,B5,$Y$5:$Y$404,1),"") | AH5: =IF(Y5=1,IFERROR(IF(ISNUMBER(INDEX('分群統計'!$G$20:$G$59,MATCH(B5,'分群統計'!$A$20:$A$59,0))),INDEX('分群統計'!$H$20:$H$59,MATCH(B5,'分群統計'!$A$20:$A$59,0))+INDEX('分群統計'!$G$20:$G$59,MATCH(B5,'分群統計'!$A$20:$A$59,0))*AU5,""),""),"") | AI5: =IF(ISNUMBER(AH5),N5-AH5,"") | AJ5: =IF(Y5=1,IFERROR(IF(ISNUMBER(INDEX('分群統計'!$G$5:$G$8,MATCH(X5,'分群統計'!$A$5:$A$8,0))),INDEX('分群統計'!$H$5:$H$8,MATCH(X5,'分群統計'!$A$5:$A$8,0))+INDEX('分群統計'!$G$5:$G$8,MATCH(X5,'分群統計'!$A$5:$A$8,0))*AU5,""),""),"") | AK5: =IF(ISNUMBER(AJ5),N5-AJ5,"") | AL5: =IF(ISNUMBER(AJ5),IF(AJ5>0,AK5/AJ5,""),"") | AM5: =IF(AY5<>1,"",IFERROR(IF(INDEX('分群統計'!$K$5:$K$8,MATCH(X5,'分群統計'!$A$5:$A$8,0))<3,"",IF(INDEX('分群統計'!$M$5:$M$8,MATCH(X5,'分群統計'!$A$5:$A$8,0))>0,MAX(-3,MIN(3,(AX5-INDEX('分群統計'!$L$5:$L$8,MATCH(X5,'分群統計'!$A$5:$A$8,0)))/INDEX('分群統計'!$M$5:$M$8,MATCH(X5,'分群統計'!$A$5:$A$8,0)))),0)),"")) | AN5: =IF(ISNUMBER(AB5),IF(Z5>0,AB5/Z5*100,""),"") | AO5: =IF(BA5<>1,"",IFERROR(IF(INDEX('分群統計'!$N$5:$N$8,MATCH(X5,'分群統計'!$A$5:$A$8,0))<3,"",IF(INDEX('分群統計'!$P$5:$P$8,MATCH(X5,'分群統計'!$A$5:$A$8,0))>0,MAX(-3,MIN(3,(AZ5-INDEX('分群統計'!$O$5:$O$8,MATCH(X5,'分群統計'!$A$5:$A$8,0)))/INDEX('分群統計'!$P$5:$P$8,MATCH(X5,'分群統計'!$A$5:$A$8,0)))),0)),"")) | AP5: =IF(BC5<>1,"",IFERROR(IF(INDEX('分群統計'!$Q$5:$Q$8,MATCH(X5,'分群統計'!$A$5:$A$8,0))<3,"",IF(INDEX('分群統計'!$S$5:$S$8,MATCH(X5,'分群統計'!$A$5:$A$8,0))>0,MAX(-3,MIN(3,(BB5-INDEX('分群統計'!$R$5:$R$8,MATCH(X5,'分群統計'!$A$5:$A$8,0)))/INDEX('分群統計'!$S$5:$S$8,MATCH(X5,'分群統計'!$A$5:$A$8,0)))),0)),"")) | AQ5: =IF(Y5=1,(IF(ISNUMBER(AF5),AF5,0)*'參數'!$B$13+IF(ISNUMBER(AM5),AM5,0)*'參數'!$B$14+IF(ISNUMBER(AO5),AO5,0)*'參數'!$B$15+IF(ISNUMBER(AP5),AP5,0)*'參數'!$B$16)/('參數'!$B$13+'參數'!$B$14+'參數'!$B$15+'參數'!$B$16),"") | AR5: =IF(Y5=1,(SUMPRODUCT(($X$5:$X$404=X5)*($Y$5:$Y$404=1)*($BD$5:$BD$404>BD5))+1)/COUNTIFS($X$5:$X$404,X5,$Y$5:$Y$404,1),"") | AS5: =IF(ISNUMBER(AR5),IF(AR5<='參數'!$B$18,"加碼候選",IF(AR5>'參數'!$B$19,"減碼候選","")),"") | AT5: =IF(Y5=1,N5,0) | AU5: =IF(Y5=1,LN(O5),0) | AV5: =IF(Y5=1,IF(ISNUMBER(F5),F5,0),0) | AW5: =IF(Y5=1,Z5,0) | AX5: =IF(Y5=1,IF(ISNUMBER(AL5),AL5,0),0) | AY5: =IF(Y5=1,IF(ISNUMBER(AL5),1,0),0) | AZ5: =IF(Y5=1,IF(ISNUMBER(AN5),AN5,0),0) | BA5: =IF(Y5=1,IF(ISNUMBER(AN5),1,0),0) | BB5: =IF(Y5=1,IF(ISNUMBER(T5),T5,0),0) | BC5: =IF(Y5=1,IF(ISNUMBER(T5),1,0),0) | BD5: =IF(Y5=1,AQ5+ROW()/1E9,-1E9) | BE5: =IF(Y5=1,AQ5+ROW()/1E9,1E9)
B6: =IF($A6="","",BDP($A6,B$3)) | C6: =IF($A6="","",BDP($A6,C$3)) | D6: =IF($A6="","",BDP($A6,D$3)) | E6: =IF($A6="","",BDP($A6,E$3)) | F6: =IF($A6="","",BDP($A6,F$3)) | G6: =IF($A6="","",BDP($A6,G$3)) | H6: =IF($A6="","",BDP($A6,H$3)) | I6: =IF($A6="","",BDP($A6,I$3)) | ... O6: =IF($A6="","",BDP($A6,O$3)) | P6: =IF($A6="","",BDH($A6,$N$3,'參數'!$B$5,'參數'!$B$5,"Days=A","Fill=P","Dates=H")) | Q6: =IF($A6="","",BDH($A6,$N$3,'參數'!$B$6,'參數'!$B$6,"Days=A","Fill=P","Dates=H")) | R6: =IF($A6="","",BDH($A6,$N$3,'參數'!$B$7,'參數'!$B$7,"Days=A","Fill=P","Dates=H")) | S6: =IF($A6="","",IFERROR(INDEX('發行人'!$A$5:$A$44,MATCH(B6,'發行人'!$D$5:$D$44,0)),"未對應")) | T6: =IF($A6="","",IFERROR(INDEX('發行人'!$G$5:$G$44,MATCH(B6,'發行人'!$D$5:$D$44,0))+0,"")) | U6: =IF(ISNUMBER(E6),YEARFRAC('參數'!$B$4,E6),"") | V6: =IF(U6="","",IF(U6<3,"1-3y",IF(U6<5,"3-5y",IF(U6<7,"5-7y",IF(U6<10,"7-10y","10y+"))))) | W6: =IF($A6="","",IFERROR(INDEX('參數'!$B$24:$B$45,MATCH(G6,'參數'!$A$24:$A$45,0)),"")) | X6: =IF($A6="","",IFERROR(INDEX('參數'!$C$24:$C$45,MATCH(G6,'參數'!$A$24:$A$45,0)),"")) | Y6: =IF(AND(ISNUMBER(N6),ISNUMBER(O6),ISNUMBER(U6)),IF(AND(O6>0,X6<>""),1,0),0) | Z6: =IF(Y6=1,O6*N6,"") | AA6: =IF(Y6=1,IF(ISNUMBER(Q6),N6-Q6,""),"") | AB6: =IF(Y6=1,IF(AND(ISNUMBER(P6),ISNUMBER(R6)),R6*5/12-O6*(P6-R6),""),"") | AC6: =IF(Y6=1,COUNTIFS($X$5:$X$404,X6,$V$5:$V$404,V6,$Y$5:$Y$404,1),"") | AD6: =IF(Y6=1,IFERROR(IF(AC6>='參數'!$B$9,INDEX('分群統計'!$G$13:$K$16,MATCH(X6,'分群統計'!$A$13:$A$16,0),MATCH(V6,'分群統計'!$G$12:$K$12,0)),INDEX('分群統計'!$I$5:$I$8,MATCH(X6,'分群統計'!$A$5:$A$8,0))),""),"") | AE6: =IF(Y6=1,IFERROR(IF(AC6>='參數'!$B$9,INDEX('分群統計'!$L$13:$P$16,MATCH(X6,'分群統計'!$A$13:$A$16,0),MATCH(V6,'分群統計'!$L$12:$P$12,0)),INDEX('分群統計'!$J$5:$J$8,MATCH(X6,'分群統計'!$A$5:$A$8,0))),""),"") | AF6: =IF(ISNUMBER(AE6),IF(AE6>0,MAX(-3,MIN(3,(N6-AD6)/AE6)),0),"") | AG6: =IF(Y6=1,COUNTIFS($B$5:$B$404,B6,$Y$5:$Y$404,1),"") | AH6: =IF(Y6=1,IFERROR(IF(ISNUMBER(INDEX('分群統計'!$G$20:$G$59,MATCH(B6,'分群統計'!$A$20:$A$59,0))),INDEX('分群統計'!$H$20:$H$59,MATCH(B6,'分群統計'!$A$20:$A$59,0))+INDEX('分群統計'!$G$20:$G$59,MATCH(B6,'分群統計'!$A$20:$A$59,0))*AU6,""),""),"") | AI6: =IF(ISNUMBER(AH6),N6-AH6,"") | AJ6: =IF(Y6=1,IFERROR(IF(ISNUMBER(INDEX('分群統計'!$G$5:$G$8,MATCH(X6,'分群統計'!$A$5:$A$8,0))),INDEX('分群統計'!$H$5:$H$8,MATCH(X6,'分群統計'!$A$5:$A$8,0))+INDEX('分群統計'!$G$5:$G$8,MATCH(X6,'分群統計'!$A$5:$A$8,0))*AU6,""),""),"") | AK6: =IF(ISNUMBER(AJ6),N6-AJ6,"") | AL6: =IF(ISNUMBER(AJ6),IF(AJ6>0,AK6/AJ6,""),"") | AM6: =IF(AY6<>1,"",IFERROR(IF(INDEX('分群統計'!$K$5:$K$8,MATCH(X6,'分群統計'!$A$5:$A$8,0))<3,"",IF(INDEX('分群統計'!$M$5:$M$8,MATCH(X6,'分群統計'!$A$5:$A$8,0))>0,MAX(-3,MIN(3,(AX6-INDEX('分群統計'!$L$5:$L$8,MATCH(X6,'分群統計'!$A$5:$A$8,0)))/INDEX('分群統計'!$M$5:$M$8,MATCH(X6,'分群統計'!$A$5:$A$8,0)))),0)),"")) | AN6: =IF(ISNUMBER(AB6),IF(Z6>0,AB6/Z6*100,""),"") | AO6: =IF(BA6<>1,"",IFERROR(IF(INDEX('分群統計'!$N$5:$N$8,MATCH(X6,'分群統計'!$A$5:$A$8,0))<3,"",IF(INDEX('分群統計'!$P$5:$P$8,MATCH(X6,'分群統計'!$A$5:$A$8,0))>0,MAX(-3,MIN(3,(AZ6-INDEX('分群統計'!$O$5:$O$8,MATCH(X6,'分群統計'!$A$5:$A$8,0)))/INDEX('分群統計'!$P$5:$P$8,MATCH(X6,'分群統計'!$A$5:$A$8,0)))),0)),"")) | AP6: =IF(BC6<>1,"",IFERROR(IF(INDEX('分群統計'!$Q$5:$Q$8,MATCH(X6,'分群統計'!$A$5:$A$8,0))<3,"",IF(INDEX('分群統計'!$S$5:$S$8,MATCH(X6,'分群統計'!$A$5:$A$8,0))>0,MAX(-3,MIN(3,(BB6-INDEX('分群統計'!$R$5:$R$8,MATCH(X6,'分群統計'!$A$5:$A$8,0)))/INDEX('分群統計'!$S$5:$S$8,MATCH(X6,'分群統計'!$A$5:$A$8,0)))),0)),"")) | AQ6: =IF(Y6=1,(IF(ISNUMBER(AF6),AF6,0)*'參數'!$B$13+IF(ISNUMBER(AM6),AM6,0)*'參數'!$B$14+IF(ISNUMBER(AO6),AO6,0)*'參數'!$B$15+IF(ISNUMBER(AP6),AP6,0)*'參數'!$B$16)/('參數'!$B$13+'參數'!$B$14+'參數'!$B$15+'參數'!$B$16),"") | AR6: =IF(Y6=1,(SUMPRODUCT(($X$5:$X$404=X6)*($Y$5:$Y$404=1)*($BD$5:$BD$404>BD6))+1)/COUNTIFS($X$5:$X$404,X6,$Y$5:$Y$404,1),"") | AS6: =IF(ISNUMBER(AR6),IF(AR6<='參數'!$B$18,"加碼候選",IF(AR6>'參數'!$B$19,"減碼候選","")),"") | AT6: =IF(Y6=1,N6,0) | AU6: =IF(Y6=1,LN(O6),0) | AV6: =IF(Y6=1,IF(ISNUMBER(F6),F6,0),0) | AW6: =IF(Y6=1,Z6,0) | AX6: =IF(Y6=1,IF(ISNUMBER(AL6),AL6,0),0) | AY6: =IF(Y6=1,IF(ISNUMBER(AL6),1,0),0) | AZ6: =IF(Y6=1,IF(ISNUMBER(AN6),AN6,0),0) | BA6: =IF(Y6=1,IF(ISNUMBER(AN6),1,0),0) | BB6: =IF(Y6=1,IF(ISNUMBER(T6),T6,0),0) | BC6: =IF(Y6=1,IF(ISNUMBER(T6),1,0),0) | BD6: =IF(Y6=1,AQ6+ROW()/1E9,-1E9) | BE6: =IF(Y6=1,AQ6+ROW()/1E9,1E9)
B7: =IF($A7="","",BDP($A7,B$3)) | C7: =IF($A7="","",BDP($A7,C$3)) | D7: =IF($A7="","",BDP($A7,D$3)) | E7: =IF($A7="","",BDP($A7,E$3)) | F7: =IF($A7="","",BDP($A7,F$3)) | G7: =IF($A7="","",BDP($A7,G$3)) | H7: =IF($A7="","",BDP($A7,H$3)) | I7: =IF($A7="","",BDP($A7,I$3)) | ... O7: =IF($A7="","",BDP($A7,O$3)) | P7: =IF($A7="","",BDH($A7,$N$3,'參數'!$B$5,'參數'!$B$5,"Days=A","Fill=P","Dates=H")) | Q7: =IF($A7="","",BDH($A7,$N$3,'參數'!$B$6,'參數'!$B$6,"Days=A","Fill=P","Dates=H")) | R7: =IF($A7="","",BDH($A7,$N$3,'參數'!$B$7,'參數'!$B$7,"Days=A","Fill=P","Dates=H")) | S7: =IF($A7="","",IFERROR(INDEX('發行人'!$A$5:$A$44,MATCH(B7,'發行人'!$D$5:$D$44,0)),"未對應")) | T7: =IF($A7="","",IFERROR(INDEX('發行人'!$G$5:$G$44,MATCH(B7,'發行人'!$D$5:$D$44,0))+0,"")) | U7: =IF(ISNUMBER(E7),YEARFRAC('參數'!$B$4,E7),"") | V7: =IF(U7="","",IF(U7<3,"1-3y",IF(U7<5,"3-5y",IF(U7<7,"5-7y",IF(U7<10,"7-10y","10y+"))))) | W7: =IF($A7="","",IFERROR(INDEX('參數'!$B$24:$B$45,MATCH(G7,'參數'!$A$24:$A$45,0)),"")) | X7: =IF($A7="","",IFERROR(INDEX('參數'!$C$24:$C$45,MATCH(G7,'參數'!$A$24:$A$45,0)),"")) | Y7: =IF(AND(ISNUMBER(N7),ISNUMBER(O7),ISNUMBER(U7)),IF(AND(O7>0,X7<>""),1,0),0) | Z7: =IF(Y7=1,O7*N7,"") | AA7: =IF(Y7=1,IF(ISNUMBER(Q7),N7-Q7,""),"") | AB7: =IF(Y7=1,IF(AND(ISNUMBER(P7),ISNUMBER(R7)),R7*5/12-O7*(P7-R7),""),"") | AC7: =IF(Y7=1,COUNTIFS($X$5:$X$404,X7,$V$5:$V$404,V7,$Y$5:$Y$404,1),"") | AD7: =IF(Y7=1,IFERROR(IF(AC7>='參數'!$B$9,INDEX('分群統計'!$G$13:$K$16,MATCH(X7,'分群統計'!$A$13:$A$16,0),MATCH(V7,'分群統計'!$G$12:$K$12,0)),INDEX('分群統計'!$I$5:$I$8,MATCH(X7,'分群統計'!$A$5:$A$8,0))),""),"") | AE7: =IF(Y7=1,IFERROR(IF(AC7>='參數'!$B$9,INDEX('分群統計'!$L$13:$P$16,MATCH(X7,'分群統計'!$A$13:$A$16,0),MATCH(V7,'分群統計'!$L$12:$P$12,0)),INDEX('分群統計'!$J$5:$J$8,MATCH(X7,'分群統計'!$A$5:$A$8,0))),""),"") | AF7: =IF(ISNUMBER(AE7),IF(AE7>0,MAX(-3,MIN(3,(N7-AD7)/AE7)),0),"") | AG7: =IF(Y7=1,COUNTIFS($B$5:$B$404,B7,$Y$5:$Y$404,1),"") | AH7: =IF(Y7=1,IFERROR(IF(ISNUMBER(INDEX('分群統計'!$G$20:$G$59,MATCH(B7,'分群統計'!$A$20:$A$59,0))),INDEX('分群統計'!$H$20:$H$59,MATCH(B7,'分群統計'!$A$20:$A$59,0))+INDEX('分群統計'!$G$20:$G$59,MATCH(B7,'分群統計'!$A$20:$A$59,0))*AU7,""),""),"") | AI7: =IF(ISNUMBER(AH7),N7-AH7,"") | AJ7: =IF(Y7=1,IFERROR(IF(ISNUMBER(INDEX('分群統計'!$G$5:$G$8,MATCH(X7,'分群統計'!$A$5:$A$8,0))),INDEX('分群統計'!$H$5:$H$8,MATCH(X7,'分群統計'!$A$5:$A$8,0))+INDEX('分群統計'!$G$5:$G$8,MATCH(X7,'分群統計'!$A$5:$A$8,0))*AU7,""),""),"") | AK7: =IF(ISNUMBER(AJ7),N7-AJ7,"") | AL7: =IF(ISNUMBER(AJ7),IF(AJ7>0,AK7/AJ7,""),"") | AM7: =IF(AY7<>1,"",IFERROR(IF(INDEX('分群統計'!$K$5:$K$8,MATCH(X7,'分群統計'!$A$5:$A$8,0))<3,"",IF(INDEX('分群統計'!$M$5:$M$8,MATCH(X7,'分群統計'!$A$5:$A$8,0))>0,MAX(-3,MIN(3,(AX7-INDEX('分群統計'!$L$5:$L$8,MATCH(X7,'分群統計'!$A$5:$A$8,0)))/INDEX('分群統計'!$M$5:$M$8,MATCH(X7,'分群統計'!$A$5:$A$8,0)))),0)),"")) | AN7: =IF(ISNUMBER(AB7),IF(Z7>0,AB7/Z7*100,""),"") | AO7: =IF(BA7<>1,"",IFERROR(IF(INDEX('分群統計'!$N$5:$N$8,MATCH(X7,'分群統計'!$A$5:$A$8,0))<3,"",IF(INDEX('分群統計'!$P$5:$P$8,MATCH(X7,'分群統計'!$A$5:$A$8,0))>0,MAX(-3,MIN(3,(AZ7-INDEX('分群統計'!$O$5:$O$8,MATCH(X7,'分群統計'!$A$5:$A$8,0)))/INDEX('分群統計'!$P$5:$P$8,MATCH(X7,'分群統計'!$A$5:$A$8,0)))),0)),"")) | AP7: =IF(BC7<>1,"",IFERROR(IF(INDEX('分群統計'!$Q$5:$Q$8,MATCH(X7,'分群統計'!$A$5:$A$8,0))<3,"",IF(INDEX('分群統計'!$S$5:$S$8,MATCH(X7,'分群統計'!$A$5:$A$8,0))>0,MAX(-3,MIN(3,(BB7-INDEX('分群統計'!$R$5:$R$8,MATCH(X7,'分群統計'!$A$5:$A$8,0)))/INDEX('分群統計'!$S$5:$S$8,MATCH(X7,'分群統計'!$A$5:$A$8,0)))),0)),"")) | AQ7: =IF(Y7=1,(IF(ISNUMBER(AF7),AF7,0)*'參數'!$B$13+IF(ISNUMBER(AM7),AM7,0)*'參數'!$B$14+IF(ISNUMBER(AO7),AO7,0)*'參數'!$B$15+IF(ISNUMBER(AP7),AP7,0)*'參數'!$B$16)/('參數'!$B$13+'參數'!$B$14+'參數'!$B$15+'參數'!$B$16),"") | AR7: =IF(Y7=1,(SUMPRODUCT(($X$5:$X$404=X7)*($Y$5:$Y$404=1)*($BD$5:$BD$404>BD7))+1)/COUNTIFS($X$5:$X$404,X7,$Y$5:$Y$404,1),"") | AS7: =IF(ISNUMBER(AR7),IF(AR7<='參數'!$B$18,"加碼候選",IF(AR7>'參數'!$B$19,"減碼候選","")),"") | AT7: =IF(Y7=1,N7,0) | AU7: =IF(Y7=1,LN(O7),0) | AV7: =IF(Y7=1,IF(ISNUMBER(F7),F7,0),0) | AW7: =IF(Y7=1,Z7,0) | AX7: =IF(Y7=1,IF(ISNUMBER(AL7),AL7,0),0) | AY7: =IF(Y7=1,IF(ISNUMBER(AL7),1,0),0) | AZ7: =IF(Y7=1,IF(ISNUMBER(AN7),AN7,0),0) | BA7: =IF(Y7=1,IF(ISNUMBER(AN7),1,0),0) | BB7: =IF(Y7=1,IF(ISNUMBER(T7),T7,0),0) | BC7: =IF(Y7=1,IF(ISNUMBER(T7),1,0),0) | BD7: =IF(Y7=1,AQ7+ROW()/1E9,-1E9) | BE7: =IF(Y7=1,AQ7+ROW()/1E9,1E9)
B8: =IF($A8="","",BDP($A8,B$3)) | C8: =IF($A8="","",BDP($A8,C$3)) | D8: =IF($A8="","",BDP($A8,D$3)) | E8: =IF($A8="","",BDP($A8,E$3)) | F8: =IF($A8="","",BDP($A8,F$3)) | G8: =IF($A8="","",BDP($A8,G$3)) | H8: =IF($A8="","",BDP($A8,H$3)) | I8: =IF($A8="","",BDP($A8,I$3)) | ... O8: =IF($A8="","",BDP($A8,O$3)) | P8: =IF($A8="","",BDH($A8,$N$3,'參數'!$B$5,'參數'!$B$5,"Days=A","Fill=P","Dates=H")) | Q8: =IF($A8="","",BDH($A8,$N$3,'參數'!$B$6,'參數'!$B$6,"Days=A","Fill=P","Dates=H")) | R8: =IF($A8="","",BDH($A8,$N$3,'參數'!$B$7,'參數'!$B$7,"Days=A","Fill=P","Dates=H")) | S8: =IF($A8="","",IFERROR(INDEX('發行人'!$A$5:$A$44,MATCH(B8,'發行人'!$D$5:$D$44,0)),"未對應")) | T8: =IF($A8="","",IFERROR(INDEX('發行人'!$G$5:$G$44,MATCH(B8,'發行人'!$D$5:$D$44,0))+0,"")) | U8: =IF(ISNUMBER(E8),YEARFRAC('參數'!$B$4,E8),"") | V8: =IF(U8="","",IF(U8<3,"1-3y",IF(U8<5,"3-5y",IF(U8<7,"5-7y",IF(U8<10,"7-10y","10y+"))))) | W8: =IF($A8="","",IFERROR(INDEX('參數'!$B$24:$B$45,MATCH(G8,'參數'!$A$24:$A$45,0)),"")) | X8: =IF($A8="","",IFERROR(INDEX('參數'!$C$24:$C$45,MATCH(G8,'參數'!$A$24:$A$45,0)),"")) | Y8: =IF(AND(ISNUMBER(N8),ISNUMBER(O8),ISNUMBER(U8)),IF(AND(O8>0,X8<>""),1,0),0) | Z8: =IF(Y8=1,O8*N8,"") | AA8: =IF(Y8=1,IF(ISNUMBER(Q8),N8-Q8,""),"") | AB8: =IF(Y8=1,IF(AND(ISNUMBER(P8),ISNUMBER(R8)),R8*5/12-O8*(P8-R8),""),"") | AC8: =IF(Y8=1,COUNTIFS($X$5:$X$404,X8,$V$5:$V$404,V8,$Y$5:$Y$404,1),"") | AD8: =IF(Y8=1,IFERROR(IF(AC8>='參數'!$B$9,INDEX('分群統計'!$G$13:$K$16,MATCH(X8,'分群統計'!$A$13:$A$16,0),MATCH(V8,'分群統計'!$G$12:$K$12,0)),INDEX('分群統計'!$I$5:$I$8,MATCH(X8,'分群統計'!$A$5:$A$8,0))),""),"") | AE8: =IF(Y8=1,IFERROR(IF(AC8>='參數'!$B$9,INDEX('分群統計'!$L$13:$P$16,MATCH(X8,'分群統計'!$A$13:$A$16,0),MATCH(V8,'分群統計'!$L$12:$P$12,0)),INDEX('分群統計'!$J$5:$J$8,MATCH(X8,'分群統計'!$A$5:$A$8,0))),""),"") | AF8: =IF(ISNUMBER(AE8),IF(AE8>0,MAX(-3,MIN(3,(N8-AD8)/AE8)),0),"") | AG8: =IF(Y8=1,COUNTIFS($B$5:$B$404,B8,$Y$5:$Y$404,1),"") | AH8: =IF(Y8=1,IFERROR(IF(ISNUMBER(INDEX('分群統計'!$G$20:$G$59,MATCH(B8,'分群統計'!$A$20:$A$59,0))),INDEX('分群統計'!$H$20:$H$59,MATCH(B8,'分群統計'!$A$20:$A$59,0))+INDEX('分群統計'!$G$20:$G$59,MATCH(B8,'分群統計'!$A$20:$A$59,0))*AU8,""),""),"") | AI8: =IF(ISNUMBER(AH8),N8-AH8,"") | AJ8: =IF(Y8=1,IFERROR(IF(ISNUMBER(INDEX('分群統計'!$G$5:$G$8,MATCH(X8,'分群統計'!$A$5:$A$8,0))),INDEX('分群統計'!$H$5:$H$8,MATCH(X8,'分群統計'!$A$5:$A$8,0))+INDEX('分群統計'!$G$5:$G$8,MATCH(X8,'分群統計'!$A$5:$A$8,0))*AU8,""),""),"") | AK8: =IF(ISNUMBER(AJ8),N8-AJ8,"") | AL8: =IF(ISNUMBER(AJ8),IF(AJ8>0,AK8/AJ8,""),"") | AM8: =IF(AY8<>1,"",IFERROR(IF(INDEX('分群統計'!$K$5:$K$8,MATCH(X8,'分群統計'!$A$5:$A$8,0))<3,"",IF(INDEX('分群統計'!$M$5:$M$8,MATCH(X8,'分群統計'!$A$5:$A$8,0))>0,MAX(-3,MIN(3,(AX8-INDEX('分群統計'!$L$5:$L$8,MATCH(X8,'分群統計'!$A$5:$A$8,0)))/INDEX('分群統計'!$M$5:$M$8,MATCH(X8,'分群統計'!$A$5:$A$8,0)))),0)),"")) | AN8: =IF(ISNUMBER(AB8),IF(Z8>0,AB8/Z8*100,""),"") | AO8: =IF(BA8<>1,"",IFERROR(IF(INDEX('分群統計'!$N$5:$N$8,MATCH(X8,'分群統計'!$A$5:$A$8,0))<3,"",IF(INDEX('分群統計'!$P$5:$P$8,MATCH(X8,'分群統計'!$A$5:$A$8,0))>0,MAX(-3,MIN(3,(AZ8-INDEX('分群統計'!$O$5:$O$8,MATCH(X8,'分群統計'!$A$5:$A$8,0)))/INDEX('分群統計'!$P$5:$P$8,MATCH(X8,'分群統計'!$A$5:$A$8,0)))),0)),"")) | AP8: =IF(BC8<>1,"",IFERROR(IF(INDEX('分群統計'!$Q$5:$Q$8,MATCH(X8,'分群統計'!$A$5:$A$8,0))<3,"",IF(INDEX('分群統計'!$S$5:$S$8,MATCH(X8,'分群統計'!$A$5:$A$8,0))>0,MAX(-3,MIN(3,(BB8-INDEX('分群統計'!$R$5:$R$8,MATCH(X8,'分群統計'!$A$5:$A$8,0)))/INDEX('分群統計'!$S$5:$S$8,MATCH(X8,'分群統計'!$A$5:$A$8,0)))),0)),"")) | AQ8: =IF(Y8=1,(IF(ISNUMBER(AF8),AF8,0)*'參數'!$B$13+IF(ISNUMBER(AM8),AM8,0)*'參數'!$B$14+IF(ISNUMBER(AO8),AO8,0)*'參數'!$B$15+IF(ISNUMBER(AP8),AP8,0)*'參數'!$B$16)/('參數'!$B$13+'參數'!$B$14+'參數'!$B$15+'參數'!$B$16),"") | AR8: =IF(Y8=1,(SUMPRODUCT(($X$5:$X$404=X8)*($Y$5:$Y$404=1)*($BD$5:$BD$404>BD8))+1)/COUNTIFS($X$5:$X$404,X8,$Y$5:$Y$404,1),"") | AS8: =IF(ISNUMBER(AR8),IF(AR8<='參數'!$B$18,"加碼候選",IF(AR8>'參數'!$B$19,"減碼候選","")),"") | AT8: =IF(Y8=1,N8,0) | AU8: =IF(Y8=1,LN(O8),0) | AV8: =IF(Y8=1,IF(ISNUMBER(F8),F8,0),0) | AW8: =IF(Y8=1,Z8,0) | AX8: =IF(Y8=1,IF(ISNUMBER(AL8),AL8,0),0) | AY8: =IF(Y8=1,IF(ISNUMBER(AL8),1,0),0) | AZ8: =IF(Y8=1,IF(ISNUMBER(AN8),AN8,0),0) | BA8: =IF(Y8=1,IF(ISNUMBER(AN8),1,0),0) | BB8: =IF(Y8=1,IF(ISNUMBER(T8),T8,0),0) | BC8: =IF(Y8=1,IF(ISNUMBER(T8),1,0),0) | BD8: =IF(Y8=1,AQ8+ROW()/1E9,-1E9) | BE8: =IF(Y8=1,AQ8+ROW()/1E9,1E9)
B9: =IF($A9="","",BDP($A9,B$3)) | C9: =IF($A9="","",BDP($A9,C$3)) | D9: =IF($A9="","",BDP($A9,D$3)) | E9: =IF($A9="","",BDP($A9,E$3)) | F9: =IF($A9="","",BDP($A9,F$3)) | G9: =IF($A9="","",BDP($A9,G$3)) | H9: =IF($A9="","",BDP($A9,H$3)) | I9: =IF($A9="","",BDP($A9,I$3)) | ... O9: =IF($A9="","",BDP($A9,O$3)) | P9: =IF($A9="","",BDH($A9,$N$3,'參數'!$B$5,'參數'!$B$5,"Days=A","Fill=P","Dates=H")) | Q9: =IF($A9="","",BDH($A9,$N$3,'參數'!$B$6,'參數'!$B$6,"Days=A","Fill=P","Dates=H")) | R9: =IF($A9="","",BDH($A9,$N$3,'參數'!$B$7,'參數'!$B$7,"Days=A","Fill=P","Dates=H")) | S9: =IF($A9="","",IFERROR(INDEX('發行人'!$A$5:$A$44,MATCH(B9,'發行人'!$D$5:$D$44,0)),"未對應")) | T9: =IF($A9="","",IFERROR(INDEX('發行人'!$G$5:$G$44,MATCH(B9,'發行人'!$D$5:$D$44,0))+0,"")) | U9: =IF(ISNUMBER(E9),YEARFRAC('參數'!$B$4,E9),"") | V9: =IF(U9="","",IF(U9<3,"1-3y",IF(U9<5,"3-5y",IF(U9<7,"5-7y",IF(U9<10,"7-10y","10y+"))))) | W9: =IF($A9="","",IFERROR(INDEX('參數'!$B$24:$B$45,MATCH(G9,'參數'!$A$24:$A$45,0)),"")) | X9: =IF($A9="","",IFERROR(INDEX('參數'!$C$24:$C$45,MATCH(G9,'參數'!$A$24:$A$45,0)),"")) | Y9: =IF(AND(ISNUMBER(N9),ISNUMBER(O9),ISNUMBER(U9)),IF(AND(O9>0,X9<>""),1,0),0) | Z9: =IF(Y9=1,O9*N9,"") | AA9: =IF(Y9=1,IF(ISNUMBER(Q9),N9-Q9,""),"") | AB9: =IF(Y9=1,IF(AND(ISNUMBER(P9),ISNUMBER(R9)),R9*5/12-O9*(P9-R9),""),"") | AC9: =IF(Y9=1,COUNTIFS($X$5:$X$404,X9,$V$5:$V$404,V9,$Y$5:$Y$404,1),"") | AD9: =IF(Y9=1,IFERROR(IF(AC9>='參數'!$B$9,INDEX('分群統計'!$G$13:$K$16,MATCH(X9,'分群統計'!$A$13:$A$16,0),MATCH(V9,'分群統計'!$G$12:$K$12,0)),INDEX('分群統計'!$I$5:$I$8,MATCH(X9,'分群統計'!$A$5:$A$8,0))),""),"") | AE9: =IF(Y9=1,IFERROR(IF(AC9>='參數'!$B$9,INDEX('分群統計'!$L$13:$P$16,MATCH(X9,'分群統計'!$A$13:$A$16,0),MATCH(V9,'分群統計'!$L$12:$P$12,0)),INDEX('分群統計'!$J$5:$J$8,MATCH(X9,'分群統計'!$A$5:$A$8,0))),""),"") | AF9: =IF(ISNUMBER(AE9),IF(AE9>0,MAX(-3,MIN(3,(N9-AD9)/AE9)),0),"") | AG9: =IF(Y9=1,COUNTIFS($B$5:$B$404,B9,$Y$5:$Y$404,1),"") | AH9: =IF(Y9=1,IFERROR(IF(ISNUMBER(INDEX('分群統計'!$G$20:$G$59,MATCH(B9,'分群統計'!$A$20:$A$59,0))),INDEX('分群統計'!$H$20:$H$59,MATCH(B9,'分群統計'!$A$20:$A$59,0))+INDEX('分群統計'!$G$20:$G$59,MATCH(B9,'分群統計'!$A$20:$A$59,0))*AU9,""),""),"") | AI9: =IF(ISNUMBER(AH9),N9-AH9,"") | AJ9: =IF(Y9=1,IFERROR(IF(ISNUMBER(INDEX('分群統計'!$G$5:$G$8,MATCH(X9,'分群統計'!$A$5:$A$8,0))),INDEX('分群統計'!$H$5:$H$8,MATCH(X9,'分群統計'!$A$5:$A$8,0))+INDEX('分群統計'!$G$5:$G$8,MATCH(X9,'分群統計'!$A$5:$A$8,0))*AU9,""),""),"") | AK9: =IF(ISNUMBER(AJ9),N9-AJ9,"") | AL9: =IF(ISNUMBER(AJ9),IF(AJ9>0,AK9/AJ9,""),"") | AM9: =IF(AY9<>1,"",IFERROR(IF(INDEX('分群統計'!$K$5:$K$8,MATCH(X9,'分群統計'!$A$5:$A$8,0))<3,"",IF(INDEX('分群統計'!$M$5:$M$8,MATCH(X9,'分群統計'!$A$5:$A$8,0))>0,MAX(-3,MIN(3,(AX9-INDEX('分群統計'!$L$5:$L$8,MATCH(X9,'分群統計'!$A$5:$A$8,0)))/INDEX('分群統計'!$M$5:$M$8,MATCH(X9,'分群統計'!$A$5:$A$8,0)))),0)),"")) | AN9: =IF(ISNUMBER(AB9),IF(Z9>0,AB9/Z9*100,""),"") | AO9: =IF(BA9<>1,"",IFERROR(IF(INDEX('分群統計'!$N$5:$N$8,MATCH(X9,'分群統計'!$A$5:$A$8,0))<3,"",IF(INDEX('分群統計'!$P$5:$P$8,MATCH(X9,'分群統計'!$A$5:$A$8,0))>0,MAX(-3,MIN(3,(AZ9-INDEX('分群統計'!$O$5:$O$8,MATCH(X9,'分群統計'!$A$5:$A$8,0)))/INDEX('分群統計'!$P$5:$P$8,MATCH(X9,'分群統計'!$A$5:$A$8,0)))),0)),"")) | AP9: =IF(BC9<>1,"",IFERROR(IF(INDEX('分群統計'!$Q$5:$Q$8,MATCH(X9,'分群統計'!$A$5:$A$8,0))<3,"",IF(INDEX('分群統計'!$S$5:$S$8,MATCH(X9,'分群統計'!$A$5:$A$8,0))>0,MAX(-3,MIN(3,(BB9-INDEX('分群統計'!$R$5:$R$8,MATCH(X9,'分群統計'!$A$5:$A$8,0)))/INDEX('分群統計'!$S$5:$S$8,MATCH(X9,'分群統計'!$A$5:$A$8,0)))),0)),"")) | AQ9: =IF(Y9=1,(IF(ISNUMBER(AF9),AF9,0)*'參數'!$B$13+IF(ISNUMBER(AM9),AM9,0)*'參數'!$B$14+IF(ISNUMBER(AO9),AO9,0)*'參數'!$B$15+IF(ISNUMBER(AP9),AP9,0)*'參數'!$B$16)/('參數'!$B$13+'參數'!$B$14+'參數'!$B$15+'參數'!$B$16),"") | AR9: =IF(Y9=1,(SUMPRODUCT(($X$5:$X$404=X9)*($Y$5:$Y$404=1)*($BD$5:$BD$404>BD9))+1)/COUNTIFS($X$5:$X$404,X9,$Y$5:$Y$404,1),"") | AS9: =IF(ISNUMBER(AR9),IF(AR9<='參數'!$B$18,"加碼候選",IF(AR9>'參數'!$B$19,"減碼候選","")),"") | AT9: =IF(Y9=1,N9,0) | AU9: =IF(Y9=1,LN(O9),0) | AV9: =IF(Y9=1,IF(ISNUMBER(F9),F9,0),0) | AW9: =IF(Y9=1,Z9,0) | AX9: =IF(Y9=1,IF(ISNUMBER(AL9),AL9,0),0) | AY9: =IF(Y9=1,IF(ISNUMBER(AL9),1,0),0) | AZ9: =IF(Y9=1,IF(ISNUMBER(AN9),AN9,0),0) | BA9: =IF(Y9=1,IF(ISNUMBER(AN9),1,0),0) | BB9: =IF(Y9=1,IF(ISNUMBER(T9),T9,0),0) | BC9: =IF(Y9=1,IF(ISNUMBER(T9),1,0),0) | BD9: =IF(Y9=1,AQ9+ROW()/1E9,-1E9) | BE9: =IF(Y9=1,AQ9+ROW()/1E9,1E9)
B10: =IF($A10="","",BDP($A10,B$3)) | C10: =IF($A10="","",BDP($A10,C$3)) | D10: =IF($A10="","",BDP($A10,D$3)) | E10: =IF($A10="","",BDP($A10,E$3)) | F10: =IF($A10="","",BDP($A10,F$3)) | G10: =IF($A10="","",BDP($A10,G$3)) | H10: =IF($A10="","",BDP($A10,H$3)) | I10: =IF($A10="","",BDP($A10,I$3)) | ... O10: =IF($A10="","",BDP($A10,O$3)) | P10: =IF($A10="","",BDH($A10,$N$3,'參數'!$B$5,'參數'!$B$5,"Days=A","Fill=P","Dates=H")) | Q10: =IF($A10="","",BDH($A10,$N$3,'參數'!$B$6,'參數'!$B$6,"Days=A","Fill=P","Dates=H")) | R10: =IF($A10="","",BDH($A10,$N$3,'參數'!$B$7,'參數'!$B$7,"Days=A","Fill=P","Dates=H")) | S10: =IF($A10="","",IFERROR(INDEX('發行人'!$A$5:$A$44,MATCH(B10,'發行人'!$D$5:$D$44,0)),"未對應")) | T10: =IF($A10="","",IFERROR(INDEX('發行人'!$G$5:$G$44,MATCH(B10,'發行人'!$D$5:$D$44,0))+0,"")) | U10: =IF(ISNUMBER(E10),YEARFRAC('參數'!$B$4,E10),"") | V10: =IF(U10="","",IF(U10<3,"1-3y",IF(U10<5,"3-5y",IF(U10<7,"5-7y",IF(U10<10,"7-10y","10y+"))))) | W10: =IF($A10="","",IFERROR(INDEX('參數'!$B$24:$B$45,MATCH(G10,'參數'!$A$24:$A$45,0)),"")) | X10: =IF($A10="","",IFERROR(INDEX('參數'!$C$24:$C$45,MATCH(G10,'參數'!$A$24:$A$45,0)),"")) | Y10: =IF(AND(ISNUMBER(N10),ISNUMBER(O10),ISNUMBER(U10)),IF(AND(O10>0,X10<>""),1,0),0) | Z10: =IF(Y10=1,O10*N10,"") | AA10: =IF(Y10=1,IF(ISNUMBER(Q10),N10-Q10,""),"") | AB10: =IF(Y10=1,IF(AND(ISNUMBER(P10),ISNUMBER(R10)),R10*5/12-O10*(P10-R10),""),"") | AC10: =IF(Y10=1,COUNTIFS($X$5:$X$404,X10,$V$5:$V$404,V10,$Y$5:$Y$404,1),"") | AD10: =IF(Y10=1,IFERROR(IF(AC10>='參數'!$B$9,INDEX('分群統計'!$G$13:$K$16,MATCH(X10,'分群統計'!$A$13:$A$16,0),MATCH(V10,'分群統計'!$G$12:$K$12,0)),INDEX('分群統計'!$I$5:$I$8,MATCH(X10,'分群統計'!$A$5:$A$8,0))),""),"") | AE10: =IF(Y10=1,IFERROR(IF(AC10>='參數'!$B$9,INDEX('分群統計'!$L$13:$P$16,MATCH(X10,'分群統計'!$A$13:$A$16,0),MATCH(V10,'分群統計'!$L$12:$P$12,0)),INDEX('分群統計'!$J$5:$J$8,MATCH(X10,'分群統計'!$A$5:$A$8,0))),""),"") | AF10: =IF(ISNUMBER(AE10),IF(AE10>0,MAX(-3,MIN(3,(N10-AD10)/AE10)),0),"") | AG10: =IF(Y10=1,COUNTIFS($B$5:$B$404,B10,$Y$5:$Y$404,1),"") | AH10: =IF(Y10=1,IFERROR(IF(ISNUMBER(INDEX('分群統計'!$G$20:$G$59,MATCH(B10,'分群統計'!$A$20:$A$59,0))),INDEX('分群統計'!$H$20:$H$59,MATCH(B10,'分群統計'!$A$20:$A$59,0))+INDEX('分群統計'!$G$20:$G$59,MATCH(B10,'分群統計'!$A$20:$A$59,0))*AU10,""),""),"") | AI10: =IF(ISNUMBER(AH10),N10-AH10,"") | AJ10: =IF(Y10=1,IFERROR(IF(ISNUMBER(INDEX('分群統計'!$G$5:$G$8,MATCH(X10,'分群統計'!$A$5:$A$8,0))),INDEX('分群統計'!$H$5:$H$8,MATCH(X10,'分群統計'!$A$5:$A$8,0))+INDEX('分群統計'!$G$5:$G$8,MATCH(X10,'分群統計'!$A$5:$A$8,0))*AU10,""),""),"") | AK10: =IF(ISNUMBER(AJ10),N10-AJ10,"") | AL10: =IF(ISNUMBER(AJ10),IF(AJ10>0,AK10/AJ10,""),"") | AM10: =IF(AY10<>1,"",IFERROR(IF(INDEX('分群統計'!$K$5:$K$8,MATCH(X10,'分群統計'!$A$5:$A$8,0))<3,"",IF(INDEX('分群統計'!$M$5:$M$8,MATCH(X10,'分群統計'!$A$5:$A$8,0))>0,MAX(-3,MIN(3,(AX10-INDEX('分群統計'!$L$5:$L$8,MATCH(X10,'分群統計'!$A$5:$A$8,0)))/INDEX('分群統計'!$M$5:$M$8,MATCH(X10,'分群統計'!$A$5:$A$8,0)))),0)),"")) | AN10: =IF(ISNUMBER(AB10),IF(Z10>0,AB10/Z10*100,""),"") | AO10: =IF(BA10<>1,"",IFERROR(IF(INDEX('分群統計'!$N$5:$N$8,MATCH(X10,'分群統計'!$A$5:$A$8,0))<3,"",IF(INDEX('分群統計'!$P$5:$P$8,MATCH(X10,'分群統計'!$A$5:$A$8,0))>0,MAX(-3,MIN(3,(AZ10-INDEX('分群統計'!$O$5:$O$8,MATCH(X10,'分群統計'!$A$5:$A$8,0)))/INDEX('分群統計'!$P$5:$P$8,MATCH(X10,'分群統計'!$A$5:$A$8,0)))),0)),"")) | AP10: =IF(BC10<>1,"",IFERROR(IF(INDEX('分群統計'!$Q$5:$Q$8,MATCH(X10,'分群統計'!$A$5:$A$8,0))<3,"",IF(INDEX('分群統計'!$S$5:$S$8,MATCH(X10,'分群統計'!$A$5:$A$8,0))>0,MAX(-3,MIN(3,(BB10-INDEX('分群統計'!$R$5:$R$8,MATCH(X10,'分群統計'!$A$5:$A$8,0)))/INDEX('分群統計'!$S$5:$S$8,MATCH(X10,'分群統計'!$A$5:$A$8,0)))),0)),"")) | AQ10: =IF(Y10=1,(IF(ISNUMBER(AF10),AF10,0)*'參數'!$B$13+IF(ISNUMBER(AM10),AM10,0)*'參數'!$B$14+IF(ISNUMBER(AO10),AO10,0)*'參數'!$B$15+IF(ISNUMBER(AP10),AP10,0)*'參數'!$B$16)/('參數'!$B$13+'參數'!$B$14+'參數'!$B$15+'參數'!$B$16),"") | AR10: =IF(Y10=1,(SUMPRODUCT(($X$5:$X$404=X10)*($Y$5:$Y$404=1)*($BD$5:$BD$404>BD10))+1)/COUNTIFS($X$5:$X$404,X10,$Y$5:$Y$404,1),"") | AS10: =IF(ISNUMBER(AR10),IF(AR10<='參數'!$B$18,"加碼候選",IF(AR10>'參數'!$B$19,"減碼候選","")),"") | AT10: =IF(Y10=1,N10,0) | AU10: =IF(Y10=1,LN(O10),0) | AV10: =IF(Y10=1,IF(ISNUMBER(F10),F10,0),0) | AW10: =IF(Y10=1,Z10,0) | AX10: =IF(Y10=1,IF(ISNUMBER(AL10),AL10,0),0) | AY10: =IF(Y10=1,IF(ISNUMBER(AL10),1,0),0) | AZ10: =IF(Y10=1,IF(ISNUMBER(AN10),AN10,0),0) | BA10: =IF(Y10=1,IF(ISNUMBER(AN10),1,0),0) | BB10: =IF(Y10=1,IF(ISNUMBER(T10),T10,0),0) | BC10: =IF(Y10=1,IF(ISNUMBER(T10),1,0),0) | BD10: =IF(Y10=1,AQ10+ROW()/1E9,-1E9) | BE10: =IF(Y10=1,AQ10+ROW()/1E9,1E9)
B11: =IF($A11="","",BDP($A11,B$3)) | C11: =IF($A11="","",BDP($A11,C$3)) | D11: =IF($A11="","",BDP($A11,D$3)) | E11: =IF($A11="","",BDP($A11,E$3)) | F11: =IF($A11="","",BDP($A11,F$3)) | G11: =IF($A11="","",BDP($A11,G$3)) | H11: =IF($A11="","",BDP($A11,H$3)) | I11: =IF($A11="","",BDP($A11,I$3)) | ... O11: =IF($A11="","",BDP($A11,O$3)) | P11: =IF($A11="","",BDH($A11,$N$3,'參數'!$B$5,'參數'!$B$5,"Days=A","Fill=P","Dates=H")) | Q11: =IF($A11="","",BDH($A11,$N$3,'參數'!$B$6,'參數'!$B$6,"Days=A","Fill=P","Dates=H")) | R11: =IF($A11="","",BDH($A11,$N$3,'參數'!$B$7,'參數'!$B$7,"Days=A","Fill=P","Dates=H")) | S11: =IF($A11="","",IFERROR(INDEX('發行人'!$A$5:$A$44,MATCH(B11,'發行人'!$D$5:$D$44,0)),"未對應")) | T11: =IF($A11="","",IFERROR(INDEX('發行人'!$G$5:$G$44,MATCH(B11,'發行人'!$D$5:$D$44,0))+0,"")) | U11: =IF(ISNUMBER(E11),YEARFRAC('參數'!$B$4,E11),"") | V11: =IF(U11="","",IF(U11<3,"1-3y",IF(U11<5,"3-5y",IF(U11<7,"5-7y",IF(U11<10,"7-10y","10y+"))))) | W11: =IF($A11="","",IFERROR(INDEX('參數'!$B$24:$B$45,MATCH(G11,'參數'!$A$24:$A$45,0)),"")) | X11: =IF($A11="","",IFERROR(INDEX('參數'!$C$24:$C$45,MATCH(G11,'參數'!$A$24:$A$45,0)),"")) | Y11: =IF(AND(ISNUMBER(N11),ISNUMBER(O11),ISNUMBER(U11)),IF(AND(O11>0,X11<>""),1,0),0) | Z11: =IF(Y11=1,O11*N11,"") | AA11: =IF(Y11=1,IF(ISNUMBER(Q11),N11-Q11,""),"") | AB11: =IF(Y11=1,IF(AND(ISNUMBER(P11),ISNUMBER(R11)),R11*5/12-O11*(P11-R11),""),"") | AC11: =IF(Y11=1,COUNTIFS($X$5:$X$404,X11,$V$5:$V$404,V11,$Y$5:$Y$404,1),"") | AD11: =IF(Y11=1,IFERROR(IF(AC11>='參數'!$B$9,INDEX('分群統計'!$G$13:$K$16,MATCH(X11,'分群統計'!$A$13:$A$16,0),MATCH(V11,'分群統計'!$G$12:$K$12,0)),INDEX('分群統計'!$I$5:$I$8,MATCH(X11,'分群統計'!$A$5:$A$8,0))),""),"") | AE11: =IF(Y11=1,IFERROR(IF(AC11>='參數'!$B$9,INDEX('分群統計'!$L$13:$P$16,MATCH(X11,'分群統計'!$A$13:$A$16,0),MATCH(V11,'分群統計'!$L$12:$P$12,0)),INDEX('分群統計'!$J$5:$J$8,MATCH(X11,'分群統計'!$A$5:$A$8,0))),""),"") | AF11: =IF(ISNUMBER(AE11),IF(AE11>0,MAX(-3,MIN(3,(N11-AD11)/AE11)),0),"") | AG11: =IF(Y11=1,COUNTIFS($B$5:$B$404,B11,$Y$5:$Y$404,1),"") | AH11: =IF(Y11=1,IFERROR(IF(ISNUMBER(INDEX('分群統計'!$G$20:$G$59,MATCH(B11,'分群統計'!$A$20:$A$59,0))),INDEX('分群統計'!$H$20:$H$59,MATCH(B11,'分群統計'!$A$20:$A$59,0))+INDEX('分群統計'!$G$20:$G$59,MATCH(B11,'分群統計'!$A$20:$A$59,0))*AU11,""),""),"") | AI11: =IF(ISNUMBER(AH11),N11-AH11,"") | AJ11: =IF(Y11=1,IFERROR(IF(ISNUMBER(INDEX('分群統計'!$G$5:$G$8,MATCH(X11,'分群統計'!$A$5:$A$8,0))),INDEX('分群統計'!$H$5:$H$8,MATCH(X11,'分群統計'!$A$5:$A$8,0))+INDEX('分群統計'!$G$5:$G$8,MATCH(X11,'分群統計'!$A$5:$A$8,0))*AU11,""),""),"") | AK11: =IF(ISNUMBER(AJ11),N11-AJ11,"") | AL11: =IF(ISNUMBER(AJ11),IF(AJ11>0,AK11/AJ11,""),"") | AM11: =IF(AY11<>1,"",IFERROR(IF(INDEX('分群統計'!$K$5:$K$8,MATCH(X11,'分群統計'!$A$5:$A$8,0))<3,"",IF(INDEX('分群統計'!$M$5:$M$8,MATCH(X11,'分群統計'!$A$5:$A$8,0))>0,MAX(-3,MIN(3,(AX11-INDEX('分群統計'!$L$5:$L$8,MATCH(X11,'分群統計'!$A$5:$A$8,0)))/INDEX('分群統計'!$M$5:$M$8,MATCH(X11,'分群統計'!$A$5:$A$8,0)))),0)),"")) | AN11: =IF(ISNUMBER(AB11),IF(Z11>0,AB11/Z11*100,""),"") | AO11: =IF(BA11<>1,"",IFERROR(IF(INDEX('分群統計'!$N$5:$N$8,MATCH(X11,'分群統計'!$A$5:$A$8,0))<3,"",IF(INDEX('分群統計'!$P$5:$P$8,MATCH(X11,'分群統計'!$A$5:$A$8,0))>0,MAX(-3,MIN(3,(AZ11-INDEX('分群統計'!$O$5:$O$8,MATCH(X11,'分群統計'!$A$5:$A$8,0)))/INDEX('分群統計'!$P$5:$P$8,MATCH(X11,'分群統計'!$A$5:$A$8,0)))),0)),"")) | AP11: =IF(BC11<>1,"",IFERROR(IF(INDEX('分群統計'!$Q$5:$Q$8,MATCH(X11,'分群統計'!$A$5:$A$8,0))<3,"",IF(INDEX('分群統計'!$S$5:$S$8,MATCH(X11,'分群統計'!$A$5:$A$8,0))>0,MAX(-3,MIN(3,(BB11-INDEX('分群統計'!$R$5:$R$8,MATCH(X11,'分群統計'!$A$5:$A$8,0)))/INDEX('分群統計'!$S$5:$S$8,MATCH(X11,'分群統計'!$A$5:$A$8,0)))),0)),"")) | AQ11: =IF(Y11=1,(IF(ISNUMBER(AF11),AF11,0)*'參數'!$B$13+IF(ISNUMBER(AM11),AM11,0)*'參數'!$B$14+IF(ISNUMBER(AO11),AO11,0)*'參數'!$B$15+IF(ISNUMBER(AP11),AP11,0)*'參數'!$B$16)/('參數'!$B$13+'參數'!$B$14+'參數'!$B$15+'參數'!$B$16),"") | AR11: =IF(Y11=1,(SUMPRODUCT(($X$5:$X$404=X11)*($Y$5:$Y$404=1)*($BD$5:$BD$404>BD11))+1)/COUNTIFS($X$5:$X$404,X11,$Y$5:$Y$404,1),"") | AS11: =IF(ISNUMBER(AR11),IF(AR11<='參數'!$B$18,"加碼候選",IF(AR11>'參數'!$B$19,"減碼候選","")),"") | AT11: =IF(Y11=1,N11,0) | AU11: =IF(Y11=1,LN(O11),0) | AV11: =IF(Y11=1,IF(ISNUMBER(F11),F11,0),0) | AW11: =IF(Y11=1,Z11,0) | AX11: =IF(Y11=1,IF(ISNUMBER(AL11),AL11,0),0) | AY11: =IF(Y11=1,IF(ISNUMBER(AL11),1,0),0) | AZ11: =IF(Y11=1,IF(ISNUMBER(AN11),AN11,0),0) | BA11: =IF(Y11=1,IF(ISNUMBER(AN11),1,0),0) | BB11: =IF(Y11=1,IF(ISNUMBER(T11),T11,0),0) | BC11: =IF(Y11=1,IF(ISNUMBER(T11),1,0),0) | BD11: =IF(Y11=1,AQ11+ROW()/1E9,-1E9) | BE11: =IF(Y11=1,AQ11+ROW()/1E9,1E9)
B12: =IF($A12="","",BDP($A12,B$3)) | C12: =IF($A12="","",BDP($A12,C$3)) | D12: =IF($A12="","",BDP($A12,D$3)) | E12: =IF($A12="","",BDP($A12,E$3)) | F12: =IF($A12="","",BDP($A12,F$3)) | G12: =IF($A12="","",BDP($A12,G$3)) | H12: =IF($A12="","",BDP($A12,H$3)) | I12: =IF($A12="","",BDP($A12,I$3)) | ... O12: =IF($A12="","",BDP($A12,O$3)) | P12: =IF($A12="","",BDH($A12,$N$3,'參數'!$B$5,'參數'!$B$5,"Days=A","Fill=P","Dates=H")) | Q12: =IF($A12="","",BDH($A12,$N$3,'參數'!$B$6,'參數'!$B$6,"Days=A","Fill=P","Dates=H")) | R12: =IF($A12="","",BDH($A12,$N$3,'參數'!$B$7,'參數'!$B$7,"Days=A","Fill=P","Dates=H")) | S12: =IF($A12="","",IFERROR(INDEX('發行人'!$A$5:$A$44,MATCH(B12,'發行人'!$D$5:$D$44,0)),"未對應")) | T12: =IF($A12="","",IFERROR(INDEX('發行人'!$G$5:$G$44,MATCH(B12,'發行人'!$D$5:$D$44,0))+0,"")) | U12: =IF(ISNUMBER(E12),YEARFRAC('參數'!$B$4,E12),"") | V12: =IF(U12="","",IF(U12<3,"1-3y",IF(U12<5,"3-5y",IF(U12<7,"5-7y",IF(U12<10,"7-10y","10y+"))))) | W12: =IF($A12="","",IFERROR(INDEX('參數'!$B$24:$B$45,MATCH(G12,'參數'!$A$24:$A$45,0)),"")) | X12: =IF($A12="","",IFERROR(INDEX('參數'!$C$24:$C$45,MATCH(G12,'參數'!$A$24:$A$45,0)),"")) | Y12: =IF(AND(ISNUMBER(N12),ISNUMBER(O12),ISNUMBER(U12)),IF(AND(O12>0,X12<>""),1,0),0) | Z12: =IF(Y12=1,O12*N12,"") | AA12: =IF(Y12=1,IF(ISNUMBER(Q12),N12-Q12,""),"") | AB12: =IF(Y12=1,IF(AND(ISNUMBER(P12),ISNUMBER(R12)),R12*5/12-O12*(P12-R12),""),"") | AC12: =IF(Y12=1,COUNTIFS($X$5:$X$404,X12,$V$5:$V$404,V12,$Y$5:$Y$404,1),"") | AD12: =IF(Y12=1,IFERROR(IF(AC12>='參數'!$B$9,INDEX('分群統計'!$G$13:$K$16,MATCH(X12,'分群統計'!$A$13:$A$16,0),MATCH(V12,'分群統計'!$G$12:$K$12,0)),INDEX('分群統計'!$I$5:$I$8,MATCH(X12,'分群統計'!$A$5:$A$8,0))),""),"") | AE12: =IF(Y12=1,IFERROR(IF(AC12>='參數'!$B$9,INDEX('分群統計'!$L$13:$P$16,MATCH(X12,'分群統計'!$A$13:$A$16,0),MATCH(V12,'分群統計'!$L$12:$P$12,0)),INDEX('分群統計'!$J$5:$J$8,MATCH(X12,'分群統計'!$A$5:$A$8,0))),""),"") | AF12: =IF(ISNUMBER(AE12),IF(AE12>0,MAX(-3,MIN(3,(N12-AD12)/AE12)),0),"") | AG12: =IF(Y12=1,COUNTIFS($B$5:$B$404,B12,$Y$5:$Y$404,1),"") | AH12: =IF(Y12=1,IFERROR(IF(ISNUMBER(INDEX('分群統計'!$G$20:$G$59,MATCH(B12,'分群統計'!$A$20:$A$59,0))),INDEX('分群統計'!$H$20:$H$59,MATCH(B12,'分群統計'!$A$20:$A$59,0))+INDEX('分群統計'!$G$20:$G$59,MATCH(B12,'分群統計'!$A$20:$A$59,0))*AU12,""),""),"") | AI12: =IF(ISNUMBER(AH12),N12-AH12,"") | AJ12: =IF(Y12=1,IFERROR(IF(ISNUMBER(INDEX('分群統計'!$G$5:$G$8,MATCH(X12,'分群統計'!$A$5:$A$8,0))),INDEX('分群統計'!$H$5:$H$8,MATCH(X12,'分群統計'!$A$5:$A$8,0))+INDEX('分群統計'!$G$5:$G$8,MATCH(X12,'分群統計'!$A$5:$A$8,0))*AU12,""),""),"") | AK12: =IF(ISNUMBER(AJ12),N12-AJ12,"") | AL12: =IF(ISNUMBER(AJ12),IF(AJ12>0,AK12/AJ12,""),"") | AM12: =IF(AY12<>1,"",IFERROR(IF(INDEX('分群統計'!$K$5:$K$8,MATCH(X12,'分群統計'!$A$5:$A$8,0))<3,"",IF(INDEX('分群統計'!$M$5:$M$8,MATCH(X12,'分群統計'!$A$5:$A$8,0))>0,MAX(-3,MIN(3,(AX12-INDEX('分群統計'!$L$5:$L$8,MATCH(X12,'分群統計'!$A$5:$A$8,0)))/INDEX('分群統計'!$M$5:$M$8,MATCH(X12,'分群統計'!$A$5:$A$8,0)))),0)),"")) | AN12: =IF(ISNUMBER(AB12),IF(Z12>0,AB12/Z12*100,""),"") | AO12: =IF(BA12<>1,"",IFERROR(IF(INDEX('分群統計'!$N$5:$N$8,MATCH(X12,'分群統計'!$A$5:$A$8,0))<3,"",IF(INDEX('分群統計'!$P$5:$P$8,MATCH(X12,'分群統計'!$A$5:$A$8,0))>0,MAX(-3,MIN(3,(AZ12-INDEX('分群統計'!$O$5:$O$8,MATCH(X12,'分群統計'!$A$5:$A$8,0)))/INDEX('分群統計'!$P$5:$P$8,MATCH(X12,'分群統計'!$A$5:$A$8,0)))),0)),"")) | AP12: =IF(BC12<>1,"",IFERROR(IF(INDEX('分群統計'!$Q$5:$Q$8,MATCH(X12,'分群統計'!$A$5:$A$8,0))<3,"",IF(INDEX('分群統計'!$S$5:$S$8,MATCH(X12,'分群統計'!$A$5:$A$8,0))>0,MAX(-3,MIN(3,(BB12-INDEX('分群統計'!$R$5:$R$8,MATCH(X12,'分群統計'!$A$5:$A$8,0)))/INDEX('分群統計'!$S$5:$S$8,MATCH(X12,'分群統計'!$A$5:$A$8,0)))),0)),"")) | AQ12: =IF(Y12=1,(IF(ISNUMBER(AF12),AF12,0)*'參數'!$B$13+IF(ISNUMBER(AM12),AM12,0)*'參數'!$B$14+IF(ISNUMBER(AO12),AO12,0)*'參數'!$B$15+IF(ISNUMBER(AP12),AP12,0)*'參數'!$B$16)/('參數'!$B$13+'參數'!$B$14+'參數'!$B$15+'參數'!$B$16),"") | AR12: =IF(Y12=1,(SUMPRODUCT(($X$5:$X$404=X12)*($Y$5:$Y$404=1)*($BD$5:$BD$404>BD12))+1)/COUNTIFS($X$5:$X$404,X12,$Y$5:$Y$404,1),"") | AS12: =IF(ISNUMBER(AR12),IF(AR12<='參數'!$B$18,"加碼候選",IF(AR12>'參數'!$B$19,"減碼候選","")),"") | AT12: =IF(Y12=1,N12,0) | AU12: =IF(Y12=1,LN(O12),0) | AV12: =IF(Y12=1,IF(ISNUMBER(F12),F12,0),0) | AW12: =IF(Y12=1,Z12,0) | AX12: =IF(Y12=1,IF(ISNUMBER(AL12),AL12,0),0) | AY12: =IF(Y12=1,IF(ISNUMBER(AL12),1,0),0) | AZ12: =IF(Y12=1,IF(ISNUMBER(AN12),AN12,0),0) | BA12: =IF(Y12=1,IF(ISNUMBER(AN12),1,0),0) | BB12: =IF(Y12=1,IF(ISNUMBER(T12),T12,0),0) | BC12: =IF(Y12=1,IF(ISNUMBER(T12),1,0),0) | BD12: =IF(Y12=1,AQ12+ROW()/1E9,-1E9) | BE12: =IF(Y12=1,AQ12+ROW()/1E9,1E9)
B13: =IF($A13="","",BDP($A13,B$3)) | C13: =IF($A13="","",BDP($A13,C$3)) | D13: =IF($A13="","",BDP($A13,D$3)) | E13: =IF($A13="","",BDP($A13,E$3)) | F13: =IF($A13="","",BDP($A13,F$3)) | G13: =IF($A13="","",BDP($A13,G$3)) | H13: =IF($A13="","",BDP($A13,H$3)) | I13: =IF($A13="","",BDP($A13,I$3)) | ... O13: =IF($A13="","",BDP($A13,O$3)) | P13: =IF($A13="","",BDH($A13,$N$3,'參數'!$B$5,'參數'!$B$5,"Days=A","Fill=P","Dates=H")) | Q13: =IF($A13="","",BDH($A13,$N$3,'參數'!$B$6,'參數'!$B$6,"Days=A","Fill=P","Dates=H")) | R13: =IF($A13="","",BDH($A13,$N$3,'參數'!$B$7,'參數'!$B$7,"Days=A","Fill=P","Dates=H")) | S13: =IF($A13="","",IFERROR(INDEX('發行人'!$A$5:$A$44,MATCH(B13,'發行人'!$D$5:$D$44,0)),"未對應")) | T13: =IF($A13="","",IFERROR(INDEX('發行人'!$G$5:$G$44,MATCH(B13,'發行人'!$D$5:$D$44,0))+0,"")) | U13: =IF(ISNUMBER(E13),YEARFRAC('參數'!$B$4,E13),"") | V13: =IF(U13="","",IF(U13<3,"1-3y",IF(U13<5,"3-5y",IF(U13<7,"5-7y",IF(U13<10,"7-10y","10y+"))))) | W13: =IF($A13="","",IFERROR(INDEX('參數'!$B$24:$B$45,MATCH(G13,'參數'!$A$24:$A$45,0)),"")) | X13: =IF($A13="","",IFERROR(INDEX('參數'!$C$24:$C$45,MATCH(G13,'參數'!$A$24:$A$45,0)),"")) | Y13: =IF(AND(ISNUMBER(N13),ISNUMBER(O13),ISNUMBER(U13)),IF(AND(O13>0,X13<>""),1,0),0) | Z13: =IF(Y13=1,O13*N13,"") | AA13: =IF(Y13=1,IF(ISNUMBER(Q13),N13-Q13,""),"") | AB13: =IF(Y13=1,IF(AND(ISNUMBER(P13),ISNUMBER(R13)),R13*5/12-O13*(P13-R13),""),"") | AC13: =IF(Y13=1,COUNTIFS($X$5:$X$404,X13,$V$5:$V$404,V13,$Y$5:$Y$404,1),"") | AD13: =IF(Y13=1,IFERROR(IF(AC13>='參數'!$B$9,INDEX('分群統計'!$G$13:$K$16,MATCH(X13,'分群統計'!$A$13:$A$16,0),MATCH(V13,'分群統計'!$G$12:$K$12,0)),INDEX('分群統計'!$I$5:$I$8,MATCH(X13,'分群統計'!$A$5:$A$8,0))),""),"") | AE13: =IF(Y13=1,IFERROR(IF(AC13>='參數'!$B$9,INDEX('分群統計'!$L$13:$P$16,MATCH(X13,'分群統計'!$A$13:$A$16,0),MATCH(V13,'分群統計'!$L$12:$P$12,0)),INDEX('分群統計'!$J$5:$J$8,MATCH(X13,'分群統計'!$A$5:$A$8,0))),""),"") | AF13: =IF(ISNUMBER(AE13),IF(AE13>0,MAX(-3,MIN(3,(N13-AD13)/AE13)),0),"") | AG13: =IF(Y13=1,COUNTIFS($B$5:$B$404,B13,$Y$5:$Y$404,1),"") | AH13: =IF(Y13=1,IFERROR(IF(ISNUMBER(INDEX('分群統計'!$G$20:$G$59,MATCH(B13,'分群統計'!$A$20:$A$59,0))),INDEX('分群統計'!$H$20:$H$59,MATCH(B13,'分群統計'!$A$20:$A$59,0))+INDEX('分群統計'!$G$20:$G$59,MATCH(B13,'分群統計'!$A$20:$A$59,0))*AU13,""),""),"") | AI13: =IF(ISNUMBER(AH13),N13-AH13,"") | AJ13: =IF(Y13=1,IFERROR(IF(ISNUMBER(INDEX('分群統計'!$G$5:$G$8,MATCH(X13,'分群統計'!$A$5:$A$8,0))),INDEX('分群統計'!$H$5:$H$8,MATCH(X13,'分群統計'!$A$5:$A$8,0))+INDEX('分群統計'!$G$5:$G$8,MATCH(X13,'分群統計'!$A$5:$A$8,0))*AU13,""),""),"") | AK13: =IF(ISNUMBER(AJ13),N13-AJ13,"") | AL13: =IF(ISNUMBER(AJ13),IF(AJ13>0,AK13/AJ13,""),"") | AM13: =IF(AY13<>1,"",IFERROR(IF(INDEX('分群統計'!$K$5:$K$8,MATCH(X13,'分群統計'!$A$5:$A$8,0))<3,"",IF(INDEX('分群統計'!$M$5:$M$8,MATCH(X13,'分群統計'!$A$5:$A$8,0))>0,MAX(-3,MIN(3,(AX13-INDEX('分群統計'!$L$5:$L$8,MATCH(X13,'分群統計'!$A$5:$A$8,0)))/INDEX('分群統計'!$M$5:$M$8,MATCH(X13,'分群統計'!$A$5:$A$8,0)))),0)),"")) | AN13: =IF(ISNUMBER(AB13),IF(Z13>0,AB13/Z13*100,""),"") | AO13: =IF(BA13<>1,"",IFERROR(IF(INDEX('分群統計'!$N$5:$N$8,MATCH(X13,'分群統計'!$A$5:$A$8,0))<3,"",IF(INDEX('分群統計'!$P$5:$P$8,MATCH(X13,'分群統計'!$A$5:$A$8,0))>0,MAX(-3,MIN(3,(AZ13-INDEX('分群統計'!$O$5:$O$8,MATCH(X13,'分群統計'!$A$5:$A$8,0)))/INDEX('分群統計'!$P$5:$P$8,MATCH(X13,'分群統計'!$A$5:$A$8,0)))),0)),"")) | AP13: =IF(BC13<>1,"",IFERROR(IF(INDEX('分群統計'!$Q$5:$Q$8,MATCH(X13,'分群統計'!$A$5:$A$8,0))<3,"",IF(INDEX('分群統計'!$S$5:$S$8,MATCH(X13,'分群統計'!$A$5:$A$8,0))>0,MAX(-3,MIN(3,(BB13-INDEX('分群統計'!$R$5:$R$8,MATCH(X13,'分群統計'!$A$5:$A$8,0)))/INDEX('分群統計'!$S$5:$S$8,MATCH(X13,'分群統計'!$A$5:$A$8,0)))),0)),"")) | AQ13: =IF(Y13=1,(IF(ISNUMBER(AF13),AF13,0)*'參數'!$B$13+IF(ISNUMBER(AM13),AM13,0)*'參數'!$B$14+IF(ISNUMBER(AO13),AO13,0)*'參數'!$B$15+IF(ISNUMBER(AP13),AP13,0)*'參數'!$B$16)/('參數'!$B$13+'參數'!$B$14+'參數'!$B$15+'參數'!$B$16),"") | AR13: =IF(Y13=1,(SUMPRODUCT(($X$5:$X$404=X13)*($Y$5:$Y$404=1)*($BD$5:$BD$404>BD13))+1)/COUNTIFS($X$5:$X$404,X13,$Y$5:$Y$404,1),"") | AS13: =IF(ISNUMBER(AR13),IF(AR13<='參數'!$B$18,"加碼候選",IF(AR13>'參數'!$B$19,"減碼候選","")),"") | AT13: =IF(Y13=1,N13,0) | AU13: =IF(Y13=1,LN(O13),0) | AV13: =IF(Y13=1,IF(ISNUMBER(F13),F13,0),0) | AW13: =IF(Y13=1,Z13,0) | AX13: =IF(Y13=1,IF(ISNUMBER(AL13),AL13,0),0) | AY13: =IF(Y13=1,IF(ISNUMBER(AL13),1,0),0) | AZ13: =IF(Y13=1,IF(ISNUMBER(AN13),AN13,0),0) | BA13: =IF(Y13=1,IF(ISNUMBER(AN13),1,0),0) | BB13: =IF(Y13=1,IF(ISNUMBER(T13),T13,0),0) | BC13: =IF(Y13=1,IF(ISNUMBER(T13),1,0),0) | BD13: =IF(Y13=1,AQ13+ROW()/1E9,-1E9) | BE13: =IF(Y13=1,AQ13+ROW()/1E9,1E9)
B14: =IF($A14="","",BDP($A14,B$3)) | C14: =IF($A14="","",BDP($A14,C$3)) | D14: =IF($A14="","",BDP($A14,D$3)) | E14: =IF($A14="","",BDP($A14,E$3)) | F14: =IF($A14="","",BDP($A14,F$3)) | G14: =IF($A14="","",BDP($A14,G$3)) | H14: =IF($A14="","",BDP($A14,H$3)) | I14: =IF($A14="","",BDP($A14,I$3)) | ... O14: =IF($A14="","",BDP($A14,O$3)) | P14: =IF($A14="","",BDH($A14,$N$3,'參數'!$B$5,'參數'!$B$5,"Days=A","Fill=P","Dates=H")) | Q14: =IF($A14="","",BDH($A14,$N$3,'參數'!$B$6,'參數'!$B$6,"Days=A","Fill=P","Dates=H")) | R14: =IF($A14="","",BDH($A14,$N$3,'參數'!$B$7,'參數'!$B$7,"Days=A","Fill=P","Dates=H")) | S14: =IF($A14="","",IFERROR(INDEX('發行人'!$A$5:$A$44,MATCH(B14,'發行人'!$D$5:$D$44,0)),"未對應")) | T14: =IF($A14="","",IFERROR(INDEX('發行人'!$G$5:$G$44,MATCH(B14,'發行人'!$D$5:$D$44,0))+0,"")) | U14: =IF(ISNUMBER(E14),YEARFRAC('參數'!$B$4,E14),"") | V14: =IF(U14="","",IF(U14<3,"1-3y",IF(U14<5,"3-5y",IF(U14<7,"5-7y",IF(U14<10,"7-10y","10y+"))))) | W14: =IF($A14="","",IFERROR(INDEX('參數'!$B$24:$B$45,MATCH(G14,'參數'!$A$24:$A$45,0)),"")) | X14: =IF($A14="","",IFERROR(INDEX('參數'!$C$24:$C$45,MATCH(G14,'參數'!$A$24:$A$45,0)),"")) | Y14: =IF(AND(ISNUMBER(N14),ISNUMBER(O14),ISNUMBER(U14)),IF(AND(O14>0,X14<>""),1,0),0) | Z14: =IF(Y14=1,O14*N14,"") | AA14: =IF(Y14=1,IF(ISNUMBER(Q14),N14-Q14,""),"") | AB14: =IF(Y14=1,IF(AND(ISNUMBER(P14),ISNUMBER(R14)),R14*5/12-O14*(P14-R14),""),"") | AC14: =IF(Y14=1,COUNTIFS($X$5:$X$404,X14,$V$5:$V$404,V14,$Y$5:$Y$404,1),"") | AD14: =IF(Y14=1,IFERROR(IF(AC14>='參數'!$B$9,INDEX('分群統計'!$G$13:$K$16,MATCH(X14,'分群統計'!$A$13:$A$16,0),MATCH(V14,'分群統計'!$G$12:$K$12,0)),INDEX('分群統計'!$I$5:$I$8,MATCH(X14,'分群統計'!$A$5:$A$8,0))),""),"") | AE14: =IF(Y14=1,IFERROR(IF(AC14>='參數'!$B$9,INDEX('分群統計'!$L$13:$P$16,MATCH(X14,'分群統計'!$A$13:$A$16,0),MATCH(V14,'分群統計'!$L$12:$P$12,0)),INDEX('分群統計'!$J$5:$J$8,MATCH(X14,'分群統計'!$A$5:$A$8,0))),""),"") | AF14: =IF(ISNUMBER(AE14),IF(AE14>0,MAX(-3,MIN(3,(N14-AD14)/AE14)),0),"") | AG14: =IF(Y14=1,COUNTIFS($B$5:$B$404,B14,$Y$5:$Y$404,1),"") | AH14: =IF(Y14=1,IFERROR(IF(ISNUMBER(INDEX('分群統計'!$G$20:$G$59,MATCH(B14,'分群統計'!$A$20:$A$59,0))),INDEX('分群統計'!$H$20:$H$59,MATCH(B14,'分群統計'!$A$20:$A$59,0))+INDEX('分群統計'!$G$20:$G$59,MATCH(B14,'分群統計'!$A$20:$A$59,0))*AU14,""),""),"") | AI14: =IF(ISNUMBER(AH14),N14-AH14,"") | AJ14: =IF(Y14=1,IFERROR(IF(ISNUMBER(INDEX('分群統計'!$G$5:$G$8,MATCH(X14,'分群統計'!$A$5:$A$8,0))),INDEX('分群統計'!$H$5:$H$8,MATCH(X14,'分群統計'!$A$5:$A$8,0))+INDEX('分群統計'!$G$5:$G$8,MATCH(X14,'分群統計'!$A$5:$A$8,0))*AU14,""),""),"") | AK14: =IF(ISNUMBER(AJ14),N14-AJ14,"") | AL14: =IF(ISNUMBER(AJ14),IF(AJ14>0,AK14/AJ14,""),"") | AM14: =IF(AY14<>1,"",IFERROR(IF(INDEX('分群統計'!$K$5:$K$8,MATCH(X14,'分群統計'!$A$5:$A$8,0))<3,"",IF(INDEX('分群統計'!$M$5:$M$8,MATCH(X14,'分群統計'!$A$5:$A$8,0))>0,MAX(-3,MIN(3,(AX14-INDEX('分群統計'!$L$5:$L$8,MATCH(X14,'分群統計'!$A$5:$A$8,0)))/INDEX('分群統計'!$M$5:$M$8,MATCH(X14,'分群統計'!$A$5:$A$8,0)))),0)),"")) | AN14: =IF(ISNUMBER(AB14),IF(Z14>0,AB14/Z14*100,""),"") | AO14: =IF(BA14<>1,"",IFERROR(IF(INDEX('分群統計'!$N$5:$N$8,MATCH(X14,'分群統計'!$A$5:$A$8,0))<3,"",IF(INDEX('分群統計'!$P$5:$P$8,MATCH(X14,'分群統計'!$A$5:$A$8,0))>0,MAX(-3,MIN(3,(AZ14-INDEX('分群統計'!$O$5:$O$8,MATCH(X14,'分群統計'!$A$5:$A$8,0)))/INDEX('分群統計'!$P$5:$P$8,MATCH(X14,'分群統計'!$A$5:$A$8,0)))),0)),"")) | AP14: =IF(BC14<>1,"",IFERROR(IF(INDEX('分群統計'!$Q$5:$Q$8,MATCH(X14,'分群統計'!$A$5:$A$8,0))<3,"",IF(INDEX('分群統計'!$S$5:$S$8,MATCH(X14,'分群統計'!$A$5:$A$8,0))>0,MAX(-3,MIN(3,(BB14-INDEX('分群統計'!$R$5:$R$8,MATCH(X14,'分群統計'!$A$5:$A$8,0)))/INDEX('分群統計'!$S$5:$S$8,MATCH(X14,'分群統計'!$A$5:$A$8,0)))),0)),"")) | AQ14: =IF(Y14=1,(IF(ISNUMBER(AF14),AF14,0)*'參數'!$B$13+IF(ISNUMBER(AM14),AM14,0)*'參數'!$B$14+IF(ISNUMBER(AO14),AO14,0)*'參數'!$B$15+IF(ISNUMBER(AP14),AP14,0)*'參數'!$B$16)/('參數'!$B$13+'參數'!$B$14+'參數'!$B$15+'參數'!$B$16),"") | AR14: =IF(Y14=1,(SUMPRODUCT(($X$5:$X$404=X14)*($Y$5:$Y$404=1)*($BD$5:$BD$404>BD14))+1)/COUNTIFS($X$5:$X$404,X14,$Y$5:$Y$404,1),"") | AS14: =IF(ISNUMBER(AR14),IF(AR14<='參數'!$B$18,"加碼候選",IF(AR14>'參數'!$B$19,"減碼候選","")),"") | AT14: =IF(Y14=1,N14,0) | AU14: =IF(Y14=1,LN(O14),0) | AV14: =IF(Y14=1,IF(ISNUMBER(F14),F14,0),0) | AW14: =IF(Y14=1,Z14,0) | AX14: =IF(Y14=1,IF(ISNUMBER(AL14),AL14,0),0) | AY14: =IF(Y14=1,IF(ISNUMBER(AL14),1,0),0) | AZ14: =IF(Y14=1,IF(ISNUMBER(AN14),AN14,0),0) | BA14: =IF(Y14=1,IF(ISNUMBER(AN14),1,0),0) | BB14: =IF(Y14=1,IF(ISNUMBER(T14),T14,0),0) | BC14: =IF(Y14=1,IF(ISNUMBER(T14),1,0),0) | BD14: =IF(Y14=1,AQ14+ROW()/1E9,-1E9) | BE14: =IF(Y14=1,AQ14+ROW()/1E9,1E9)
B15: =IF($A15="","",BDP($A15,B$3)) | C15: =IF($A15="","",BDP($A15,C$3)) | D15: =IF($A15="","",BDP($A15,D$3)) | E15: =IF($A15="","",BDP($A15,E$3)) | F15: =IF($A15="","",BDP($A15,F$3)) | G15: =IF($A15="","",BDP($A15,G$3)) | H15: =IF($A15="","",BDP($A15,H$3)) | I15: =IF($A15="","",BDP($A15,I$3)) | ... O15: =IF($A15="","",BDP($A15,O$3)) | P15: =IF($A15="","",BDH($A15,$N$3,'參數'!$B$5,'參數'!$B$5,"Days=A","Fill=P","Dates=H")) | Q15: =IF($A15="","",BDH($A15,$N$3,'參數'!$B$6,'參數'!$B$6,"Days=A","Fill=P","Dates=H")) | R15: =IF($A15="","",BDH($A15,$N$3,'參數'!$B$7,'參數'!$B$7,"Days=A","Fill=P","Dates=H")) | S15: =IF($A15="","",IFERROR(INDEX('發行人'!$A$5:$A$44,MATCH(B15,'發行人'!$D$5:$D$44,0)),"未對應")) | T15: =IF($A15="","",IFERROR(INDEX('發行人'!$G$5:$G$44,MATCH(B15,'發行人'!$D$5:$D$44,0))+0,"")) | U15: =IF(ISNUMBER(E15),YEARFRAC('參數'!$B$4,E15),"") | V15: =IF(U15="","",IF(U15<3,"1-3y",IF(U15<5,"3-5y",IF(U15<7,"5-7y",IF(U15<10,"7-10y","10y+"))))) | W15: =IF($A15="","",IFERROR(INDEX('參數'!$B$24:$B$45,MATCH(G15,'參數'!$A$24:$A$45,0)),"")) | X15: =IF($A15="","",IFERROR(INDEX('參數'!$C$24:$C$45,MATCH(G15,'參數'!$A$24:$A$45,0)),"")) | Y15: =IF(AND(ISNUMBER(N15),ISNUMBER(O15),ISNUMBER(U15)),IF(AND(O15>0,X15<>""),1,0),0) | Z15: =IF(Y15=1,O15*N15,"") | AA15: =IF(Y15=1,IF(ISNUMBER(Q15),N15-Q15,""),"") | AB15: =IF(Y15=1,IF(AND(ISNUMBER(P15),ISNUMBER(R15)),R15*5/12-O15*(P15-R15),""),"") | AC15: =IF(Y15=1,COUNTIFS($X$5:$X$404,X15,$V$5:$V$404,V15,$Y$5:$Y$404,1),"") | AD15: =IF(Y15=1,IFERROR(IF(AC15>='參數'!$B$9,INDEX('分群統計'!$G$13:$K$16,MATCH(X15,'分群統計'!$A$13:$A$16,0),MATCH(V15,'分群統計'!$G$12:$K$12,0)),INDEX('分群統計'!$I$5:$I$8,MATCH(X15,'分群統計'!$A$5:$A$8,0))),""),"") | AE15: =IF(Y15=1,IFERROR(IF(AC15>='參數'!$B$9,INDEX('分群統計'!$L$13:$P$16,MATCH(X15,'分群統計'!$A$13:$A$16,0),MATCH(V15,'分群統計'!$L$12:$P$12,0)),INDEX('分群統計'!$J$5:$J$8,MATCH(X15,'分群統計'!$A$5:$A$8,0))),""),"") | AF15: =IF(ISNUMBER(AE15),IF(AE15>0,MAX(-3,MIN(3,(N15-AD15)/AE15)),0),"") | AG15: =IF(Y15=1,COUNTIFS($B$5:$B$404,B15,$Y$5:$Y$404,1),"") | AH15: =IF(Y15=1,IFERROR(IF(ISNUMBER(INDEX('分群統計'!$G$20:$G$59,MATCH(B15,'分群統計'!$A$20:$A$59,0))),INDEX('分群統計'!$H$20:$H$59,MATCH(B15,'分群統計'!$A$20:$A$59,0))+INDEX('分群統計'!$G$20:$G$59,MATCH(B15,'分群統計'!$A$20:$A$59,0))*AU15,""),""),"") | AI15: =IF(ISNUMBER(AH15),N15-AH15,"") | AJ15: =IF(Y15=1,IFERROR(IF(ISNUMBER(INDEX('分群統計'!$G$5:$G$8,MATCH(X15,'分群統計'!$A$5:$A$8,0))),INDEX('分群統計'!$H$5:$H$8,MATCH(X15,'分群統計'!$A$5:$A$8,0))+INDEX('分群統計'!$G$5:$G$8,MATCH(X15,'分群統計'!$A$5:$A$8,0))*AU15,""),""),"") | AK15: =IF(ISNUMBER(AJ15),N15-AJ15,"") | AL15: =IF(ISNUMBER(AJ15),IF(AJ15>0,AK15/AJ15,""),"") | AM15: =IF(AY15<>1,"",IFERROR(IF(INDEX('分群統計'!$K$5:$K$8,MATCH(X15,'分群統計'!$A$5:$A$8,0))<3,"",IF(INDEX('分群統計'!$M$5:$M$8,MATCH(X15,'分群統計'!$A$5:$A$8,0))>0,MAX(-3,MIN(3,(AX15-INDEX('分群統計'!$L$5:$L$8,MATCH(X15,'分群統計'!$A$5:$A$8,0)))/INDEX('分群統計'!$M$5:$M$8,MATCH(X15,'分群統計'!$A$5:$A$8,0)))),0)),"")) | AN15: =IF(ISNUMBER(AB15),IF(Z15>0,AB15/Z15*100,""),"") | AO15: =IF(BA15<>1,"",IFERROR(IF(INDEX('分群統計'!$N$5:$N$8,MATCH(X15,'分群統計'!$A$5:$A$8,0))<3,"",IF(INDEX('分群統計'!$P$5:$P$8,MATCH(X15,'分群統計'!$A$5:$A$8,0))>0,MAX(-3,MIN(3,(AZ15-INDEX('分群統計'!$O$5:$O$8,MATCH(X15,'分群統計'!$A$5:$A$8,0)))/INDEX('分群統計'!$P$5:$P$8,MATCH(X15,'分群統計'!$A$5:$A$8,0)))),0)),"")) | AP15: =IF(BC15<>1,"",IFERROR(IF(INDEX('分群統計'!$Q$5:$Q$8,MATCH(X15,'分群統計'!$A$5:$A$8,0))<3,"",IF(INDEX('分群統計'!$S$5:$S$8,MATCH(X15,'分群統計'!$A$5:$A$8,0))>0,MAX(-3,MIN(3,(BB15-INDEX('分群統計'!$R$5:$R$8,MATCH(X15,'分群統計'!$A$5:$A$8,0)))/INDEX('分群統計'!$S$5:$S$8,MATCH(X15,'分群統計'!$A$5:$A$8,0)))),0)),"")) | AQ15: =IF(Y15=1,(IF(ISNUMBER(AF15),AF15,0)*'參數'!$B$13+IF(ISNUMBER(AM15),AM15,0)*'參數'!$B$14+IF(ISNUMBER(AO15),AO15,0)*'參數'!$B$15+IF(ISNUMBER(AP15),AP15,0)*'參數'!$B$16)/('參數'!$B$13+'參數'!$B$14+'參數'!$B$15+'參數'!$B$16),"") | AR15: =IF(Y15=1,(SUMPRODUCT(($X$5:$X$404=X15)*($Y$5:$Y$404=1)*($BD$5:$BD$404>BD15))+1)/COUNTIFS($X$5:$X$404,X15,$Y$5:$Y$404,1),"") | AS15: =IF(ISNUMBER(AR15),IF(AR15<='參數'!$B$18,"加碼候選",IF(AR15>'參數'!$B$19,"減碼候選","")),"") | AT15: =IF(Y15=1,N15,0) | AU15: =IF(Y15=1,LN(O15),0) | AV15: =IF(Y15=1,IF(ISNUMBER(F15),F15,0),0) | AW15: =IF(Y15=1,Z15,0) | AX15: =IF(Y15=1,IF(ISNUMBER(AL15),AL15,0),0) | AY15: =IF(Y15=1,IF(ISNUMBER(AL15),1,0),0) | AZ15: =IF(Y15=1,IF(ISNUMBER(AN15),AN15,0),0) | BA15: =IF(Y15=1,IF(ISNUMBER(AN15),1,0),0) | BB15: =IF(Y15=1,IF(ISNUMBER(T15),T15,0),0) | BC15: =IF(Y15=1,IF(ISNUMBER(T15),1,0),0) | BD15: =IF(Y15=1,AQ15+ROW()/1E9,-1E9) | BE15: =IF(Y15=1,AQ15+ROW()/1E9,1E9)
B16: =IF($A16="","",BDP($A16,B$3)) | C16: =IF($A16="","",BDP($A16,C$3)) | D16: =IF($A16="","",BDP($A16,D$3)) | E16: =IF($A16="","",BDP($A16,E$3)) | F16: =IF($A16="","",BDP($A16,F$3)) | G16: =IF($A16="","",BDP($A16,G$3)) | H16: =IF($A16="","",BDP($A16,H$3)) | I16: =IF($A16="","",BDP($A16,I$3)) | ... O16: =IF($A16="","",BDP($A16,O$3)) | P16: =IF($A16="","",BDH($A16,$N$3,'參數'!$B$5,'參數'!$B$5,"Days=A","Fill=P","Dates=H")) | Q16: =IF($A16="","",BDH($A16,$N$3,'參數'!$B$6,'參數'!$B$6,"Days=A","Fill=P","Dates=H")) | R16: =IF($A16="","",BDH($A16,$N$3,'參數'!$B$7,'參數'!$B$7,"Days=A","Fill=P","Dates=H")) | S16: =IF($A16="","",IFERROR(INDEX('發行人'!$A$5:$A$44,MATCH(B16,'發行人'!$D$5:$D$44,0)),"未對應")) | T16: =IF($A16="","",IFERROR(INDEX('發行人'!$G$5:$G$44,MATCH(B16,'發行人'!$D$5:$D$44,0))+0,"")) | U16: =IF(ISNUMBER(E16),YEARFRAC('參數'!$B$4,E16),"") | V16: =IF(U16="","",IF(U16<3,"1-3y",IF(U16<5,"3-5y",IF(U16<7,"5-7y",IF(U16<10,"7-10y","10y+"))))) | W16: =IF($A16="","",IFERROR(INDEX('參數'!$B$24:$B$45,MATCH(G16,'參數'!$A$24:$A$45,0)),"")) | X16: =IF($A16="","",IFERROR(INDEX('參數'!$C$24:$C$45,MATCH(G16,'參數'!$A$24:$A$45,0)),"")) | Y16: =IF(AND(ISNUMBER(N16),ISNUMBER(O16),ISNUMBER(U16)),IF(AND(O16>0,X16<>""),1,0),0) | Z16: =IF(Y16=1,O16*N16,"") | AA16: =IF(Y16=1,IF(ISNUMBER(Q16),N16-Q16,""),"") | AB16: =IF(Y16=1,IF(AND(ISNUMBER(P16),ISNUMBER(R16)),R16*5/12-O16*(P16-R16),""),"") | AC16: =IF(Y16=1,COUNTIFS($X$5:$X$404,X16,$V$5:$V$404,V16,$Y$5:$Y$404,1),"") | AD16: =IF(Y16=1,IFERROR(IF(AC16>='參數'!$B$9,INDEX('分群統計'!$G$13:$K$16,MATCH(X16,'分群統計'!$A$13:$A$16,0),MATCH(V16,'分群統計'!$G$12:$K$12,0)),INDEX('分群統計'!$I$5:$I$8,MATCH(X16,'分群統計'!$A$5:$A$8,0))),""),"") | AE16: =IF(Y16=1,IFERROR(IF(AC16>='參數'!$B$9,INDEX('分群統計'!$L$13:$P$16,MATCH(X16,'分群統計'!$A$13:$A$16,0),MATCH(V16,'分群統計'!$L$12:$P$12,0)),INDEX('分群統計'!$J$5:$J$8,MATCH(X16,'分群統計'!$A$5:$A$8,0))),""),"") | AF16: =IF(ISNUMBER(AE16),IF(AE16>0,MAX(-3,MIN(3,(N16-AD16)/AE16)),0),"") | AG16: =IF(Y16=1,COUNTIFS($B$5:$B$404,B16,$Y$5:$Y$404,1),"") | AH16: =IF(Y16=1,IFERROR(IF(ISNUMBER(INDEX('分群統計'!$G$20:$G$59,MATCH(B16,'分群統計'!$A$20:$A$59,0))),INDEX('分群統計'!$H$20:$H$59,MATCH(B16,'分群統計'!$A$20:$A$59,0))+INDEX('分群統計'!$G$20:$G$59,MATCH(B16,'分群統計'!$A$20:$A$59,0))*AU16,""),""),"") | AI16: =IF(ISNUMBER(AH16),N16-AH16,"") | AJ16: =IF(Y16=1,IFERROR(IF(ISNUMBER(INDEX('分群統計'!$G$5:$G$8,MATCH(X16,'分群統計'!$A$5:$A$8,0))),INDEX('分群統計'!$H$5:$H$8,MATCH(X16,'分群統計'!$A$5:$A$8,0))+INDEX('分群統計'!$G$5:$G$8,MATCH(X16,'分群統計'!$A$5:$A$8,0))*AU16,""),""),"") | AK16: =IF(ISNUMBER(AJ16),N16-AJ16,"") | AL16: =IF(ISNUMBER(AJ16),IF(AJ16>0,AK16/AJ16,""),"") | AM16: =IF(AY16<>1,"",IFERROR(IF(INDEX('分群統計'!$K$5:$K$8,MATCH(X16,'分群統計'!$A$5:$A$8,0))<3,"",IF(INDEX('分群統計'!$M$5:$M$8,MATCH(X16,'分群統計'!$A$5:$A$8,0))>0,MAX(-3,MIN(3,(AX16-INDEX('分群統計'!$L$5:$L$8,MATCH(X16,'分群統計'!$A$5:$A$8,0)))/INDEX('分群統計'!$M$5:$M$8,MATCH(X16,'分群統計'!$A$5:$A$8,0)))),0)),"")) | AN16: =IF(ISNUMBER(AB16),IF(Z16>0,AB16/Z16*100,""),"") | AO16: =IF(BA16<>1,"",IFERROR(IF(INDEX('分群統計'!$N$5:$N$8,MATCH(X16,'分群統計'!$A$5:$A$8,0))<3,"",IF(INDEX('分群統計'!$P$5:$P$8,MATCH(X16,'分群統計'!$A$5:$A$8,0))>0,MAX(-3,MIN(3,(AZ16-INDEX('分群統計'!$O$5:$O$8,MATCH(X16,'分群統計'!$A$5:$A$8,0)))/INDEX('分群統計'!$P$5:$P$8,MATCH(X16,'分群統計'!$A$5:$A$8,0)))),0)),"")) | AP16: =IF(BC16<>1,"",IFERROR(IF(INDEX('分群統計'!$Q$5:$Q$8,MATCH(X16,'分群統計'!$A$5:$A$8,0))<3,"",IF(INDEX('分群統計'!$S$5:$S$8,MATCH(X16,'分群統計'!$A$5:$A$8,0))>0,MAX(-3,MIN(3,(BB16-INDEX('分群統計'!$R$5:$R$8,MATCH(X16,'分群統計'!$A$5:$A$8,0)))/INDEX('分群統計'!$S$5:$S$8,MATCH(X16,'分群統計'!$A$5:$A$8,0)))),0)),"")) | AQ16: =IF(Y16=1,(IF(ISNUMBER(AF16),AF16,0)*'參數'!$B$13+IF(ISNUMBER(AM16),AM16,0)*'參數'!$B$14+IF(ISNUMBER(AO16),AO16,0)*'參數'!$B$15+IF(ISNUMBER(AP16),AP16,0)*'參數'!$B$16)/('參數'!$B$13+'參數'!$B$14+'參數'!$B$15+'參數'!$B$16),"") | AR16: =IF(Y16=1,(SUMPRODUCT(($X$5:$X$404=X16)*($Y$5:$Y$404=1)*($BD$5:$BD$404>BD16))+1)/COUNTIFS($X$5:$X$404,X16,$Y$5:$Y$404,1),"") | AS16: =IF(ISNUMBER(AR16),IF(AR16<='參數'!$B$18,"加碼候選",IF(AR16>'參數'!$B$19,"減碼候選","")),"") | AT16: =IF(Y16=1,N16,0) | AU16: =IF(Y16=1,LN(O16),0) | AV16: =IF(Y16=1,IF(ISNUMBER(F16),F16,0),0) | AW16: =IF(Y16=1,Z16,0) | AX16: =IF(Y16=1,IF(ISNUMBER(AL16),AL16,0),0) | AY16: =IF(Y16=1,IF(ISNUMBER(AL16),1,0),0) | AZ16: =IF(Y16=1,IF(ISNUMBER(AN16),AN16,0),0) | BA16: =IF(Y16=1,IF(ISNUMBER(AN16),1,0),0) | BB16: =IF(Y16=1,IF(ISNUMBER(T16),T16,0),0) | BC16: =IF(Y16=1,IF(ISNUMBER(T16),1,0),0) | BD16: =IF(Y16=1,AQ16+ROW()/1E9,-1E9) | BE16: =IF(Y16=1,AQ16+ROW()/1E9,1E9)
... B404: =IF($A404="","",BDP($A404,B$3)) | C404: =IF($A404="","",BDP($A404,C$3)) | D404: =IF($A404="","",BDP($A404,D$3)) | E404: =IF($A404="","",BDP($A404,E$3)) | F404: =IF($A404="","",BDP($A404,F$3)) | G404: =IF($A404="","",BDP($A404,G$3)) | H404: =IF($A404="","",BDP($A404,H$3)) | I404: =IF($A404="","",BDP($A404,I$3)) | ... O404: =IF($A404="","",BDP($A404,O$3)) | P404: =IF($A404="","",BDH($A404,$N$3,'參數'!$B$5,'參數'!$B$5,"Days=A","Fill=P","Dates=H")) | Q404: =IF($A404="","",BDH($A404,$N$3,'參數'!$B$6,'參數'!$B$6,"Days=A","Fill=P","Dates=H")) | R404: =IF($A404="","",BDH($A404,$N$3,'參數'!$B$7,'參數'!$B$7,"Days=A","Fill=P","Dates=H")) | S404: =IF($A404="","",IFERROR(INDEX('發行人'!$A$5:$A$44,MATCH(B404,'發行人'!$D$5:$D$44,0)),"未對應")) | T404: =IF($A404="","",IFERROR(INDEX('發行人'!$G$5:$G$44,MATCH(B404,'發行人'!$D$5:$D$44,0))+0,"")) | U404: =IF(ISNUMBER(E404),YEARFRAC('參數'!$B$4,E404),"") | V404: =IF(U404="","",IF(U404<3,"1-3y",IF(U404<5,"3-5y",IF(U404<7,"5-7y",IF(U404<10,"7-10y","10y+"))))) | W404: =IF($A404="","",IFERROR(INDEX('參數'!$B$24:$B$45,MATCH(G404,'參數'!$A$24:$A$45,0)),"")) | X404: =IF($A404="","",IFERROR(INDEX('參數'!$C$24:$C$45,MATCH(G404,'參數'!$A$24:$A$45,0)),"")) | Y404: =IF(AND(ISNUMBER(N404),ISNUMBER(O404),ISNUMBER(U404)),IF(AND(O404>0,X404<>""),1,0),0) | Z404: =IF(Y404=1,O404*N404,"") | AA404: =IF(Y404=1,IF(ISNUMBER(Q404),N404-Q404,""),"") | AB404: =IF(Y404=1,IF(AND(ISNUMBER(P404),ISNUMBER(R404)),R404*5/12-O404*(P404-R404),""),"") | AC404: =IF(Y404=1,COUNTIFS($X$5:$X$404,X404,$V$5:$V$404,V404,$Y$5:$Y$404,1),"") | AD404: =IF(Y404=1,IFERROR(IF(AC404>='參數'!$B$9,INDEX('分群統計'!$G$13:$K$16,MATCH(X404,'分群統計'!$A$13:$A$16,0),MATCH(V404,'分群統計'!$G$12:$K$12,0)),INDEX('分群統計'!$I$5:$I$8,MATCH(X404,'分群統計'!$A$5:$A$8,0))),""),"") | AE404: =IF(Y404=1,IFERROR(IF(AC404>='參數'!$B$9,INDEX('分群統計'!$L$13:$P$16,MATCH(X404,'分群統計'!$A$13:$A$16,0),MATCH(V404,'分群統計'!$L$12:$P$12,0)),INDEX('分群統計'!$J$5:$J$8,MATCH(X404,'分群統計'!$A$5:$A$8,0))),""),"") | AF404: =IF(ISNUMBER(AE404),IF(AE404>0,MAX(-3,MIN(3,(N404-AD404)/AE404)),0),"") | AG404: =IF(Y404=1,COUNTIFS($B$5:$B$404,B404,$Y$5:$Y$404,1),"") | AH404: =IF(Y404=1,IFERROR(IF(ISNUMBER(INDEX('分群統計'!$G$20:$G$59,MATCH(B404,'分群統計'!$A$20:$A$59,0))),INDEX('分群統計'!$H$20:$H$59,MATCH(B404,'分群統計'!$A$20:$A$59,0))+INDEX('分群統計'!$G$20:$G$59,MATCH(B404,'分群統計'!$A$20:$A$59,0))*AU404,""),""),"") | AI404: =IF(ISNUMBER(AH404),N404-AH404,"") | AJ404: =IF(Y404=1,IFERROR(IF(ISNUMBER(INDEX('分群統計'!$G$5:$G$8,MATCH(X404,'分群統計'!$A$5:$A$8,0))),INDEX('分群統計'!$H$5:$H$8,MATCH(X404,'分群統計'!$A$5:$A$8,0))+INDEX('分群統計'!$G$5:$G$8,MATCH(X404,'分群統計'!$A$5:$A$8,0))*AU404,""),""),"") | AK404: =IF(ISNUMBER(AJ404),N404-AJ404,"") | AL404: =IF(ISNUMBER(AJ404),IF(AJ404>0,AK404/AJ404,""),"") | AM404: =IF(AY404<>1,"",IFERROR(IF(INDEX('分群統計'!$K$5:$K$8,MATCH(X404,'分群統計'!$A$5:$A$8,0))<3,"",IF(INDEX('分群統計'!$M$5:$M$8,MATCH(X404,'分群統計'!$A$5:$A$8,0))>0,MAX(-3,MIN(3,(AX404-INDEX('分群統計'!$L$5:$L$8,MATCH(X404,'分群統計'!$A$5:$A$8,0)))/INDEX('分群統計'!$M$5:$M$8,MATCH(X404,'分群統計'!$A$5:$A$8,0)))),0)),"")) | AN404: =IF(ISNUMBER(AB404),IF(Z404>0,AB404/Z404*100,""),"") | AO404: =IF(BA404<>1,"",IFERROR(IF(INDEX('分群統計'!$N$5:$N$8,MATCH(X404,'分群統計'!$A$5:$A$8,0))<3,"",IF(INDEX('分群統計'!$P$5:$P$8,MATCH(X404,'分群統計'!$A$5:$A$8,0))>0,MAX(-3,MIN(3,(AZ404-INDEX('分群統計'!$O$5:$O$8,MATCH(X404,'分群統計'!$A$5:$A$8,0)))/INDEX('分群統計'!$P$5:$P$8,MATCH(X404,'分群統計'!$A$5:$A$8,0)))),0)),"")) | AP404: =IF(BC404<>1,"",IFERROR(IF(INDEX('分群統計'!$Q$5:$Q$8,MATCH(X404,'分群統計'!$A$5:$A$8,0))<3,"",IF(INDEX('分群統計'!$S$5:$S$8,MATCH(X404,'分群統計'!$A$5:$A$8,0))>0,MAX(-3,MIN(3,(BB404-INDEX('分群統計'!$R$5:$R$8,MATCH(X404,'分群統計'!$A$5:$A$8,0)))/INDEX('分群統計'!$S$5:$S$8,MATCH(X404,'分群統計'!$A$5:$A$8,0)))),0)),"")) | AQ404: =IF(Y404=1,(IF(ISNUMBER(AF404),AF404,0)*'參數'!$B$13+IF(ISNUMBER(AM404),AM404,0)*'參數'!$B$14+IF(ISNUMBER(AO404),AO404,0)*'參數'!$B$15+IF(ISNUMBER(AP404),AP404,0)*'參數'!$B$16)/('參數'!$B$13+'參數'!$B$14+'參數'!$B$15+'參數'!$B$16),"") | AR404: =IF(Y404=1,(SUMPRODUCT(($X$5:$X$404=X404)*($Y$5:$Y$404=1)*($BD$5:$BD$404>BD404))+1)/COUNTIFS($X$5:$X$404,X404,$Y$5:$Y$404,1),"") | AS404: =IF(ISNUMBER(AR404),IF(AR404<='參數'!$B$18,"加碼候選",IF(AR404>'參數'!$B$19,"減碼候選","")),"") | AT404: =IF(Y404=1,N404,0) | AU404: =IF(Y404=1,LN(O404),0) | AV404: =IF(Y404=1,IF(ISNUMBER(F404),F404,0),0) | AW404: =IF(Y404=1,Z404,0) | AX404: =IF(Y404=1,IF(ISNUMBER(AL404),AL404,0),0) | AY404: =IF(Y404=1,IF(ISNUMBER(AL404),1,0),0) | AZ404: =IF(Y404=1,IF(ISNUMBER(AN404),AN404,0),0) | BA404: =IF(Y404=1,IF(ISNUMBER(AN404),1,0),0) | BB404: =IF(Y404=1,IF(ISNUMBER(T404),T404,0),0) | BC404: =IF(Y404=1,IF(ISNUMBER(T404),1,0),0) | BD404: =IF(Y404=1,AQ404+ROW()/1E9,-1E9) | BE404: =IF(Y404=1,AQ404+ROW()/1E9,1E9)

Sheet 分群統計
A1: 分群統計（自動計算，請勿修改）
A2: 曲線擬合：OAS = 截距 + 斜率 × ln(存續期間)，用最小平方法；檔數不足「參數」表門檻時不擬合。z 分數用的平均與標準差也在這裡計算。
A3: A. 評等分群：評等曲線、Carry 退回值、各因子的平均與標準差
A4: 評等分群 | B4: 檔數 | C4: Σx | D4: Σy | E4: Σx² | F4: Σxy | G4: 曲線斜率 | H4: 曲線截距 | I4: OAS 平均 | J4: OAS 標準差 | K4: Value 檔數 | L4: Value 平均 | M4: Value 標準差 | N4: 動能 檔數 | O4: 動能 平均 | P4: 動能 標準差 | Q4: 股票 檔數 | R4: 股票 平均 | S4: 股票 標準差
A5: AA以上 | B5: =SUMPRODUCT(('債券'!$Y$5:$Y$404=1)*('債券'!$X$5:$X$404=$A5)) | C5: =SUMPRODUCT(('債券'!$Y$5:$Y$404=1)*('債券'!$X$5:$X$404=$A5)*'債券'!$AU$5:$AU$404) | D5: =SUMPRODUCT(('債券'!$Y$5:$Y$404=1)*('債券'!$X$5:$X$404=$A5)*'債券'!$AT$5:$AT$404) | E5: =SUMPRODUCT(('債券'!$Y$5:$Y$404=1)*('債券'!$X$5:$X$404=$A5)*'債券'!$AU$5:$AU$404^2) | F5: =SUMPRODUCT(('債券'!$Y$5:$Y$404=1)*('債券'!$X$5:$X$404=$A5)*'債券'!$AU$5:$AU$404*'債券'!$AT$5:$AT$404) | G5: =IF(B5<'參數'!$B$11,"",IF(ABS((B5*E5-C5^2))<1E-9,0,(B5*F5-C5*D5)/(B5*E5-C5^2))) | H5: =IF(B5<'參數'!$B$11,"",(D5-G5*C5)/B5) | I5: =IF(B5>0,D5/B5,"") | J5: =IF(B5>1,SQRT(SUMPRODUCT(('債券'!$Y$5:$Y$404=1)*('債券'!$X$5:$X$404=$A5)*('債券'!$AT$5:$AT$404-I5)^2)/(B5-1)),"") | K5: =SUMPRODUCT(('債券'!$AY$5:$AY$404=1)*('債券'!$X$5:$X$404=$A5)) | L5: =IF(K5>0,SUMPRODUCT(('債券'!$AY$5:$AY$404=1)*('債券'!$X$5:$X$404=$A5)*'債券'!$AX$5:$AX$404)/K5,"") | M5: =IF(K5>1,SQRT(SUMPRODUCT(('債券'!$AY$5:$AY$404=1)*('債券'!$X$5:$X$404=$A5)*('債券'!$AX$5:$AX$404-L5)^2)/(K5-1)),"") | N5: =SUMPRODUCT(('債券'!$BA$5:$BA$404=1)*('債券'!$X$5:$X$404=$A5)) | O5: =IF(N5>0,SUMPRODUCT(('債券'!$BA$5:$BA$404=1)*('債券'!$X$5:$X$404=$A5)*'債券'!$AZ$5:$AZ$404)/N5,"") | P5: =IF(N5>1,SQRT(SUMPRODUCT(('債券'!$BA$5:$BA$404=1)*('債券'!$X$5:$X$404=$A5)*('債券'!$AZ$5:$AZ$404-O5)^2)/(N5-1)),"") | Q5: =SUMPRODUCT(('債券'!$BC$5:$BC$404=1)*('債券'!$X$5:$X$404=$A5)) | R5: =IF(Q5>0,SUMPRODUCT(('債券'!$BC$5:$BC$404=1)*('債券'!$X$5:$X$404=$A5)*'債券'!$BB$5:$BB$404)/Q5,"") | S5: =IF(Q5>1,SQRT(SUMPRODUCT(('債券'!$BC$5:$BC$404=1)*('債券'!$X$5:$X$404=$A5)*('債券'!$BB$5:$BB$404-R5)^2)/(Q5-1)),"")
A6: A | B6: =SUMPRODUCT(('債券'!$Y$5:$Y$404=1)*('債券'!$X$5:$X$404=$A6)) | C6: =SUMPRODUCT(('債券'!$Y$5:$Y$404=1)*('債券'!$X$5:$X$404=$A6)*'債券'!$AU$5:$AU$404) | D6: =SUMPRODUCT(('債券'!$Y$5:$Y$404=1)*('債券'!$X$5:$X$404=$A6)*'債券'!$AT$5:$AT$404) | E6: =SUMPRODUCT(('債券'!$Y$5:$Y$404=1)*('債券'!$X$5:$X$404=$A6)*'債券'!$AU$5:$AU$404^2) | F6: =SUMPRODUCT(('債券'!$Y$5:$Y$404=1)*('債券'!$X$5:$X$404=$A6)*'債券'!$AU$5:$AU$404*'債券'!$AT$5:$AT$404) | G6: =IF(B6<'參數'!$B$11,"",IF(ABS((B6*E6-C6^2))<1E-9,0,(B6*F6-C6*D6)/(B6*E6-C6^2))) | H6: =IF(B6<'參數'!$B$11,"",(D6-G6*C6)/B6) | I6: =IF(B6>0,D6/B6,"") | J6: =IF(B6>1,SQRT(SUMPRODUCT(('債券'!$Y$5:$Y$404=1)*('債券'!$X$5:$X$404=$A6)*('債券'!$AT$5:$AT$404-I6)^2)/(B6-1)),"") | K6: =SUMPRODUCT(('債券'!$AY$5:$AY$404=1)*('債券'!$X$5:$X$404=$A6)) | L6: =IF(K6>0,SUMPRODUCT(('債券'!$AY$5:$AY$404=1)*('債券'!$X$5:$X$404=$A6)*'債券'!$AX$5:$AX$404)/K6,"") | M6: =IF(K6>1,SQRT(SUMPRODUCT(('債券'!$AY$5:$AY$404=1)*('債券'!$X$5:$X$404=$A6)*('債券'!$AX$5:$AX$404-L6)^2)/(K6-1)),"") | N6: =SUMPRODUCT(('債券'!$BA$5:$BA$404=1)*('債券'!$X$5:$X$404=$A6)) | O6: =IF(N6>0,SUMPRODUCT(('債券'!$BA$5:$BA$404=1)*('債券'!$X$5:$X$404=$A6)*'債券'!$AZ$5:$AZ$404)/N6,"") | P6: =IF(N6>1,SQRT(SUMPRODUCT(('債券'!$BA$5:$BA$404=1)*('債券'!$X$5:$X$404=$A6)*('債券'!$AZ$5:$AZ$404-O6)^2)/(N6-1)),"") | Q6: =SUMPRODUCT(('債券'!$BC$5:$BC$404=1)*('債券'!$X$5:$X$404=$A6)) | R6: =IF(Q6>0,SUMPRODUCT(('債券'!$BC$5:$BC$404=1)*('債券'!$X$5:$X$404=$A6)*'債券'!$BB$5:$BB$404)/Q6,"") | S6: =IF(Q6>1,SQRT(SUMPRODUCT(('債券'!$BC$5:$BC$404=1)*('債券'!$X$5:$X$404=$A6)*('債券'!$BB$5:$BB$404-R6)^2)/(Q6-1)),"")
A7: BBB | B7: =SUMPRODUCT(('債券'!$Y$5:$Y$404=1)*('債券'!$X$5:$X$404=$A7)) | C7: =SUMPRODUCT(('債券'!$Y$5:$Y$404=1)*('債券'!$X$5:$X$404=$A7)*'債券'!$AU$5:$AU$404) | D7: =SUMPRODUCT(('債券'!$Y$5:$Y$404=1)*('債券'!$X$5:$X$404=$A7)*'債券'!$AT$5:$AT$404) | E7: =SUMPRODUCT(('債券'!$Y$5:$Y$404=1)*('債券'!$X$5:$X$404=$A7)*'債券'!$AU$5:$AU$404^2) | F7: =SUMPRODUCT(('債券'!$Y$5:$Y$404=1)*('債券'!$X$5:$X$404=$A7)*'債券'!$AU$5:$AU$404*'債券'!$AT$5:$AT$404) | G7: =IF(B7<'參數'!$B$11,"",IF(ABS((B7*E7-C7^2))<1E-9,0,(B7*F7-C7*D7)/(B7*E7-C7^2))) | H7: =IF(B7<'參數'!$B$11,"",(D7-G7*C7)/B7) | I7: =IF(B7>0,D7/B7,"") | J7: =IF(B7>1,SQRT(SUMPRODUCT(('債券'!$Y$5:$Y$404=1)*('債券'!$X$5:$X$404=$A7)*('債券'!$AT$5:$AT$404-I7)^2)/(B7-1)),"") | K7: =SUMPRODUCT(('債券'!$AY$5:$AY$404=1)*('債券'!$X$5:$X$404=$A7)) | L7: =IF(K7>0,SUMPRODUCT(('債券'!$AY$5:$AY$404=1)*('債券'!$X$5:$X$404=$A7)*'債券'!$AX$5:$AX$404)/K7,"") | M7: =IF(K7>1,SQRT(SUMPRODUCT(('債券'!$AY$5:$AY$404=1)*('債券'!$X$5:$X$404=$A7)*('債券'!$AX$5:$AX$404-L7)^2)/(K7-1)),"") | N7: =SUMPRODUCT(('債券'!$BA$5:$BA$404=1)*('債券'!$X$5:$X$404=$A7)) | O7: =IF(N7>0,SUMPRODUCT(('債券'!$BA$5:$BA$404=1)*('債券'!$X$5:$X$404=$A7)*'債券'!$AZ$5:$AZ$404)/N7,"") | P7: =IF(N7>1,SQRT(SUMPRODUCT(('債券'!$BA$5:$BA$404=1)*('債券'!$X$5:$X$404=$A7)*('債券'!$AZ$5:$AZ$404-O7)^2)/(N7-1)),"") | Q7: =SUMPRODUCT(('債券'!$BC$5:$BC$404=1)*('債券'!$X$5:$X$404=$A7)) | R7: =IF(Q7>0,SUMPRODUCT(('債券'!$BC$5:$BC$404=1)*('債券'!$X$5:$X$404=$A7)*'債券'!$BB$5:$BB$404)/Q7,"") | S7: =IF(Q7>1,SQRT(SUMPRODUCT(('債券'!$BC$5:$BC$404=1)*('債券'!$X$5:$X$404=$A7)*('債券'!$BB$5:$BB$404-R7)^2)/(Q7-1)),"")
A8: HY | B8: =SUMPRODUCT(('債券'!$Y$5:$Y$404=1)*('債券'!$X$5:$X$404=$A8)) | C8: =SUMPRODUCT(('債券'!$Y$5:$Y$404=1)*('債券'!$X$5:$X$404=$A8)*'債券'!$AU$5:$AU$404) | D8: =SUMPRODUCT(('債券'!$Y$5:$Y$404=1)*('債券'!$X$5:$X$404=$A8)*'債券'!$AT$5:$AT$404) | E8: =SUMPRODUCT(('債券'!$Y$5:$Y$404=1)*('債券'!$X$5:$X$404=$A8)*'債券'!$AU$5:$AU$404^2) | F8: =SUMPRODUCT(('債券'!$Y$5:$Y$404=1)*('債券'!$X$5:$X$404=$A8)*'債券'!$AU$5:$AU$404*'債券'!$AT$5:$AT$404) | G8: =IF(B8<'參數'!$B$11,"",IF(ABS((B8*E8-C8^2))<1E-9,0,(B8*F8-C8*D8)/(B8*E8-C8^2))) | H8: =IF(B8<'參數'!$B$11,"",(D8-G8*C8)/B8) | I8: =IF(B8>0,D8/B8,"") | J8: =IF(B8>1,SQRT(SUMPRODUCT(('債券'!$Y$5:$Y$404=1)*('債券'!$X$5:$X$404=$A8)*('債券'!$AT$5:$AT$404-I8)^2)/(B8-1)),"") | K8: =SUMPRODUCT(('債券'!$AY$5:$AY$404=1)*('債券'!$X$5:$X$404=$A8)) | L8: =IF(K8>0,SUMPRODUCT(('債券'!$AY$5:$AY$404=1)*('債券'!$X$5:$X$404=$A8)*'債券'!$AX$5:$AX$404)/K8,"") | M8: =IF(K8>1,SQRT(SUMPRODUCT(('債券'!$AY$5:$AY$404=1)*('債券'!$X$5:$X$404=$A8)*('債券'!$AX$5:$AX$404-L8)^2)/(K8-1)),"") | N8: =SUMPRODUCT(('債券'!$BA$5:$BA$404=1)*('債券'!$X$5:$X$404=$A8)) | O8: =IF(N8>0,SUMPRODUCT(('債券'!$BA$5:$BA$404=1)*('債券'!$X$5:$X$404=$A8)*'債券'!$AZ$5:$AZ$404)/N8,"") | P8: =IF(N8>1,SQRT(SUMPRODUCT(('債券'!$BA$5:$BA$404=1)*('債券'!$X$5:$X$404=$A8)*('債券'!$AZ$5:$AZ$404-O8)^2)/(N8-1)),"") | Q8: =SUMPRODUCT(('債券'!$BC$5:$BC$404=1)*('債券'!$X$5:$X$404=$A8)) | R8: =IF(Q8>0,SUMPRODUCT(('債券'!$BC$5:$BC$404=1)*('債券'!$X$5:$X$404=$A8)*'債券'!$BB$5:$BB$404)/Q8,"") | S8: =IF(Q8>1,SQRT(SUMPRODUCT(('債券'!$BC$5:$BC$404=1)*('債券'!$X$5:$X$404=$A8)*('債券'!$BB$5:$BB$404-R8)^2)/(Q8-1)),"")
A10: B. Carry 分群（評等 × 天期）
B11: 檔數 | G11: OAS 平均 | L11: OAS 標準差
A12: 評等分群 | B12: 1-3y | C12: 3-5y | D12: 5-7y | E12: 7-10y | F12: 10y+ | G12: 1-3y | H12: 3-5y | I12: 5-7y | J12: 7-10y | K12: 10y+ | L12: 1-3y | M12: 3-5y | N12: 5-7y | O12: 7-10y | P12: 10y+
A13: AA以上 | B13: =SUMPRODUCT(('債券'!$Y$5:$Y$404=1)*('債券'!$X$5:$X$404=$A13)*('債券'!$V$5:$V$404=B$12)) | C13: =SUMPRODUCT(('債券'!$Y$5:$Y$404=1)*('債券'!$X$5:$X$404=$A13)*('債券'!$V$5:$V$404=C$12)) | D13: =SUMPRODUCT(('債券'!$Y$5:$Y$404=1)*('債券'!$X$5:$X$404=$A13)*('債券'!$V$5:$V$404=D$12)) | E13: =SUMPRODUCT(('債券'!$Y$5:$Y$404=1)*('債券'!$X$5:$X$404=$A13)*('債券'!$V$5:$V$404=E$12)) | F13: =SUMPRODUCT(('債券'!$Y$5:$Y$404=1)*('債券'!$X$5:$X$404=$A13)*('債券'!$V$5:$V$404=F$12)) | G13: =IF(B13>0,SUMPRODUCT(('債券'!$Y$5:$Y$404=1)*('債券'!$X$5:$X$404=$A13)*('債券'!$V$5:$V$404=B$12)*'債券'!$AT$5:$AT$404)/B13,"") | H13: =IF(C13>0,SUMPRODUCT(('債券'!$Y$5:$Y$404=1)*('債券'!$X$5:$X$404=$A13)*('債券'!$V$5:$V$404=C$12)*'債券'!$AT$5:$AT$404)/C13,"") | I13: =IF(D13>0,SUMPRODUCT(('債券'!$Y$5:$Y$404=1)*('債券'!$X$5:$X$404=$A13)*('債券'!$V$5:$V$404=D$12)*'債券'!$AT$5:$AT$404)/D13,"") | J13: =IF(E13>0,SUMPRODUCT(('債券'!$Y$5:$Y$404=1)*('債券'!$X$5:$X$404=$A13)*('債券'!$V$5:$V$404=E$12)*'債券'!$AT$5:$AT$404)/E13,"") | K13: =IF(F13>0,SUMPRODUCT(('債券'!$Y$5:$Y$404=1)*('債券'!$X$5:$X$404=$A13)*('債券'!$V$5:$V$404=F$12)*'債券'!$AT$5:$AT$404)/F13,"") | L13: =IF(B13>1,SQRT(SUMPRODUCT(('債券'!$Y$5:$Y$404=1)*('債券'!$X$5:$X$404=$A13)*('債券'!$V$5:$V$404=B$12)*('債券'!$AT$5:$AT$404-G13)^2)/(B13-1)),"") | M13: =IF(C13>1,SQRT(SUMPRODUCT(('債券'!$Y$5:$Y$404=1)*('債券'!$X$5:$X$404=$A13)*('債券'!$V$5:$V$404=C$12)*('債券'!$AT$5:$AT$404-H13)^2)/(C13-1)),"") | N13: =IF(D13>1,SQRT(SUMPRODUCT(('債券'!$Y$5:$Y$404=1)*('債券'!$X$5:$X$404=$A13)*('債券'!$V$5:$V$404=D$12)*('債券'!$AT$5:$AT$404-I13)^2)/(D13-1)),"") | O13: =IF(E13>1,SQRT(SUMPRODUCT(('債券'!$Y$5:$Y$404=1)*('債券'!$X$5:$X$404=$A13)*('債券'!$V$5:$V$404=E$12)*('債券'!$AT$5:$AT$404-J13)^2)/(E13-1)),"") | P13: =IF(F13>1,SQRT(SUMPRODUCT(('債券'!$Y$5:$Y$404=1)*('債券'!$X$5:$X$404=$A13)*('債券'!$V$5:$V$404=F$12)*('債券'!$AT$5:$AT$404-K13)^2)/(F13-1)),"")
A14: A | B14: =SUMPRODUCT(('債券'!$Y$5:$Y$404=1)*('債券'!$X$5:$X$404=$A14)*('債券'!$V$5:$V$404=B$12)) | C14: =SUMPRODUCT(('債券'!$Y$5:$Y$404=1)*('債券'!$X$5:$X$404=$A14)*('債券'!$V$5:$V$404=C$12)) | D14: =SUMPRODUCT(('債券'!$Y$5:$Y$404=1)*('債券'!$X$5:$X$404=$A14)*('債券'!$V$5:$V$404=D$12)) | E14: =SUMPRODUCT(('債券'!$Y$5:$Y$404=1)*('債券'!$X$5:$X$404=$A14)*('債券'!$V$5:$V$404=E$12)) | F14: =SUMPRODUCT(('債券'!$Y$5:$Y$404=1)*('債券'!$X$5:$X$404=$A14)*('債券'!$V$5:$V$404=F$12)) | G14: =IF(B14>0,SUMPRODUCT(('債券'!$Y$5:$Y$404=1)*('債券'!$X$5:$X$404=$A14)*('債券'!$V$5:$V$404=B$12)*'債券'!$AT$5:$AT$404)/B14,"") | H14: =IF(C14>0,SUMPRODUCT(('債券'!$Y$5:$Y$404=1)*('債券'!$X$5:$X$404=$A14)*('債券'!$V$5:$V$404=C$12)*'債券'!$AT$5:$AT$404)/C14,"") | I14: =IF(D14>0,SUMPRODUCT(('債券'!$Y$5:$Y$404=1)*('債券'!$X$5:$X$404=$A14)*('債券'!$V$5:$V$404=D$12)*'債券'!$AT$5:$AT$404)/D14,"") | J14: =IF(E14>0,SUMPRODUCT(('債券'!$Y$5:$Y$404=1)*('債券'!$X$5:$X$404=$A14)*('債券'!$V$5:$V$404=E$12)*'債券'!$AT$5:$AT$404)/E14,"") | K14: =IF(F14>0,SUMPRODUCT(('債券'!$Y$5:$Y$404=1)*('債券'!$X$5:$X$404=$A14)*('債券'!$V$5:$V$404=F$12)*'債券'!$AT$5:$AT$404)/F14,"") | L14: =IF(B14>1,SQRT(SUMPRODUCT(('債券'!$Y$5:$Y$404=1)*('債券'!$X$5:$X$404=$A14)*('債券'!$V$5:$V$404=B$12)*('債券'!$AT$5:$AT$404-G14)^2)/(B14-1)),"") | M14: =IF(C14>1,SQRT(SUMPRODUCT(('債券'!$Y$5:$Y$404=1)*('債券'!$X$5:$X$404=$A14)*('債券'!$V$5:$V$404=C$12)*('債券'!$AT$5:$AT$404-H14)^2)/(C14-1)),"") | N14: =IF(D14>1,SQRT(SUMPRODUCT(('債券'!$Y$5:$Y$404=1)*('債券'!$X$5:$X$404=$A14)*('債券'!$V$5:$V$404=D$12)*('債券'!$AT$5:$AT$404-I14)^2)/(D14-1)),"") | O14: =IF(E14>1,SQRT(SUMPRODUCT(('債券'!$Y$5:$Y$404=1)*('債券'!$X$5:$X$404=$A14)*('債券'!$V$5:$V$404=E$12)*('債券'!$AT$5:$AT$404-J14)^2)/(E14-1)),"") | P14: =IF(F14>1,SQRT(SUMPRODUCT(('債券'!$Y$5:$Y$404=1)*('債券'!$X$5:$X$404=$A14)*('債券'!$V$5:$V$404=F$12)*('債券'!$AT$5:$AT$404-K14)^2)/(F14-1)),"")
A15: BBB | B15: =SUMPRODUCT(('債券'!$Y$5:$Y$404=1)*('債券'!$X$5:$X$404=$A15)*('債券'!$V$5:$V$404=B$12)) | C15: =SUMPRODUCT(('債券'!$Y$5:$Y$404=1)*('債券'!$X$5:$X$404=$A15)*('債券'!$V$5:$V$404=C$12)) | D15: =SUMPRODUCT(('債券'!$Y$5:$Y$404=1)*('債券'!$X$5:$X$404=$A15)*('債券'!$V$5:$V$404=D$12)) | E15: =SUMPRODUCT(('債券'!$Y$5:$Y$404=1)*('債券'!$X$5:$X$404=$A15)*('債券'!$V$5:$V$404=E$12)) | F15: =SUMPRODUCT(('債券'!$Y$5:$Y$404=1)*('債券'!$X$5:$X$404=$A15)*('債券'!$V$5:$V$404=F$12)) | G15: =IF(B15>0,SUMPRODUCT(('債券'!$Y$5:$Y$404=1)*('債券'!$X$5:$X$404=$A15)*('債券'!$V$5:$V$404=B$12)*'債券'!$AT$5:$AT$404)/B15,"") | H15: =IF(C15>0,SUMPRODUCT(('債券'!$Y$5:$Y$404=1)*('債券'!$X$5:$X$404=$A15)*('債券'!$V$5:$V$404=C$12)*'債券'!$AT$5:$AT$404)/C15,"") | I15: =IF(D15>0,SUMPRODUCT(('債券'!$Y$5:$Y$404=1)*('債券'!$X$5:$X$404=$A15)*('債券'!$V$5:$V$404=D$12)*'債券'!$AT$5:$AT$404)/D15,"") | J15: =IF(E15>0,SUMPRODUCT(('債券'!$Y$5:$Y$404=1)*('債券'!$X$5:$X$404=$A15)*('債券'!$V$5:$V$404=E$12)*'債券'!$AT$5:$AT$404)/E15,"") | K15: =IF(F15>0,SUMPRODUCT(('債券'!$Y$5:$Y$404=1)*('債券'!$X$5:$X$404=$A15)*('債券'!$V$5:$V$404=F$12)*'債券'!$AT$5:$AT$404)/F15,"") | L15: =IF(B15>1,SQRT(SUMPRODUCT(('債券'!$Y$5:$Y$404=1)*('債券'!$X$5:$X$404=$A15)*('債券'!$V$5:$V$404=B$12)*('債券'!$AT$5:$AT$404-G15)^2)/(B15-1)),"") | M15: =IF(C15>1,SQRT(SUMPRODUCT(('債券'!$Y$5:$Y$404=1)*('債券'!$X$5:$X$404=$A15)*('債券'!$V$5:$V$404=C$12)*('債券'!$AT$5:$AT$404-H15)^2)/(C15-1)),"") | N15: =IF(D15>1,SQRT(SUMPRODUCT(('債券'!$Y$5:$Y$404=1)*('債券'!$X$5:$X$404=$A15)*('債券'!$V$5:$V$404=D$12)*('債券'!$AT$5:$AT$404-I15)^2)/(D15-1)),"") | O15: =IF(E15>1,SQRT(SUMPRODUCT(('債券'!$Y$5:$Y$404=1)*('債券'!$X$5:$X$404=$A15)*('債券'!$V$5:$V$404=E$12)*('債券'!$AT$5:$AT$404-J15)^2)/(E15-1)),"") | P15: =IF(F15>1,SQRT(SUMPRODUCT(('債券'!$Y$5:$Y$404=1)*('債券'!$X$5:$X$404=$A15)*('債券'!$V$5:$V$404=F$12)*('債券'!$AT$5:$AT$404-K15)^2)/(F15-1)),"")
A16: HY | B16: =SUMPRODUCT(('債券'!$Y$5:$Y$404=1)*('債券'!$X$5:$X$404=$A16)*('債券'!$V$5:$V$404=B$12)) | C16: =SUMPRODUCT(('債券'!$Y$5:$Y$404=1)*('債券'!$X$5:$X$404=$A16)*('債券'!$V$5:$V$404=C$12)) | D16: =SUMPRODUCT(('債券'!$Y$5:$Y$404=1)*('債券'!$X$5:$X$404=$A16)*('債券'!$V$5:$V$404=D$12)) | E16: =SUMPRODUCT(('債券'!$Y$5:$Y$404=1)*('債券'!$X$5:$X$404=$A16)*('債券'!$V$5:$V$404=E$12)) | F16: =SUMPRODUCT(('債券'!$Y$5:$Y$404=1)*('債券'!$X$5:$X$404=$A16)*('債券'!$V$5:$V$404=F$12)) | G16: =IF(B16>0,SUMPRODUCT(('債券'!$Y$5:$Y$404=1)*('債券'!$X$5:$X$404=$A16)*('債券'!$V$5:$V$404=B$12)*'債券'!$AT$5:$AT$404)/B16,"") | H16: =IF(C16>0,SUMPRODUCT(('債券'!$Y$5:$Y$404=1)*('債券'!$X$5:$X$404=$A16)*('債券'!$V$5:$V$404=C$12)*'債券'!$AT$5:$AT$404)/C16,"") | I16: =IF(D16>0,SUMPRODUCT(('債券'!$Y$5:$Y$404=1)*('債券'!$X$5:$X$404=$A16)*('債券'!$V$5:$V$404=D$12)*'債券'!$AT$5:$AT$404)/D16,"") | J16: =IF(E16>0,SUMPRODUCT(('債券'!$Y$5:$Y$404=1)*('債券'!$X$5:$X$404=$A16)*('債券'!$V$5:$V$404=E$12)*'債券'!$AT$5:$AT$404)/E16,"") | K16: =IF(F16>0,SUMPRODUCT(('債券'!$Y$5:$Y$404=1)*('債券'!$X$5:$X$404=$A16)*('債券'!$V$5:$V$404=F$12)*'債券'!$AT$5:$AT$404)/F16,"") | L16: =IF(B16>1,SQRT(SUMPRODUCT(('債券'!$Y$5:$Y$404=1)*('債券'!$X$5:$X$404=$A16)*('債券'!$V$5:$V$404=B$12)*('債券'!$AT$5:$AT$404-G16)^2)/(B16-1)),"") | M16: =IF(C16>1,SQRT(SUMPRODUCT(('債券'!$Y$5:$Y$404=1)*('債券'!$X$5:$X$404=$A16)*('債券'!$V$5:$V$404=C$12)*('債券'!$AT$5:$AT$404-H16)^2)/(C16-1)),"") | N16: =IF(D16>1,SQRT(SUMPRODUCT(('債券'!$Y$5:$Y$404=1)*('債券'!$X$5:$X$404=$A16)*('債券'!$V$5:$V$404=D$12)*('債券'!$AT$5:$AT$404-I16)^2)/(D16-1)),"") | O16: =IF(E16>1,SQRT(SUMPRODUCT(('債券'!$Y$5:$Y$404=1)*('債券'!$X$5:$X$404=$A16)*('債券'!$V$5:$V$404=E$12)*('債券'!$AT$5:$AT$404-J16)^2)/(E16-1)),"") | P16: =IF(F16>1,SQRT(SUMPRODUCT(('債券'!$Y$5:$Y$404=1)*('債券'!$X$5:$X$404=$A16)*('債券'!$V$5:$V$404=F$12)*('債券'!$AT$5:$AT$404-K16)^2)/(F16-1)),"")
A18: C. 發行人曲線（對應「發行人」表 D 欄）
A19: 債券 Ticker | B19: 檔數 | C19: Σx | D19: Σy | E19: Σx² | F19: Σxy | G19: 曲線斜率 | H19: 曲線截距
A20: =IF('發行人'!$D5="","",'發行人'!$D5) | B20: =SUMPRODUCT(('債券'!$Y$5:$Y$404=1)*('債券'!$B$5:$B$404=$A20)*($A20<>"")) | C20: =SUMPRODUCT(('債券'!$Y$5:$Y$404=1)*('債券'!$B$5:$B$404=$A20)*($A20<>"")*'債券'!$AU$5:$AU$404) | D20: =SUMPRODUCT(('債券'!$Y$5:$Y$404=1)*('債券'!$B$5:$B$404=$A20)*($A20<>"")*'債券'!$AT$5:$AT$404) | E20: =SUMPRODUCT(('債券'!$Y$5:$Y$404=1)*('債券'!$B$5:$B$404=$A20)*($A20<>"")*'債券'!$AU$5:$AU$404^2) | F20: =SUMPRODUCT(('債券'!$Y$5:$Y$404=1)*('債券'!$B$5:$B$404=$A20)*($A20<>"")*'債券'!$AU$5:$AU$404*'債券'!$AT$5:$AT$404) | G20: =IF(B20<'參數'!$B$10,"",IF(ABS((B20*E20-C20^2))<1E-9,0,(B20*F20-C20*D20)/(B20*E20-C20^2))) | H20: =IF(B20<'參數'!$B$10,"",(D20-G20*C20)/B20)
A21: =IF('發行人'!$D6="","",'發行人'!$D6) | B21: =SUMPRODUCT(('債券'!$Y$5:$Y$404=1)*('債券'!$B$5:$B$404=$A21)*($A21<>"")) | C21: =SUMPRODUCT(('債券'!$Y$5:$Y$404=1)*('債券'!$B$5:$B$404=$A21)*($A21<>"")*'債券'!$AU$5:$AU$404) | D21: =SUMPRODUCT(('債券'!$Y$5:$Y$404=1)*('債券'!$B$5:$B$404=$A21)*($A21<>"")*'債券'!$AT$5:$AT$404) | E21: =SUMPRODUCT(('債券'!$Y$5:$Y$404=1)*('債券'!$B$5:$B$404=$A21)*($A21<>"")*'債券'!$AU$5:$AU$404^2) | F21: =SUMPRODUCT(('債券'!$Y$5:$Y$404=1)*('債券'!$B$5:$B$404=$A21)*($A21<>"")*'債券'!$AU$5:$AU$404*'債券'!$AT$5:$AT$404) | G21: =IF(B21<'參數'!$B$10,"",IF(ABS((B21*E21-C21^2))<1E-9,0,(B21*F21-C21*D21)/(B21*E21-C21^2))) | H21: =IF(B21<'參數'!$B$10,"",(D21-G21*C21)/B21)
A22: =IF('發行人'!$D7="","",'發行人'!$D7) | B22: =SUMPRODUCT(('債券'!$Y$5:$Y$404=1)*('債券'!$B$5:$B$404=$A22)*($A22<>"")) | C22: =SUMPRODUCT(('債券'!$Y$5:$Y$404=1)*('債券'!$B$5:$B$404=$A22)*($A22<>"")*'債券'!$AU$5:$AU$404) | D22: =SUMPRODUCT(('債券'!$Y$5:$Y$404=1)*('債券'!$B$5:$B$404=$A22)*($A22<>"")*'債券'!$AT$5:$AT$404) | E22: =SUMPRODUCT(('債券'!$Y$5:$Y$404=1)*('債券'!$B$5:$B$404=$A22)*($A22<>"")*'債券'!$AU$5:$AU$404^2) | F22: =SUMPRODUCT(('債券'!$Y$5:$Y$404=1)*('債券'!$B$5:$B$404=$A22)*($A22<>"")*'債券'!$AU$5:$AU$404*'債券'!$AT$5:$AT$404) | G22: =IF(B22<'參數'!$B$10,"",IF(ABS((B22*E22-C22^2))<1E-9,0,(B22*F22-C22*D22)/(B22*E22-C22^2))) | H22: =IF(B22<'參數'!$B$10,"",(D22-G22*C22)/B22)
A23: =IF('發行人'!$D8="","",'發行人'!$D8) | B23: =SUMPRODUCT(('債券'!$Y$5:$Y$404=1)*('債券'!$B$5:$B$404=$A23)*($A23<>"")) | C23: =SUMPRODUCT(('債券'!$Y$5:$Y$404=1)*('債券'!$B$5:$B$404=$A23)*($A23<>"")*'債券'!$AU$5:$AU$404) | D23: =SUMPRODUCT(('債券'!$Y$5:$Y$404=1)*('債券'!$B$5:$B$404=$A23)*($A23<>"")*'債券'!$AT$5:$AT$404) | E23: =SUMPRODUCT(('債券'!$Y$5:$Y$404=1)*('債券'!$B$5:$B$404=$A23)*($A23<>"")*'債券'!$AU$5:$AU$404^2) | F23: =SUMPRODUCT(('債券'!$Y$5:$Y$404=1)*('債券'!$B$5:$B$404=$A23)*($A23<>"")*'債券'!$AU$5:$AU$404*'債券'!$AT$5:$AT$404) | G23: =IF(B23<'參數'!$B$10,"",IF(ABS((B23*E23-C23^2))<1E-9,0,(B23*F23-C23*D23)/(B23*E23-C23^2))) | H23: =IF(B23<'參數'!$B$10,"",(D23-G23*C23)/B23)
A24: =IF('發行人'!$D9="","",'發行人'!$D9) | B24: =SUMPRODUCT(('債券'!$Y$5:$Y$404=1)*('債券'!$B$5:$B$404=$A24)*($A24<>"")) | C24: =SUMPRODUCT(('債券'!$Y$5:$Y$404=1)*('債券'!$B$5:$B$404=$A24)*($A24<>"")*'債券'!$AU$5:$AU$404) | D24: =SUMPRODUCT(('債券'!$Y$5:$Y$404=1)*('債券'!$B$5:$B$404=$A24)*($A24<>"")*'債券'!$AT$5:$AT$404) | E24: =SUMPRODUCT(('債券'!$Y$5:$Y$404=1)*('債券'!$B$5:$B$404=$A24)*($A24<>"")*'債券'!$AU$5:$AU$404^2) | F24: =SUMPRODUCT(('債券'!$Y$5:$Y$404=1)*('債券'!$B$5:$B$404=$A24)*($A24<>"")*'債券'!$AU$5:$AU$404*'債券'!$AT$5:$AT$404) | G24: =IF(B24<'參數'!$B$10,"",IF(ABS((B24*E24-C24^2))<1E-9,0,(B24*F24-C24*D24)/(B24*E24-C24^2))) | H24: =IF(B24<'參數'!$B$10,"",(D24-G24*C24)/B24)
A25: =IF('發行人'!$D10="","",'發行人'!$D10) | B25: =SUMPRODUCT(('債券'!$Y$5:$Y$404=1)*('債券'!$B$5:$B$404=$A25)*($A25<>"")) | C25: =SUMPRODUCT(('債券'!$Y$5:$Y$404=1)*('債券'!$B$5:$B$404=$A25)*($A25<>"")*'債券'!$AU$5:$AU$404) | D25: =SUMPRODUCT(('債券'!$Y$5:$Y$404=1)*('債券'!$B$5:$B$404=$A25)*($A25<>"")*'債券'!$AT$5:$AT$404) | E25: =SUMPRODUCT(('債券'!$Y$5:$Y$404=1)*('債券'!$B$5:$B$404=$A25)*($A25<>"")*'債券'!$AU$5:$AU$404^2) | F25: =SUMPRODUCT(('債券'!$Y$5:$Y$404=1)*('債券'!$B$5:$B$404=$A25)*($A25<>"")*'債券'!$AU$5:$AU$404*'債券'!$AT$5:$AT$404) | G25: =IF(B25<'參數'!$B$10,"",IF(ABS((B25*E25-C25^2))<1E-9,0,(B25*F25-C25*D25)/(B25*E25-C25^2))) | H25: =IF(B25<'參數'!$B$10,"",(D25-G25*C25)/B25)
A26: =IF('發行人'!$D11="","",'發行人'!$D11) | B26: =SUMPRODUCT(('債券'!$Y$5:$Y$404=1)*('債券'!$B$5:$B$404=$A26)*($A26<>"")) | C26: =SUMPRODUCT(('債券'!$Y$5:$Y$404=1)*('債券'!$B$5:$B$404=$A26)*($A26<>"")*'債券'!$AU$5:$AU$404) | D26: =SUMPRODUCT(('債券'!$Y$5:$Y$404=1)*('債券'!$B$5:$B$404=$A26)*($A26<>"")*'債券'!$AT$5:$AT$404) | E26: =SUMPRODUCT(('債券'!$Y$5:$Y$404=1)*('債券'!$B$5:$B$404=$A26)*($A26<>"")*'債券'!$AU$5:$AU$404^2) | F26: =SUMPRODUCT(('債券'!$Y$5:$Y$404=1)*('債券'!$B$5:$B$404=$A26)*($A26<>"")*'債券'!$AU$5:$AU$404*'債券'!$AT$5:$AT$404) | G26: =IF(B26<'參數'!$B$10,"",IF(ABS((B26*E26-C26^2))<1E-9,0,(B26*F26-C26*D26)/(B26*E26-C26^2))) | H26: =IF(B26<'參數'!$B$10,"",(D26-G26*C26)/B26)
A27: =IF('發行人'!$D12="","",'發行人'!$D12) | B27: =SUMPRODUCT(('債券'!$Y$5:$Y$404=1)*('債券'!$B$5:$B$404=$A27)*($A27<>"")) | C27: =SUMPRODUCT(('債券'!$Y$5:$Y$404=1)*('債券'!$B$5:$B$404=$A27)*($A27<>"")*'債券'!$AU$5:$AU$404) | D27: =SUMPRODUCT(('債券'!$Y$5:$Y$404=1)*('債券'!$B$5:$B$404=$A27)*($A27<>"")*'債券'!$AT$5:$AT$404) | E27: =SUMPRODUCT(('債券'!$Y$5:$Y$404=1)*('債券'!$B$5:$B$404=$A27)*($A27<>"")*'債券'!$AU$5:$AU$404^2) | F27: =SUMPRODUCT(('債券'!$Y$5:$Y$404=1)*('債券'!$B$5:$B$404=$A27)*($A27<>"")*'債券'!$AU$5:$AU$404*'債券'!$AT$5:$AT$404) | G27: =IF(B27<'參數'!$B$10,"",IF(ABS((B27*E27-C27^2))<1E-9,0,(B27*F27-C27*D27)/(B27*E27-C27^2))) | H27: =IF(B27<'參數'!$B$10,"",(D27-G27*C27)/B27)
A28: =IF('發行人'!$D13="","",'發行人'!$D13) | B28: =SUMPRODUCT(('債券'!$Y$5:$Y$404=1)*('債券'!$B$5:$B$404=$A28)*($A28<>"")) | C28: =SUMPRODUCT(('債券'!$Y$5:$Y$404=1)*('債券'!$B$5:$B$404=$A28)*($A28<>"")*'債券'!$AU$5:$AU$404) | D28: =SUMPRODUCT(('債券'!$Y$5:$Y$404=1)*('債券'!$B$5:$B$404=$A28)*($A28<>"")*'債券'!$AT$5:$AT$404) | E28: =SUMPRODUCT(('債券'!$Y$5:$Y$404=1)*('債券'!$B$5:$B$404=$A28)*($A28<>"")*'債券'!$AU$5:$AU$404^2) | F28: =SUMPRODUCT(('債券'!$Y$5:$Y$404=1)*('債券'!$B$5:$B$404=$A28)*($A28<>"")*'債券'!$AU$5:$AU$404*'債券'!$AT$5:$AT$404) | G28: =IF(B28<'參數'!$B$10,"",IF(ABS((B28*E28-C28^2))<1E-9,0,(B28*F28-C28*D28)/(B28*E28-C28^2))) | H28: =IF(B28<'參數'!$B$10,"",(D28-G28*C28)/B28)
A29: =IF('發行人'!$D14="","",'發行人'!$D14) | B29: =SUMPRODUCT(('債券'!$Y$5:$Y$404=1)*('債券'!$B$5:$B$404=$A29)*($A29<>"")) | C29: =SUMPRODUCT(('債券'!$Y$5:$Y$404=1)*('債券'!$B$5:$B$404=$A29)*($A29<>"")*'債券'!$AU$5:$AU$404) | D29: =SUMPRODUCT(('債券'!$Y$5:$Y$404=1)*('債券'!$B$5:$B$404=$A29)*($A29<>"")*'債券'!$AT$5:$AT$404) | E29: =SUMPRODUCT(('債券'!$Y$5:$Y$404=1)*('債券'!$B$5:$B$404=$A29)*($A29<>"")*'債券'!$AU$5:$AU$404^2) | F29: =SUMPRODUCT(('債券'!$Y$5:$Y$404=1)*('債券'!$B$5:$B$404=$A29)*($A29<>"")*'債券'!$AU$5:$AU$404*'債券'!$AT$5:$AT$404) | G29: =IF(B29<'參數'!$B$10,"",IF(ABS((B29*E29-C29^2))<1E-9,0,(B29*F29-C29*D29)/(B29*E29-C29^2))) | H29: =IF(B29<'參數'!$B$10,"",(D29-G29*C29)/B29)
A30: =IF('發行人'!$D15="","",'發行人'!$D15) | B30: =SUMPRODUCT(('債券'!$Y$5:$Y$404=1)*('債券'!$B$5:$B$404=$A30)*($A30<>"")) | C30: =SUMPRODUCT(('債券'!$Y$5:$Y$404=1)*('債券'!$B$5:$B$404=$A30)*($A30<>"")*'債券'!$AU$5:$AU$404) | D30: =SUMPRODUCT(('債券'!$Y$5:$Y$404=1)*('債券'!$B$5:$B$404=$A30)*($A30<>"")*'債券'!$AT$5:$AT$404) | E30: =SUMPRODUCT(('債券'!$Y$5:$Y$404=1)*('債券'!$B$5:$B$404=$A30)*($A30<>"")*'債券'!$AU$5:$AU$404^2) | F30: =SUMPRODUCT(('債券'!$Y$5:$Y$404=1)*('債券'!$B$5:$B$404=$A30)*($A30<>"")*'債券'!$AU$5:$AU$404*'債券'!$AT$5:$AT$404) | G30: =IF(B30<'參數'!$B$10,"",IF(ABS((B30*E30-C30^2))<1E-9,0,(B30*F30-C30*D30)/(B30*E30-C30^2))) | H30: =IF(B30<'參數'!$B$10,"",(D30-G30*C30)/B30)
A31: =IF('發行人'!$D16="","",'發行人'!$D16) | B31: =SUMPRODUCT(('債券'!$Y$5:$Y$404=1)*('債券'!$B$5:$B$404=$A31)*($A31<>"")) | C31: =SUMPRODUCT(('債券'!$Y$5:$Y$404=1)*('債券'!$B$5:$B$404=$A31)*($A31<>"")*'債券'!$AU$5:$AU$404) | D31: =SUMPRODUCT(('債券'!$Y$5:$Y$404=1)*('債券'!$B$5:$B$404=$A31)*($A31<>"")*'債券'!$AT$5:$AT$404) | E31: =SUMPRODUCT(('債券'!$Y$5:$Y$404=1)*('債券'!$B$5:$B$404=$A31)*($A31<>"")*'債券'!$AU$5:$AU$404^2) | F31: =SUMPRODUCT(('債券'!$Y$5:$Y$404=1)*('債券'!$B$5:$B$404=$A31)*($A31<>"")*'債券'!$AU$5:$AU$404*'債券'!$AT$5:$AT$404) | G31: =IF(B31<'參數'!$B$10,"",IF(ABS((B31*E31-C31^2))<1E-9,0,(B31*F31-C31*D31)/(B31*E31-C31^2))) | H31: =IF(B31<'參數'!$B$10,"",(D31-G31*C31)/B31)
... A59: =IF('發行人'!$D44="","",'發行人'!$D44) | B59: =SUMPRODUCT(('債券'!$Y$5:$Y$404=1)*('債券'!$B$5:$B$404=$A59)*($A59<>"")) | C59: =SUMPRODUCT(('債券'!$Y$5:$Y$404=1)*('債券'!$B$5:$B$404=$A59)*($A59<>"")*'債券'!$AU$5:$AU$404) | D59: =SUMPRODUCT(('債券'!$Y$5:$Y$404=1)*('債券'!$B$5:$B$404=$A59)*($A59<>"")*'債券'!$AT$5:$AT$404) | E59: =SUMPRODUCT(('債券'!$Y$5:$Y$404=1)*('債券'!$B$5:$B$404=$A59)*($A59<>"")*'債券'!$AU$5:$AU$404^2) | F59: =SUMPRODUCT(('債券'!$Y$5:$Y$404=1)*('債券'!$B$5:$B$404=$A59)*($A59<>"")*'債券'!$AU$5:$AU$404*'債券'!$AT$5:$AT$404) | G59: =IF(B59<'參數'!$B$10,"",IF(ABS((B59*E59-C59^2))<1E-9,0,(B59*F59-C59*D59)/(B59*E59-C59^2))) | H59: =IF(B59<'參數'!$B$10,"",(D59-G59*C59)/B59)

Sheet 排行
A1: 綜合分數排行與分類概覽
A2: 全部有效債券依綜合分數排序（不分評等）。要看單一評等分群，請在「債券」表用篩選。
A4: 偏便宜／偏強勢 前 20 名（加碼研究清單）
A5: 排名 | B5: 債券代碼 | C5: 債券簡稱 | D5: 分類 | E5: 評等 | F5: 剩餘年限 | G5: OAS (bp) | H5: DTS | I5: Carry z | J5: Value z | K5: Momentum z | L5: 股票動能 z | M5: 綜合分數 | N5: 相對發行人 曲線 (bp)
A6: 1 | B6: =IF(ABS(LARGE('債券'!$BD$5:$BD$404,$A6))>1E8,"",IF(INDEX('債券'!$A$5:$A$404,MATCH(LARGE('債券'!$BD$5:$BD$404,$A6),'債券'!$BD$5:$BD$404,0))="","",INDEX('債券'!$A$5:$A$404,MATCH(LARGE('債券'!$BD$5:$BD$404,$A6),'債券'!$BD$5:$BD$404,0)))) | C6: =IF(ABS(LARGE('債券'!$BD$5:$BD$404,$A6))>1E8,"",IF(INDEX('債券'!$C$5:$C$404,MATCH(LARGE('債券'!$BD$5:$BD$404,$A6),'債券'!$BD$5:$BD$404,0))="","",INDEX('債券'!$C$5:$C$404,MATCH(LARGE('債券'!$BD$5:$BD$404,$A6),'債券'!$BD$5:$BD$404,0)))) | D6: =IF(ABS(LARGE('債券'!$BD$5:$BD$404,$A6))>1E8,"",IF(INDEX('債券'!$S$5:$S$404,MATCH(LARGE('債券'!$BD$5:$BD$404,$A6),'債券'!$BD$5:$BD$404,0))="","",INDEX('債券'!$S$5:$S$404,MATCH(LARGE('債券'!$BD$5:$BD$404,$A6),'債券'!$BD$5:$BD$404,0)))) | E6: =IF(ABS(LARGE('債券'!$BD$5:$BD$404,$A6))>1E8,"",IF(INDEX('債券'!$G$5:$G$404,MATCH(LARGE('債券'!$BD$5:$BD$404,$A6),'債券'!$BD$5:$BD$404,0))="","",INDEX('債券'!$G$5:$G$404,MATCH(LARGE('債券'!$BD$5:$BD$404,$A6),'債券'!$BD$5:$BD$404,0)))) | F6: =IF(ABS(LARGE('債券'!$BD$5:$BD$404,$A6))>1E8,"",IF(INDEX('債券'!$U$5:$U$404,MATCH(LARGE('債券'!$BD$5:$BD$404,$A6),'債券'!$BD$5:$BD$404,0))="","",INDEX('債券'!$U$5:$U$404,MATCH(LARGE('債券'!$BD$5:$BD$404,$A6),'債券'!$BD$5:$BD$404,0)))) | G6: =IF(ABS(LARGE('債券'!$BD$5:$BD$404,$A6))>1E8,"",IF(INDEX('債券'!$N$5:$N$404,MATCH(LARGE('債券'!$BD$5:$BD$404,$A6),'債券'!$BD$5:$BD$404,0))="","",INDEX('債券'!$N$5:$N$404,MATCH(LARGE('債券'!$BD$5:$BD$404,$A6),'債券'!$BD$5:$BD$404,0)))) | H6: =IF(ABS(LARGE('債券'!$BD$5:$BD$404,$A6))>1E8,"",IF(INDEX('債券'!$Z$5:$Z$404,MATCH(LARGE('債券'!$BD$5:$BD$404,$A6),'債券'!$BD$5:$BD$404,0))="","",INDEX('債券'!$Z$5:$Z$404,MATCH(LARGE('債券'!$BD$5:$BD$404,$A6),'債券'!$BD$5:$BD$404,0)))) | I6: =IF(ABS(LARGE('債券'!$BD$5:$BD$404,$A6))>1E8,"",IF(INDEX('債券'!$AF$5:$AF$404,MATCH(LARGE('債券'!$BD$5:$BD$404,$A6),'債券'!$BD$5:$BD$404,0))="","",INDEX('債券'!$AF$5:$AF$404,MATCH(LARGE('債券'!$BD$5:$BD$404,$A6),'債券'!$BD$5:$BD$404,0)))) | J6: =IF(ABS(LARGE('債券'!$BD$5:$BD$404,$A6))>1E8,"",IF(INDEX('債券'!$AM$5:$AM$404,MATCH(LARGE('債券'!$BD$5:$BD$404,$A6),'債券'!$BD$5:$BD$404,0))="","",INDEX('債券'!$AM$5:$AM$404,MATCH(LARGE('債券'!$BD$5:$BD$404,$A6),'債券'!$BD$5:$BD$404,0)))) | K6: =IF(ABS(LARGE('債券'!$BD$5:$BD$404,$A6))>1E8,"",IF(INDEX('債券'!$AO$5:$AO$404,MATCH(LARGE('債券'!$BD$5:$BD$404,$A6),'債券'!$BD$5:$BD$404,0))="","",INDEX('債券'!$AO$5:$AO$404,MATCH(LARGE('債券'!$BD$5:$BD$404,$A6),'債券'!$BD$5:$BD$404,0)))) | L6: =IF(ABS(LARGE('債券'!$BD$5:$BD$404,$A6))>1E8,"",IF(INDEX('債券'!$AP$5:$AP$404,MATCH(LARGE('債券'!$BD$5:$BD$404,$A6),'債券'!$BD$5:$BD$404,0))="","",INDEX('債券'!$AP$5:$AP$404,MATCH(LARGE('債券'!$BD$5:$BD$404,$A6),'債券'!$BD$5:$BD$404,0)))) | M6: =IF(ABS(LARGE('債券'!$BD$5:$BD$404,$A6))>1E8,"",IF(INDEX('債券'!$AQ$5:$AQ$404,MATCH(LARGE('債券'!$BD$5:$BD$404,$A6),'債券'!$BD$5:$BD$404,0))="","",INDEX('債券'!$AQ$5:$AQ$404,MATCH(LARGE('債券'!$BD$5:$BD$404,$A6),'債券'!$BD$5:$BD$404,0)))) | N6: =IF(ABS(LARGE('債券'!$BD$5:$BD$404,$A6))>1E8,"",IF(INDEX('債券'!$AI$5:$AI$404,MATCH(LARGE('債券'!$BD$5:$BD$404,$A6),'債券'!$BD$5:$BD$404,0))="","",INDEX('債券'!$AI$5:$AI$404,MATCH(LARGE('債券'!$BD$5:$BD$404,$A6),'債券'!$BD$5:$BD$404,0))))
A7: 2 | B7: =IF(ABS(LARGE('債券'!$BD$5:$BD$404,$A7))>1E8,"",IF(INDEX('債券'!$A$5:$A$404,MATCH(LARGE('債券'!$BD$5:$BD$404,$A7),'債券'!$BD$5:$BD$404,0))="","",INDEX('債券'!$A$5:$A$404,MATCH(LARGE('債券'!$BD$5:$BD$404,$A7),'債券'!$BD$5:$BD$404,0)))) | C7: =IF(ABS(LARGE('債券'!$BD$5:$BD$404,$A7))>1E8,"",IF(INDEX('債券'!$C$5:$C$404,MATCH(LARGE('債券'!$BD$5:$BD$404,$A7),'債券'!$BD$5:$BD$404,0))="","",INDEX('債券'!$C$5:$C$404,MATCH(LARGE('債券'!$BD$5:$BD$404,$A7),'債券'!$BD$5:$BD$404,0)))) | D7: =IF(ABS(LARGE('債券'!$BD$5:$BD$404,$A7))>1E8,"",IF(INDEX('債券'!$S$5:$S$404,MATCH(LARGE('債券'!$BD$5:$BD$404,$A7),'債券'!$BD$5:$BD$404,0))="","",INDEX('債券'!$S$5:$S$404,MATCH(LARGE('債券'!$BD$5:$BD$404,$A7),'債券'!$BD$5:$BD$404,0)))) | E7: =IF(ABS(LARGE('債券'!$BD$5:$BD$404,$A7))>1E8,"",IF(INDEX('債券'!$G$5:$G$404,MATCH(LARGE('債券'!$BD$5:$BD$404,$A7),'債券'!$BD$5:$BD$404,0))="","",INDEX('債券'!$G$5:$G$404,MATCH(LARGE('債券'!$BD$5:$BD$404,$A7),'債券'!$BD$5:$BD$404,0)))) | F7: =IF(ABS(LARGE('債券'!$BD$5:$BD$404,$A7))>1E8,"",IF(INDEX('債券'!$U$5:$U$404,MATCH(LARGE('債券'!$BD$5:$BD$404,$A7),'債券'!$BD$5:$BD$404,0))="","",INDEX('債券'!$U$5:$U$404,MATCH(LARGE('債券'!$BD$5:$BD$404,$A7),'債券'!$BD$5:$BD$404,0)))) | G7: =IF(ABS(LARGE('債券'!$BD$5:$BD$404,$A7))>1E8,"",IF(INDEX('債券'!$N$5:$N$404,MATCH(LARGE('債券'!$BD$5:$BD$404,$A7),'債券'!$BD$5:$BD$404,0))="","",INDEX('債券'!$N$5:$N$404,MATCH(LARGE('債券'!$BD$5:$BD$404,$A7),'債券'!$BD$5:$BD$404,0)))) | H7: =IF(ABS(LARGE('債券'!$BD$5:$BD$404,$A7))>1E8,"",IF(INDEX('債券'!$Z$5:$Z$404,MATCH(LARGE('債券'!$BD$5:$BD$404,$A7),'債券'!$BD$5:$BD$404,0))="","",INDEX('債券'!$Z$5:$Z$404,MATCH(LARGE('債券'!$BD$5:$BD$404,$A7),'債券'!$BD$5:$BD$404,0)))) | I7: =IF(ABS(LARGE('債券'!$BD$5:$BD$404,$A7))>1E8,"",IF(INDEX('債券'!$AF$5:$AF$404,MATCH(LARGE('債券'!$BD$5:$BD$404,$A7),'債券'!$BD$5:$BD$404,0))="","",INDEX('債券'!$AF$5:$AF$404,MATCH(LARGE('債券'!$BD$5:$BD$404,$A7),'債券'!$BD$5:$BD$404,0)))) | J7: =IF(ABS(LARGE('債券'!$BD$5:$BD$404,$A7))>1E8,"",IF(INDEX('債券'!$AM$5:$AM$404,MATCH(LARGE('債券'!$BD$5:$BD$404,$A7),'債券'!$BD$5:$BD$404,0))="","",INDEX('債券'!$AM$5:$AM$404,MATCH(LARGE('債券'!$BD$5:$BD$404,$A7),'債券'!$BD$5:$BD$404,0)))) | K7: =IF(ABS(LARGE('債券'!$BD$5:$BD$404,$A7))>1E8,"",IF(INDEX('債券'!$AO$5:$AO$404,MATCH(LARGE('債券'!$BD$5:$BD$404,$A7),'債券'!$BD$5:$BD$404,0))="","",INDEX('債券'!$AO$5:$AO$404,MATCH(LARGE('債券'!$BD$5:$BD$404,$A7),'債券'!$BD$5:$BD$404,0)))) | L7: =IF(ABS(LARGE('債券'!$BD$5:$BD$404,$A7))>1E8,"",IF(INDEX('債券'!$AP$5:$AP$404,MATCH(LARGE('債券'!$BD$5:$BD$404,$A7),'債券'!$BD$5:$BD$404,0))="","",INDEX('債券'!$AP$5:$AP$404,MATCH(LARGE('債券'!$BD$5:$BD$404,$A7),'債券'!$BD$5:$BD$404,0)))) | M7: =IF(ABS(LARGE('債券'!$BD$5:$BD$404,$A7))>1E8,"",IF(INDEX('債券'!$AQ$5:$AQ$404,MATCH(LARGE('債券'!$BD$5:$BD$404,$A7),'債券'!$BD$5:$BD$404,0))="","",INDEX('債券'!$AQ$5:$AQ$404,MATCH(LARGE('債券'!$BD$5:$BD$404,$A7),'債券'!$BD$5:$BD$404,0)))) | N7: =IF(ABS(LARGE('債券'!$BD$5:$BD$404,$A7))>1E8,"",IF(INDEX('債券'!$AI$5:$AI$404,MATCH(LARGE('債券'!$BD$5:$BD$404,$A7),'債券'!$BD$5:$BD$404,0))="","",INDEX('債券'!$AI$5:$AI$404,MATCH(LARGE('債券'!$BD$5:$BD$404,$A7),'債券'!$BD$5:$BD$404,0))))
A8: 3 | B8: =IF(ABS(LARGE('債券'!$BD$5:$BD$404,$A8))>1E8,"",IF(INDEX('債券'!$A$5:$A$404,MATCH(LARGE('債券'!$BD$5:$BD$404,$A8),'債券'!$BD$5:$BD$404,0))="","",INDEX('債券'!$A$5:$A$404,MATCH(LARGE('債券'!$BD$5:$BD$404,$A8),'債券'!$BD$5:$BD$404,0)))) | C8: =IF(ABS(LARGE('債券'!$BD$5:$BD$404,$A8))>1E8,"",IF(INDEX('債券'!$C$5:$C$404,MATCH(LARGE('債券'!$BD$5:$BD$404,$A8),'債券'!$BD$5:$BD$404,0))="","",INDEX('債券'!$C$5:$C$404,MATCH(LARGE('債券'!$BD$5:$BD$404,$A8),'債券'!$BD$5:$BD$404,0)))) | D8: =IF(ABS(LARGE('債券'!$BD$5:$BD$404,$A8))>1E8,"",IF(INDEX('債券'!$S$5:$S$404,MATCH(LARGE('債券'!$BD$5:$BD$404,$A8),'債券'!$BD$5:$BD$404,0))="","",INDEX('債券'!$S$5:$S$404,MATCH(LARGE('債券'!$BD$5:$BD$404,$A8),'債券'!$BD$5:$BD$404,0)))) | E8: =IF(ABS(LARGE('債券'!$BD$5:$BD$404,$A8))>1E8,"",IF(INDEX('債券'!$G$5:$G$404,MATCH(LARGE('債券'!$BD$5:$BD$404,$A8),'債券'!$BD$5:$BD$404,0))="","",INDEX('債券'!$G$5:$G$404,MATCH(LARGE('債券'!$BD$5:$BD$404,$A8),'債券'!$BD$5:$BD$404,0)))) | F8: =IF(ABS(LARGE('債券'!$BD$5:$BD$404,$A8))>1E8,"",IF(INDEX('債券'!$U$5:$U$404,MATCH(LARGE('債券'!$BD$5:$BD$404,$A8),'債券'!$BD$5:$BD$404,0))="","",INDEX('債券'!$U$5:$U$404,MATCH(LARGE('債券'!$BD$5:$BD$404,$A8),'債券'!$BD$5:$BD$404,0)))) | G8: =IF(ABS(LARGE('債券'!$BD$5:$BD$404,$A8))>1E8,"",IF(INDEX('債券'!$N$5:$N$404,MATCH(LARGE('債券'!$BD$5:$BD$404,$A8),'債券'!$BD$5:$BD$404,0))="","",INDEX('債券'!$N$5:$N$404,MATCH(LARGE('債券'!$BD$5:$BD$404,$A8),'債券'!$BD$5:$BD$404,0)))) | H8: =IF(ABS(LARGE('債券'!$BD$5:$BD$404,$A8))>1E8,"",IF(INDEX('債券'!$Z$5:$Z$404,MATCH(LARGE('債券'!$BD$5:$BD$404,$A8),'債券'!$BD$5:$BD$404,0))="","",INDEX('債券'!$Z$5:$Z$404,MATCH(LARGE('債券'!$BD$5:$BD$404,$A8),'債券'!$BD$5:$BD$404,0)))) | I8: =IF(ABS(LARGE('債券'!$BD$5:$BD$404,$A8))>1E8,"",IF(INDEX('債券'!$AF$5:$AF$404,MATCH(LARGE('債券'!$BD$5:$BD$404,$A8),'債券'!$BD$5:$BD$404,0))="","",INDEX('債券'!$AF$5:$AF$404,MATCH(LARGE('債券'!$BD$5:$BD$404,$A8),'債券'!$BD$5:$BD$404,0)))) | J8: =IF(ABS(LARGE('債券'!$BD$5:$BD$404,$A8))>1E8,"",IF(INDEX('債券'!$AM$5:$AM$404,MATCH(LARGE('債券'!$BD$5:$BD$404,$A8),'債券'!$BD$5:$BD$404,0))="","",INDEX('債券'!$AM$5:$AM$404,MATCH(LARGE('債券'!$BD$5:$BD$404,$A8),'債券'!$BD$5:$BD$404,0)))) | K8: =IF(ABS(LARGE('債券'!$BD$5:$BD$404,$A8))>1E8,"",IF(INDEX('債券'!$AO$5:$AO$404,MATCH(LARGE('債券'!$BD$5:$BD$404,$A8),'債券'!$BD$5:$BD$404,0))="","",INDEX('債券'!$AO$5:$AO$404,MATCH(LARGE('債券'!$BD$5:$BD$404,$A8),'債券'!$BD$5:$BD$404,0)))) | L8: =IF(ABS(LARGE('債券'!$BD$5:$BD$404,$A8))>1E8,"",IF(INDEX('債券'!$AP$5:$AP$404,MATCH(LARGE('債券'!$BD$5:$BD$404,$A8),'債券'!$BD$5:$BD$404,0))="","",INDEX('債券'!$AP$5:$AP$404,MATCH(LARGE('債券'!$BD$5:$BD$404,$A8),'債券'!$BD$5:$BD$404,0)))) | M8: =IF(ABS(LARGE('債券'!$BD$5:$BD$404,$A8))>1E8,"",IF(INDEX('債券'!$AQ$5:$AQ$404,MATCH(LARGE('債券'!$BD$5:$BD$404,$A8),'債券'!$BD$5:$BD$404,0))="","",INDEX('債券'!$AQ$5:$AQ$404,MATCH(LARGE('債券'!$BD$5:$BD$404,$A8),'債券'!$BD$5:$BD$404,0)))) | N8: =IF(ABS(LARGE('債券'!$BD$5:$BD$404,$A8))>1E8,"",IF(INDEX('債券'!$AI$5:$AI$404,MATCH(LARGE('債券'!$BD$5:$BD$404,$A8),'債券'!$BD$5:$BD$404,0))="","",INDEX('債券'!$AI$5:$AI$404,MATCH(LARGE('債券'!$BD$5:$BD$404,$A8),'債券'!$BD$5:$BD$404,0))))
A9: 4 | B9: =IF(ABS(LARGE('債券'!$BD$5:$BD$404,$A9))>1E8,"",IF(INDEX('債券'!$A$5:$A$404,MATCH(LARGE('債券'!$BD$5:$BD$404,$A9),'債券'!$BD$5:$BD$404,0))="","",INDEX('債券'!$A$5:$A$404,MATCH(LARGE('債券'!$BD$5:$BD$404,$A9),'債券'!$BD$5:$BD$404,0)))) | C9: =IF(ABS(LARGE('債券'!$BD$5:$BD$404,$A9))>1E8,"",IF(INDEX('債券'!$C$5:$C$404,MATCH(LARGE('債券'!$BD$5:$BD$404,$A9),'債券'!$BD$5:$BD$404,0))="","",INDEX('債券'!$C$5:$C$404,MATCH(LARGE('債券'!$BD$5:$BD$404,$A9),'債券'!$BD$5:$BD$404,0)))) | D9: =IF(ABS(LARGE('債券'!$BD$5:$BD$404,$A9))>1E8,"",IF(INDEX('債券'!$S$5:$S$404,MATCH(LARGE('債券'!$BD$5:$BD$404,$A9),'債券'!$BD$5:$BD$404,0))="","",INDEX('債券'!$S$5:$S$404,MATCH(LARGE('債券'!$BD$5:$BD$404,$A9),'債券'!$BD$5:$BD$404,0)))) | E9: =IF(ABS(LARGE('債券'!$BD$5:$BD$404,$A9))>1E8,"",IF(INDEX('債券'!$G$5:$G$404,MATCH(LARGE('債券'!$BD$5:$BD$404,$A9),'債券'!$BD$5:$BD$404,0))="","",INDEX('債券'!$G$5:$G$404,MATCH(LARGE('債券'!$BD$5:$BD$404,$A9),'債券'!$BD$5:$BD$404,0)))) | F9: =IF(ABS(LARGE('債券'!$BD$5:$BD$404,$A9))>1E8,"",IF(INDEX('債券'!$U$5:$U$404,MATCH(LARGE('債券'!$BD$5:$BD$404,$A9),'債券'!$BD$5:$BD$404,0))="","",INDEX('債券'!$U$5:$U$404,MATCH(LARGE('債券'!$BD$5:$BD$404,$A9),'債券'!$BD$5:$BD$404,0)))) | G9: =IF(ABS(LARGE('債券'!$BD$5:$BD$404,$A9))>1E8,"",IF(INDEX('債券'!$N$5:$N$404,MATCH(LARGE('債券'!$BD$5:$BD$404,$A9),'債券'!$BD$5:$BD$404,0))="","",INDEX('債券'!$N$5:$N$404,MATCH(LARGE('債券'!$BD$5:$BD$404,$A9),'債券'!$BD$5:$BD$404,0)))) | H9: =IF(ABS(LARGE('債券'!$BD$5:$BD$404,$A9))>1E8,"",IF(INDEX('債券'!$Z$5:$Z$404,MATCH(LARGE('債券'!$BD$5:$BD$404,$A9),'債券'!$BD$5:$BD$404,0))="","",INDEX('債券'!$Z$5:$Z$404,MATCH(LARGE('債券'!$BD$5:$BD$404,$A9),'債券'!$BD$5:$BD$404,0)))) | I9: =IF(ABS(LARGE('債券'!$BD$5:$BD$404,$A9))>1E8,"",IF(INDEX('債券'!$AF$5:$AF$404,MATCH(LARGE('債券'!$BD$5:$BD$404,$A9),'債券'!$BD$5:$BD$404,0))="","",INDEX('債券'!$AF$5:$AF$404,MATCH(LARGE('債券'!$BD$5:$BD$404,$A9),'債券'!$BD$5:$BD$404,0)))) | J9: =IF(ABS(LARGE('債券'!$BD$5:$BD$404,$A9))>1E8,"",IF(INDEX('債券'!$AM$5:$AM$404,MATCH(LARGE('債券'!$BD$5:$BD$404,$A9),'債券'!$BD$5:$BD$404,0))="","",INDEX('債券'!$AM$5:$AM$404,MATCH(LARGE('債券'!$BD$5:$BD$404,$A9),'債券'!$BD$5:$BD$404,0)))) | K9: =IF(ABS(LARGE('債券'!$BD$5:$BD$404,$A9))>1E8,"",IF(INDEX('債券'!$AO$5:$AO$404,MATCH(LARGE('債券'!$BD$5:$BD$404,$A9),'債券'!$BD$5:$BD$404,0))="","",INDEX('債券'!$AO$5:$AO$404,MATCH(LARGE('債券'!$BD$5:$BD$404,$A9),'債券'!$BD$5:$BD$404,0)))) | L9: =IF(ABS(LARGE('債券'!$BD$5:$BD$404,$A9))>1E8,"",IF(INDEX('債券'!$AP$5:$AP$404,MATCH(LARGE('債券'!$BD$5:$BD$404,$A9),'債券'!$BD$5:$BD$404,0))="","",INDEX('債券'!$AP$5:$AP$404,MATCH(LARGE('債券'!$BD$5:$BD$404,$A9),'債券'!$BD$5:$BD$404,0)))) | M9: =IF(ABS(LARGE('債券'!$BD$5:$BD$404,$A9))>1E8,"",IF(INDEX('債券'!$AQ$5:$AQ$404,MATCH(LARGE('債券'!$BD$5:$BD$404,$A9),'債券'!$BD$5:$BD$404,0))="","",INDEX('債券'!$AQ$5:$AQ$404,MATCH(LARGE('債券'!$BD$5:$BD$404,$A9),'債券'!$BD$5:$BD$404,0)))) | N9: =IF(ABS(LARGE('債券'!$BD$5:$BD$404,$A9))>1E8,"",IF(INDEX('債券'!$AI$5:$AI$404,MATCH(LARGE('債券'!$BD$5:$BD$404,$A9),'債券'!$BD$5:$BD$404,0))="","",INDEX('債券'!$AI$5:$AI$404,MATCH(LARGE('債券'!$BD$5:$BD$404,$A9),'債券'!$BD$5:$BD$404,0))))
A10: 5 | B10: =IF(ABS(LARGE('債券'!$BD$5:$BD$404,$A10))>1E8,"",IF(INDEX('債券'!$A$5:$A$404,MATCH(LARGE('債券'!$BD$5:$BD$404,$A10),'債券'!$BD$5:$BD$404,0))="","",INDEX('債券'!$A$5:$A$404,MATCH(LARGE('債券'!$BD$5:$BD$404,$A10),'債券'!$BD$5:$BD$404,0)))) | C10: =IF(ABS(LARGE('債券'!$BD$5:$BD$404,$A10))>1E8,"",IF(INDEX('債券'!$C$5:$C$404,MATCH(LARGE('債券'!$BD$5:$BD$404,$A10),'債券'!$BD$5:$BD$404,0))="","",INDEX('債券'!$C$5:$C$404,MATCH(LARGE('債券'!$BD$5:$BD$404,$A10),'債券'!$BD$5:$BD$404,0)))) | D10: =IF(ABS(LARGE('債券'!$BD$5:$BD$404,$A10))>1E8,"",IF(INDEX('債券'!$S$5:$S$404,MATCH(LARGE('債券'!$BD$5:$BD$404,$A10),'債券'!$BD$5:$BD$404,0))="","",INDEX('債券'!$S$5:$S$404,MATCH(LARGE('債券'!$BD$5:$BD$404,$A10),'債券'!$BD$5:$BD$404,0)))) | E10: =IF(ABS(LARGE('債券'!$BD$5:$BD$404,$A10))>1E8,"",IF(INDEX('債券'!$G$5:$G$404,MATCH(LARGE('債券'!$BD$5:$BD$404,$A10),'債券'!$BD$5:$BD$404,0))="","",INDEX('債券'!$G$5:$G$404,MATCH(LARGE('債券'!$BD$5:$BD$404,$A10),'債券'!$BD$5:$BD$404,0)))) | F10: =IF(ABS(LARGE('債券'!$BD$5:$BD$404,$A10))>1E8,"",IF(INDEX('債券'!$U$5:$U$404,MATCH(LARGE('債券'!$BD$5:$BD$404,$A10),'債券'!$BD$5:$BD$404,0))="","",INDEX('債券'!$U$5:$U$404,MATCH(LARGE('債券'!$BD$5:$BD$404,$A10),'債券'!$BD$5:$BD$404,0)))) | G10: =IF(ABS(LARGE('債券'!$BD$5:$BD$404,$A10))>1E8,"",IF(INDEX('債券'!$N$5:$N$404,MATCH(LARGE('債券'!$BD$5:$BD$404,$A10),'債券'!$BD$5:$BD$404,0))="","",INDEX('債券'!$N$5:$N$404,MATCH(LARGE('債券'!$BD$5:$BD$404,$A10),'債券'!$BD$5:$BD$404,0)))) | H10: =IF(ABS(LARGE('債券'!$BD$5:$BD$404,$A10))>1E8,"",IF(INDEX('債券'!$Z$5:$Z$404,MATCH(LARGE('債券'!$BD$5:$BD$404,$A10),'債券'!$BD$5:$BD$404,0))="","",INDEX('債券'!$Z$5:$Z$404,MATCH(LARGE('債券'!$BD$5:$BD$404,$A10),'債券'!$BD$5:$BD$404,0)))) | I10: =IF(ABS(LARGE('債券'!$BD$5:$BD$404,$A10))>1E8,"",IF(INDEX('債券'!$AF$5:$AF$404,MATCH(LARGE('債券'!$BD$5:$BD$404,$A10),'債券'!$BD$5:$BD$404,0))="","",INDEX('債券'!$AF$5:$AF$404,MATCH(LARGE('債券'!$BD$5:$BD$404,$A10),'債券'!$BD$5:$BD$404,0)))) | J10: =IF(ABS(LARGE('債券'!$BD$5:$BD$404,$A10))>1E8,"",IF(INDEX('債券'!$AM$5:$AM$404,MATCH(LARGE('債券'!$BD$5:$BD$404,$A10),'債券'!$BD$5:$BD$404,0))="","",INDEX('債券'!$AM$5:$AM$404,MATCH(LARGE('債券'!$BD$5:$BD$404,$A10),'債券'!$BD$5:$BD$404,0)))) | K10: =IF(ABS(LARGE('債券'!$BD$5:$BD$404,$A10))>1E8,"",IF(INDEX('債券'!$AO$5:$AO$404,MATCH(LARGE('債券'!$BD$5:$BD$404,$A10),'債券'!$BD$5:$BD$404,0))="","",INDEX('債券'!$AO$5:$AO$404,MATCH(LARGE('債券'!$BD$5:$BD$404,$A10),'債券'!$BD$5:$BD$404,0)))) | L10: =IF(ABS(LARGE('債券'!$BD$5:$BD$404,$A10))>1E8,"",IF(INDEX('債券'!$AP$5:$AP$404,MATCH(LARGE('債券'!$BD$5:$BD$404,$A10),'債券'!$BD$5:$BD$404,0))="","",INDEX('債券'!$AP$5:$AP$404,MATCH(LARGE('債券'!$BD$5:$BD$404,$A10),'債券'!$BD$5:$BD$404,0)))) | M10: =IF(ABS(LARGE('債券'!$BD$5:$BD$404,$A10))>1E8,"",IF(INDEX('債券'!$AQ$5:$AQ$404,MATCH(LARGE('債券'!$BD$5:$BD$404,$A10),'債券'!$BD$5:$BD$404,0))="","",INDEX('債券'!$AQ$5:$AQ$404,MATCH(LARGE('債券'!$BD$5:$BD$404,$A10),'債券'!$BD$5:$BD$404,0)))) | N10: =IF(ABS(LARGE('債券'!$BD$5:$BD$404,$A10))>1E8,"",IF(INDEX('債券'!$AI$5:$AI$404,MATCH(LARGE('債券'!$BD$5:$BD$404,$A10),'債券'!$BD$5:$BD$404,0))="","",INDEX('債券'!$AI$5:$AI$404,MATCH(LARGE('債券'!$BD$5:$BD$404,$A10),'債券'!$BD$5:$BD$404,0))))
A11: 6 | B11: =IF(ABS(LARGE('債券'!$BD$5:$BD$404,$A11))>1E8,"",IF(INDEX('債券'!$A$5:$A$404,MATCH(LARGE('債券'!$BD$5:$BD$404,$A11),'債券'!$BD$5:$BD$404,0))="","",INDEX('債券'!$A$5:$A$404,MATCH(LARGE('債券'!$BD$5:$BD$404,$A11),'債券'!$BD$5:$BD$404,0)))) | C11: =IF(ABS(LARGE('債券'!$BD$5:$BD$404,$A11))>1E8,"",IF(INDEX('債券'!$C$5:$C$404,MATCH(LARGE('債券'!$BD$5:$BD$404,$A11),'債券'!$BD$5:$BD$404,0))="","",INDEX('債券'!$C$5:$C$404,MATCH(LARGE('債券'!$BD$5:$BD$404,$A11),'債券'!$BD$5:$BD$404,0)))) | D11: =IF(ABS(LARGE('債券'!$BD$5:$BD$404,$A11))>1E8,"",IF(INDEX('債券'!$S$5:$S$404,MATCH(LARGE('債券'!$BD$5:$BD$404,$A11),'債券'!$BD$5:$BD$404,0))="","",INDEX('債券'!$S$5:$S$404,MATCH(LARGE('債券'!$BD$5:$BD$404,$A11),'債券'!$BD$5:$BD$404,0)))) | E11: =IF(ABS(LARGE('債券'!$BD$5:$BD$404,$A11))>1E8,"",IF(INDEX('債券'!$G$5:$G$404,MATCH(LARGE('債券'!$BD$5:$BD$404,$A11),'債券'!$BD$5:$BD$404,0))="","",INDEX('債券'!$G$5:$G$404,MATCH(LARGE('債券'!$BD$5:$BD$404,$A11),'債券'!$BD$5:$BD$404,0)))) | F11: =IF(ABS(LARGE('債券'!$BD$5:$BD$404,$A11))>1E8,"",IF(INDEX('債券'!$U$5:$U$404,MATCH(LARGE('債券'!$BD$5:$BD$404,$A11),'債券'!$BD$5:$BD$404,0))="","",INDEX('債券'!$U$5:$U$404,MATCH(LARGE('債券'!$BD$5:$BD$404,$A11),'債券'!$BD$5:$BD$404,0)))) | G11: =IF(ABS(LARGE('債券'!$BD$5:$BD$404,$A11))>1E8,"",IF(INDEX('債券'!$N$5:$N$404,MATCH(LARGE('債券'!$BD$5:$BD$404,$A11),'債券'!$BD$5:$BD$404,0))="","",INDEX('債券'!$N$5:$N$404,MATCH(LARGE('債券'!$BD$5:$BD$404,$A11),'債券'!$BD$5:$BD$404,0)))) | H11: =IF(ABS(LARGE('債券'!$BD$5:$BD$404,$A11))>1E8,"",IF(INDEX('債券'!$Z$5:$Z$404,MATCH(LARGE('債券'!$BD$5:$BD$404,$A11),'債券'!$BD$5:$BD$404,0))="","",INDEX('債券'!$Z$5:$Z$404,MATCH(LARGE('債券'!$BD$5:$BD$404,$A11),'債券'!$BD$5:$BD$404,0)))) | I11: =IF(ABS(LARGE('債券'!$BD$5:$BD$404,$A11))>1E8,"",IF(INDEX('債券'!$AF$5:$AF$404,MATCH(LARGE('債券'!$BD$5:$BD$404,$A11),'債券'!$BD$5:$BD$404,0))="","",INDEX('債券'!$AF$5:$AF$404,MATCH(LARGE('債券'!$BD$5:$BD$404,$A11),'債券'!$BD$5:$BD$404,0)))) | J11: =IF(ABS(LARGE('債券'!$BD$5:$BD$404,$A11))>1E8,"",IF(INDEX('債券'!$AM$5:$AM$404,MATCH(LARGE('債券'!$BD$5:$BD$404,$A11),'債券'!$BD$5:$BD$404,0))="","",INDEX('債券'!$AM$5:$AM$404,MATCH(LARGE('債券'!$BD$5:$BD$404,$A11),'債券'!$BD$5:$BD$404,0)))) | K11: =IF(ABS(LARGE('債券'!$BD$5:$BD$404,$A11))>1E8,"",IF(INDEX('債券'!$AO$5:$AO$404,MATCH(LARGE('債券'!$BD$5:$BD$404,$A11),'債券'!$BD$5:$BD$404,0))="","",INDEX('債券'!$AO$5:$AO$404,MATCH(LARGE('債券'!$BD$5:$BD$404,$A11),'債券'!$BD$5:$BD$404,0)))) | L11: =IF(ABS(LARGE('債券'!$BD$5:$BD$404,$A11))>1E8,"",IF(INDEX('債券'!$AP$5:$AP$404,MATCH(LARGE('債券'!$BD$5:$BD$404,$A11),'債券'!$BD$5:$BD$404,0))="","",INDEX('債券'!$AP$5:$AP$404,MATCH(LARGE('債券'!$BD$5:$BD$404,$A11),'債券'!$BD$5:$BD$404,0)))) | M11: =IF(ABS(LARGE('債券'!$BD$5:$BD$404,$A11))>1E8,"",IF(INDEX('債券'!$AQ$5:$AQ$404,MATCH(LARGE('債券'!$BD$5:$BD$404,$A11),'債券'!$BD$5:$BD$404,0))="","",INDEX('債券'!$AQ$5:$AQ$404,MATCH(LARGE('債券'!$BD$5:$BD$404,$A11),'債券'!$BD$5:$BD$404,0)))) | N11: =IF(ABS(LARGE('債券'!$BD$5:$BD$404,$A11))>1E8,"",IF(INDEX('債券'!$AI$5:$AI$404,MATCH(LARGE('債券'!$BD$5:$BD$404,$A11),'債券'!$BD$5:$BD$404,0))="","",INDEX('債券'!$AI$5:$AI$404,MATCH(LARGE('債券'!$BD$5:$BD$404,$A11),'債券'!$BD$5:$BD$404,0))))
A12: 7 | B12: =IF(ABS(LARGE('債券'!$BD$5:$BD$404,$A12))>1E8,"",IF(INDEX('債券'!$A$5:$A$404,MATCH(LARGE('債券'!$BD$5:$BD$404,$A12),'債券'!$BD$5:$BD$404,0))="","",INDEX('債券'!$A$5:$A$404,MATCH(LARGE('債券'!$BD$5:$BD$404,$A12),'債券'!$BD$5:$BD$404,0)))) | C12: =IF(ABS(LARGE('債券'!$BD$5:$BD$404,$A12))>1E8,"",IF(INDEX('債券'!$C$5:$C$404,MATCH(LARGE('債券'!$BD$5:$BD$404,$A12),'債券'!$BD$5:$BD$404,0))="","",INDEX('債券'!$C$5:$C$404,MATCH(LARGE('債券'!$BD$5:$BD$404,$A12),'債券'!$BD$5:$BD$404,0)))) | D12: =IF(ABS(LARGE('債券'!$BD$5:$BD$404,$A12))>1E8,"",IF(INDEX('債券'!$S$5:$S$404,MATCH(LARGE('債券'!$BD$5:$BD$404,$A12),'債券'!$BD$5:$BD$404,0))="","",INDEX('債券'!$S$5:$S$404,MATCH(LARGE('債券'!$BD$5:$BD$404,$A12),'債券'!$BD$5:$BD$404,0)))) | E12: =IF(ABS(LARGE('債券'!$BD$5:$BD$404,$A12))>1E8,"",IF(INDEX('債券'!$G$5:$G$404,MATCH(LARGE('債券'!$BD$5:$BD$404,$A12),'債券'!$BD$5:$BD$404,0))="","",INDEX('債券'!$G$5:$G$404,MATCH(LARGE('債券'!$BD$5:$BD$404,$A12),'債券'!$BD$5:$BD$404,0)))) | F12: =IF(ABS(LARGE('債券'!$BD$5:$BD$404,$A12))>1E8,"",IF(INDEX('債券'!$U$5:$U$404,MATCH(LARGE('債券'!$BD$5:$BD$404,$A12),'債券'!$BD$5:$BD$404,0))="","",INDEX('債券'!$U$5:$U$404,MATCH(LARGE('債券'!$BD$5:$BD$404,$A12),'債券'!$BD$5:$BD$404,0)))) | G12: =IF(ABS(LARGE('債券'!$BD$5:$BD$404,$A12))>1E8,"",IF(INDEX('債券'!$N$5:$N$404,MATCH(LARGE('債券'!$BD$5:$BD$404,$A12),'債券'!$BD$5:$BD$404,0))="","",INDEX('債券'!$N$5:$N$404,MATCH(LARGE('債券'!$BD$5:$BD$404,$A12),'債券'!$BD$5:$BD$404,0)))) | H12: =IF(ABS(LARGE('債券'!$BD$5:$BD$404,$A12))>1E8,"",IF(INDEX('債券'!$Z$5:$Z$404,MATCH(LARGE('債券'!$BD$5:$BD$404,$A12),'債券'!$BD$5:$BD$404,0))="","",INDEX('債券'!$Z$5:$Z$404,MATCH(LARGE('債券'!$BD$5:$BD$404,$A12),'債券'!$BD$5:$BD$404,0)))) | I12: =IF(ABS(LARGE('債券'!$BD$5:$BD$404,$A12))>1E8,"",IF(INDEX('債券'!$AF$5:$AF$404,MATCH(LARGE('債券'!$BD$5:$BD$404,$A12),'債券'!$BD$5:$BD$404,0))="","",INDEX('債券'!$AF$5:$AF$404,MATCH(LARGE('債券'!$BD$5:$BD$404,$A12),'債券'!$BD$5:$BD$404,0)))) | J12: =IF(ABS(LARGE('債券'!$BD$5:$BD$404,$A12))>1E8,"",IF(INDEX('債券'!$AM$5:$AM$404,MATCH(LARGE('債券'!$BD$5:$BD$404,$A12),'債券'!$BD$5:$BD$404,0))="","",INDEX('債券'!$AM$5:$AM$404,MATCH(LARGE('債券'!$BD$5:$BD$404,$A12),'債券'!$BD$5:$BD$404,0)))) | K12: =IF(ABS(LARGE('債券'!$BD$5:$BD$404,$A12))>1E8,"",IF(INDEX('債券'!$AO$5:$AO$404,MATCH(LARGE('債券'!$BD$5:$BD$404,$A12),'債券'!$BD$5:$BD$404,0))="","",INDEX('債券'!$AO$5:$AO$404,MATCH(LARGE('債券'!$BD$5:$BD$404,$A12),'債券'!$BD$5:$BD$404,0)))) | L12: =IF(ABS(LARGE('債券'!$BD$5:$BD$404,$A12))>1E8,"",IF(INDEX('債券'!$AP$5:$AP$404,MATCH(LARGE('債券'!$BD$5:$BD$404,$A12),'債券'!$BD$5:$BD$404,0))="","",INDEX('債券'!$AP$5:$AP$404,MATCH(LARGE('債券'!$BD$5:$BD$404,$A12),'債券'!$BD$5:$BD$404,0)))) | M12: =IF(ABS(LARGE('債券'!$BD$5:$BD$404,$A12))>1E8,"",IF(INDEX('債券'!$AQ$5:$AQ$404,MATCH(LARGE('債券'!$BD$5:$BD$404,$A12),'債券'!$BD$5:$BD$404,0))="","",INDEX('債券'!$AQ$5:$AQ$404,MATCH(LARGE('債券'!$BD$5:$BD$404,$A12),'債券'!$BD$5:$BD$404,0)))) | N12: =IF(ABS(LARGE('債券'!$BD$5:$BD$404,$A12))>1E8,"",IF(INDEX('債券'!$AI$5:$AI$404,MATCH(LARGE('債券'!$BD$5:$BD$404,$A12),'債券'!$BD$5:$BD$404,0))="","",INDEX('債券'!$AI$5:$AI$404,MATCH(LARGE('債券'!$BD$5:$BD$404,$A12),'債券'!$BD$5:$BD$404,0))))
A13: 8 | B13: =IF(ABS(LARGE('債券'!$BD$5:$BD$404,$A13))>1E8,"",IF(INDEX('債券'!$A$5:$A$404,MATCH(LARGE('債券'!$BD$5:$BD$404,$A13),'債券'!$BD$5:$BD$404,0))="","",INDEX('債券'!$A$5:$A$404,MATCH(LARGE('債券'!$BD$5:$BD$404,$A13),'債券'!$BD$5:$BD$404,0)))) | C13: =IF(ABS(LARGE('債券'!$BD$5:$BD$404,$A13))>1E8,"",IF(INDEX('債券'!$C$5:$C$404,MATCH(LARGE('債券'!$BD$5:$BD$404,$A13),'債券'!$BD$5:$BD$404,0))="","",INDEX('債券'!$C$5:$C$404,MATCH(LARGE('債券'!$BD$5:$BD$404,$A13),'債券'!$BD$5:$BD$404,0)))) | D13: =IF(ABS(LARGE('債券'!$BD$5:$BD$404,$A13))>1E8,"",IF(INDEX('債券'!$S$5:$S$404,MATCH(LARGE('債券'!$BD$5:$BD$404,$A13),'債券'!$BD$5:$BD$404,0))="","",INDEX('債券'!$S$5:$S$404,MATCH(LARGE('債券'!$BD$5:$BD$404,$A13),'債券'!$BD$5:$BD$404,0)))) | E13: =IF(ABS(LARGE('債券'!$BD$5:$BD$404,$A13))>1E8,"",IF(INDEX('債券'!$G$5:$G$404,MATCH(LARGE('債券'!$BD$5:$BD$404,$A13),'債券'!$BD$5:$BD$404,0))="","",INDEX('債券'!$G$5:$G$404,MATCH(LARGE('債券'!$BD$5:$BD$404,$A13),'債券'!$BD$5:$BD$404,0)))) | F13: =IF(ABS(LARGE('債券'!$BD$5:$BD$404,$A13))>1E8,"",IF(INDEX('債券'!$U$5:$U$404,MATCH(LARGE('債券'!$BD$5:$BD$404,$A13),'債券'!$BD$5:$BD$404,0))="","",INDEX('債券'!$U$5:$U$404,MATCH(LARGE('債券'!$BD$5:$BD$404,$A13),'債券'!$BD$5:$BD$404,0)))) | G13: =IF(ABS(LARGE('債券'!$BD$5:$BD$404,$A13))>1E8,"",IF(INDEX('債券'!$N$5:$N$404,MATCH(LARGE('債券'!$BD$5:$BD$404,$A13),'債券'!$BD$5:$BD$404,0))="","",INDEX('債券'!$N$5:$N$404,MATCH(LARGE('債券'!$BD$5:$BD$404,$A13),'債券'!$BD$5:$BD$404,0)))) | H13: =IF(ABS(LARGE('債券'!$BD$5:$BD$404,$A13))>1E8,"",IF(INDEX('債券'!$Z$5:$Z$404,MATCH(LARGE('債券'!$BD$5:$BD$404,$A13),'債券'!$BD$5:$BD$404,0))="","",INDEX('債券'!$Z$5:$Z$404,MATCH(LARGE('債券'!$BD$5:$BD$404,$A13),'債券'!$BD$5:$BD$404,0)))) | I13: =IF(ABS(LARGE('債券'!$BD$5:$BD$404,$A13))>1E8,"",IF(INDEX('債券'!$AF$5:$AF$404,MATCH(LARGE('債券'!$BD$5:$BD$404,$A13),'債券'!$BD$5:$BD$404,0))="","",INDEX('債券'!$AF$5:$AF$404,MATCH(LARGE('債券'!$BD$5:$BD$404,$A13),'債券'!$BD$5:$BD$404,0)))) | J13: =IF(ABS(LARGE('債券'!$BD$5:$BD$404,$A13))>1E8,"",IF(INDEX('債券'!$AM$5:$AM$404,MATCH(LARGE('債券'!$BD$5:$BD$404,$A13),'債券'!$BD$5:$BD$404,0))="","",INDEX('債券'!$AM$5:$AM$404,MATCH(LARGE('債券'!$BD$5:$BD$404,$A13),'債券'!$BD$5:$BD$404,0)))) | K13: =IF(ABS(LARGE('債券'!$BD$5:$BD$404,$A13))>1E8,"",IF(INDEX('債券'!$AO$5:$AO$404,MATCH(LARGE('債券'!$BD$5:$BD$404,$A13),'債券'!$BD$5:$BD$404,0))="","",INDEX('債券'!$AO$5:$AO$404,MATCH(LARGE('債券'!$BD$5:$BD$404,$A13),'債券'!$BD$5:$BD$404,0)))) | L13: =IF(ABS(LARGE('債券'!$BD$5:$BD$404,$A13))>1E8,"",IF(INDEX('債券'!$AP$5:$AP$404,MATCH(LARGE('債券'!$BD$5:$BD$404,$A13),'債券'!$BD$5:$BD$404,0))="","",INDEX('債券'!$AP$5:$AP$404,MATCH(LARGE('債券'!$BD$5:$BD$404,$A13),'債券'!$BD$5:$BD$404,0)))) | M13: =IF(ABS(LARGE('債券'!$BD$5:$BD$404,$A13))>1E8,"",IF(INDEX('債券'!$AQ$5:$AQ$404,MATCH(LARGE('債券'!$BD$5:$BD$404,$A13),'債券'!$BD$5:$BD$404,0))="","",INDEX('債券'!$AQ$5:$AQ$404,MATCH(LARGE('債券'!$BD$5:$BD$404,$A13),'債券'!$BD$5:$BD$404,0)))) | N13: =IF(ABS(LARGE('債券'!$BD$5:$BD$404,$A13))>1E8,"",IF(INDEX('債券'!$AI$5:$AI$404,MATCH(LARGE('債券'!$BD$5:$BD$404,$A13),'債券'!$BD$5:$BD$404,0))="","",INDEX('債券'!$AI$5:$AI$404,MATCH(LARGE('債券'!$BD$5:$BD$404,$A13),'債券'!$BD$5:$BD$404,0))))
A14: 9 | B14: =IF(ABS(LARGE('債券'!$BD$5:$BD$404,$A14))>1E8,"",IF(INDEX('債券'!$A$5:$A$404,MATCH(LARGE('債券'!$BD$5:$BD$404,$A14),'債券'!$BD$5:$BD$404,0))="","",INDEX('債券'!$A$5:$A$404,MATCH(LARGE('債券'!$BD$5:$BD$404,$A14),'債券'!$BD$5:$BD$404,0)))) | C14: =IF(ABS(LARGE('債券'!$BD$5:$BD$404,$A14))>1E8,"",IF(INDEX('債券'!$C$5:$C$404,MATCH(LARGE('債券'!$BD$5:$BD$404,$A14),'債券'!$BD$5:$BD$404,0))="","",INDEX('債券'!$C$5:$C$404,MATCH(LARGE('債券'!$BD$5:$BD$404,$A14),'債券'!$BD$5:$BD$404,0)))) | D14: =IF(ABS(LARGE('債券'!$BD$5:$BD$404,$A14))>1E8,"",IF(INDEX('債券'!$S$5:$S$404,MATCH(LARGE('債券'!$BD$5:$BD$404,$A14),'債券'!$BD$5:$BD$404,0))="","",INDEX('債券'!$S$5:$S$404,MATCH(LARGE('債券'!$BD$5:$BD$404,$A14),'債券'!$BD$5:$BD$404,0)))) | E14: =IF(ABS(LARGE('債券'!$BD$5:$BD$404,$A14))>1E8,"",IF(INDEX('債券'!$G$5:$G$404,MATCH(LARGE('債券'!$BD$5:$BD$404,$A14),'債券'!$BD$5:$BD$404,0))="","",INDEX('債券'!$G$5:$G$404,MATCH(LARGE('債券'!$BD$5:$BD$404,$A14),'債券'!$BD$5:$BD$404,0)))) | F14: =IF(ABS(LARGE('債券'!$BD$5:$BD$404,$A14))>1E8,"",IF(INDEX('債券'!$U$5:$U$404,MATCH(LARGE('債券'!$BD$5:$BD$404,$A14),'債券'!$BD$5:$BD$404,0))="","",INDEX('債券'!$U$5:$U$404,MATCH(LARGE('債券'!$BD$5:$BD$404,$A14),'債券'!$BD$5:$BD$404,0)))) | G14: =IF(ABS(LARGE('債券'!$BD$5:$BD$404,$A14))>1E8,"",IF(INDEX('債券'!$N$5:$N$404,MATCH(LARGE('債券'!$BD$5:$BD$404,$A14),'債券'!$BD$5:$BD$404,0))="","",INDEX('債券'!$N$5:$N$404,MATCH(LARGE('債券'!$BD$5:$BD$404,$A14),'債券'!$BD$5:$BD$404,0)))) | H14: =IF(ABS(LARGE('債券'!$BD$5:$BD$404,$A14))>1E8,"",IF(INDEX('債券'!$Z$5:$Z$404,MATCH(LARGE('債券'!$BD$5:$BD$404,$A14),'債券'!$BD$5:$BD$404,0))="","",INDEX('債券'!$Z$5:$Z$404,MATCH(LARGE('債券'!$BD$5:$BD$404,$A14),'債券'!$BD$5:$BD$404,0)))) | I14: =IF(ABS(LARGE('債券'!$BD$5:$BD$404,$A14))>1E8,"",IF(INDEX('債券'!$AF$5:$AF$404,MATCH(LARGE('債券'!$BD$5:$BD$404,$A14),'債券'!$BD$5:$BD$404,0))="","",INDEX('債券'!$AF$5:$AF$404,MATCH(LARGE('債券'!$BD$5:$BD$404,$A14),'債券'!$BD$5:$BD$404,0)))) | J14: =IF(ABS(LARGE('債券'!$BD$5:$BD$404,$A14))>1E8,"",IF(INDEX('債券'!$AM$5:$AM$404,MATCH(LARGE('債券'!$BD$5:$BD$404,$A14),'債券'!$BD$5:$BD$404,0))="","",INDEX('債券'!$AM$5:$AM$404,MATCH(LARGE('債券'!$BD$5:$BD$404,$A14),'債券'!$BD$5:$BD$404,0)))) | K14: =IF(ABS(LARGE('債券'!$BD$5:$BD$404,$A14))>1E8,"",IF(INDEX('債券'!$AO$5:$AO$404,MATCH(LARGE('債券'!$BD$5:$BD$404,$A14),'債券'!$BD$5:$BD$404,0))="","",INDEX('債券'!$AO$5:$AO$404,MATCH(LARGE('債券'!$BD$5:$BD$404,$A14),'債券'!$BD$5:$BD$404,0)))) | L14: =IF(ABS(LARGE('債券'!$BD$5:$BD$404,$A14))>1E8,"",IF(INDEX('債券'!$AP$5:$AP$404,MATCH(LARGE('債券'!$BD$5:$BD$404,$A14),'債券'!$BD$5:$BD$404,0))="","",INDEX('債券'!$AP$5:$AP$404,MATCH(LARGE('債券'!$BD$5:$BD$404,$A14),'債券'!$BD$5:$BD$404,0)))) | M14: =IF(ABS(LARGE('債券'!$BD$5:$BD$404,$A14))>1E8,"",IF(INDEX('債券'!$AQ$5:$AQ$404,MATCH(LARGE('債券'!$BD$5:$BD$404,$A14),'債券'!$BD$5:$BD$404,0))="","",INDEX('債券'!$AQ$5:$AQ$404,MATCH(LARGE('債券'!$BD$5:$BD$404,$A14),'債券'!$BD$5:$BD$404,0)))) | N14: =IF(ABS(LARGE('債券'!$BD$5:$BD$404,$A14))>1E8,"",IF(INDEX('債券'!$AI$5:$AI$404,MATCH(LARGE('債券'!$BD$5:$BD$404,$A14),'債券'!$BD$5:$BD$404,0))="","",INDEX('債券'!$AI$5:$AI$404,MATCH(LARGE('債券'!$BD$5:$BD$404,$A14),'債券'!$BD$5:$BD$404,0))))
A15: 10 | B15: =IF(ABS(LARGE('債券'!$BD$5:$BD$404,$A15))>1E8,"",IF(INDEX('債券'!$A$5:$A$404,MATCH(LARGE('債券'!$BD$5:$BD$404,$A15),'債券'!$BD$5:$BD$404,0))="","",INDEX('債券'!$A$5:$A$404,MATCH(LARGE('債券'!$BD$5:$BD$404,$A15),'債券'!$BD$5:$BD$404,0)))) | C15: =IF(ABS(LARGE('債券'!$BD$5:$BD$404,$A15))>1E8,"",IF(INDEX('債券'!$C$5:$C$404,MATCH(LARGE('債券'!$BD$5:$BD$404,$A15),'債券'!$BD$5:$BD$404,0))="","",INDEX('債券'!$C$5:$C$404,MATCH(LARGE('債券'!$BD$5:$BD$404,$A15),'債券'!$BD$5:$BD$404,0)))) | D15: =IF(ABS(LARGE('債券'!$BD$5:$BD$404,$A15))>1E8,"",IF(INDEX('債券'!$S$5:$S$404,MATCH(LARGE('債券'!$BD$5:$BD$404,$A15),'債券'!$BD$5:$BD$404,0))="","",INDEX('債券'!$S$5:$S$404,MATCH(LARGE('債券'!$BD$5:$BD$404,$A15),'債券'!$BD$5:$BD$404,0)))) | E15: =IF(ABS(LARGE('債券'!$BD$5:$BD$404,$A15))>1E8,"",IF(INDEX('債券'!$G$5:$G$404,MATCH(LARGE('債券'!$BD$5:$BD$404,$A15),'債券'!$BD$5:$BD$404,0))="","",INDEX('債券'!$G$5:$G$404,MATCH(LARGE('債券'!$BD$5:$BD$404,$A15),'債券'!$BD$5:$BD$404,0)))) | F15: =IF(ABS(LARGE('債券'!$BD$5:$BD$404,$A15))>1E8,"",IF(INDEX('債券'!$U$5:$U$404,MATCH(LARGE('債券'!$BD$5:$BD$404,$A15),'債券'!$BD$5:$BD$404,0))="","",INDEX('債券'!$U$5:$U$404,MATCH(LARGE('債券'!$BD$5:$BD$404,$A15),'債券'!$BD$5:$BD$404,0)))) | G15: =IF(ABS(LARGE('債券'!$BD$5:$BD$404,$A15))>1E8,"",IF(INDEX('債券'!$N$5:$N$404,MATCH(LARGE('債券'!$BD$5:$BD$404,$A15),'債券'!$BD$5:$BD$404,0))="","",INDEX('債券'!$N$5:$N$404,MATCH(LARGE('債券'!$BD$5:$BD$404,$A15),'債券'!$BD$5:$BD$404,0)))) | H15: =IF(ABS(LARGE('債券'!$BD$5:$BD$404,$A15))>1E8,"",IF(INDEX('債券'!$Z$5:$Z$404,MATCH(LARGE('債券'!$BD$5:$BD$404,$A15),'債券'!$BD$5:$BD$404,0))="","",INDEX('債券'!$Z$5:$Z$404,MATCH(LARGE('債券'!$BD$5:$BD$404,$A15),'債券'!$BD$5:$BD$404,0)))) | I15: =IF(ABS(LARGE('債券'!$BD$5:$BD$404,$A15))>1E8,"",IF(INDEX('債券'!$AF$5:$AF$404,MATCH(LARGE('債券'!$BD$5:$BD$404,$A15),'債券'!$BD$5:$BD$404,0))="","",INDEX('債券'!$AF$5:$AF$404,MATCH(LARGE('債券'!$BD$5:$BD$404,$A15),'債券'!$BD$5:$BD$404,0)))) | J15: =IF(ABS(LARGE('債券'!$BD$5:$BD$404,$A15))>1E8,"",IF(INDEX('債券'!$AM$5:$AM$404,MATCH(LARGE('債券'!$BD$5:$BD$404,$A15),'債券'!$BD$5:$BD$404,0))="","",INDEX('債券'!$AM$5:$AM$404,MATCH(LARGE('債券'!$BD$5:$BD$404,$A15),'債券'!$BD$5:$BD$404,0)))) | K15: =IF(ABS(LARGE('債券'!$BD$5:$BD$404,$A15))>1E8,"",IF(INDEX('債券'!$AO$5:$AO$404,MATCH(LARGE('債券'!$BD$5:$BD$404,$A15),'債券'!$BD$5:$BD$404,0))="","",INDEX('債券'!$AO$5:$AO$404,MATCH(LARGE('債券'!$BD$5:$BD$404,$A15),'債券'!$BD$5:$BD$404,0)))) | L15: =IF(ABS(LARGE('債券'!$BD$5:$BD$404,$A15))>1E8,"",IF(INDEX('債券'!$AP$5:$AP$404,MATCH(LARGE('債券'!$BD$5:$BD$404,$A15),'債券'!$BD$5:$BD$404,0))="","",INDEX('債券'!$AP$5:$AP$404,MATCH(LARGE('債券'!$BD$5:$BD$404,$A15),'債券'!$BD$5:$BD$404,0)))) | M15: =IF(ABS(LARGE('債券'!$BD$5:$BD$404,$A15))>1E8,"",IF(INDEX('債券'!$AQ$5:$AQ$404,MATCH(LARGE('債券'!$BD$5:$BD$404,$A15),'債券'!$BD$5:$BD$404,0))="","",INDEX('債券'!$AQ$5:$AQ$404,MATCH(LARGE('債券'!$BD$5:$BD$404,$A15),'債券'!$BD$5:$BD$404,0)))) | N15: =IF(ABS(LARGE('債券'!$BD$5:$BD$404,$A15))>1E8,"",IF(INDEX('債券'!$AI$5:$AI$404,MATCH(LARGE('債券'!$BD$5:$BD$404,$A15),'債券'!$BD$5:$BD$404,0))="","",INDEX('債券'!$AI$5:$AI$404,MATCH(LARGE('債券'!$BD$5:$BD$404,$A15),'債券'!$BD$5:$BD$404,0))))
A16: 11 | B16: =IF(ABS(LARGE('債券'!$BD$5:$BD$404,$A16))>1E8,"",IF(INDEX('債券'!$A$5:$A$404,MATCH(LARGE('債券'!$BD$5:$BD$404,$A16),'債券'!$BD$5:$BD$404,0))="","",INDEX('債券'!$A$5:$A$404,MATCH(LARGE('債券'!$BD$5:$BD$404,$A16),'債券'!$BD$5:$BD$404,0)))) | C16: =IF(ABS(LARGE('債券'!$BD$5:$BD$404,$A16))>1E8,"",IF(INDEX('債券'!$C$5:$C$404,MATCH(LARGE('債券'!$BD$5:$BD$404,$A16),'債券'!$BD$5:$BD$404,0))="","",INDEX('債券'!$C$5:$C$404,MATCH(LARGE('債券'!$BD$5:$BD$404,$A16),'債券'!$BD$5:$BD$404,0)))) | D16: =IF(ABS(LARGE('債券'!$BD$5:$BD$404,$A16))>1E8,"",IF(INDEX('債券'!$S$5:$S$404,MATCH(LARGE('債券'!$BD$5:$BD$404,$A16),'債券'!$BD$5:$BD$404,0))="","",INDEX('債券'!$S$5:$S$404,MATCH(LARGE('債券'!$BD$5:$BD$404,$A16),'債券'!$BD$5:$BD$404,0)))) | E16: =IF(ABS(LARGE('債券'!$BD$5:$BD$404,$A16))>1E8,"",IF(INDEX('債券'!$G$5:$G$404,MATCH(LARGE('債券'!$BD$5:$BD$404,$A16),'債券'!$BD$5:$BD$404,0))="","",INDEX('債券'!$G$5:$G$404,MATCH(LARGE('債券'!$BD$5:$BD$404,$A16),'債券'!$BD$5:$BD$404,0)))) | F16: =IF(ABS(LARGE('債券'!$BD$5:$BD$404,$A16))>1E8,"",IF(INDEX('債券'!$U$5:$U$404,MATCH(LARGE('債券'!$BD$5:$BD$404,$A16),'債券'!$BD$5:$BD$404,0))="","",INDEX('債券'!$U$5:$U$404,MATCH(LARGE('債券'!$BD$5:$BD$404,$A16),'債券'!$BD$5:$BD$404,0)))) | G16: =IF(ABS(LARGE('債券'!$BD$5:$BD$404,$A16))>1E8,"",IF(INDEX('債券'!$N$5:$N$404,MATCH(LARGE('債券'!$BD$5:$BD$404,$A16),'債券'!$BD$5:$BD$404,0))="","",INDEX('債券'!$N$5:$N$404,MATCH(LARGE('債券'!$BD$5:$BD$404,$A16),'債券'!$BD$5:$BD$404,0)))) | H16: =IF(ABS(LARGE('債券'!$BD$5:$BD$404,$A16))>1E8,"",IF(INDEX('債券'!$Z$5:$Z$404,MATCH(LARGE('債券'!$BD$5:$BD$404,$A16),'債券'!$BD$5:$BD$404,0))="","",INDEX('債券'!$Z$5:$Z$404,MATCH(LARGE('債券'!$BD$5:$BD$404,$A16),'債券'!$BD$5:$BD$404,0)))) | I16: =IF(ABS(LARGE('債券'!$BD$5:$BD$404,$A16))>1E8,"",IF(INDEX('債券'!$AF$5:$AF$404,MATCH(LARGE('債券'!$BD$5:$BD$404,$A16),'債券'!$BD$5:$BD$404,0))="","",INDEX('債券'!$AF$5:$AF$404,MATCH(LARGE('債券'!$BD$5:$BD$404,$A16),'債券'!$BD$5:$BD$404,0)))) | J16: =IF(ABS(LARGE('債券'!$BD$5:$BD$404,$A16))>1E8,"",IF(INDEX('債券'!$AM$5:$AM$404,MATCH(LARGE('債券'!$BD$5:$BD$404,$A16),'債券'!$BD$5:$BD$404,0))="","",INDEX('債券'!$AM$5:$AM$404,MATCH(LARGE('債券'!$BD$5:$BD$404,$A16),'債券'!$BD$5:$BD$404,0)))) | K16: =IF(ABS(LARGE('債券'!$BD$5:$BD$404,$A16))>1E8,"",IF(INDEX('債券'!$AO$5:$AO$404,MATCH(LARGE('債券'!$BD$5:$BD$404,$A16),'債券'!$BD$5:$BD$404,0))="","",INDEX('債券'!$AO$5:$AO$404,MATCH(LARGE('債券'!$BD$5:$BD$404,$A16),'債券'!$BD$5:$BD$404,0)))) | L16: =IF(ABS(LARGE('債券'!$BD$5:$BD$404,$A16))>1E8,"",IF(INDEX('債券'!$AP$5:$AP$404,MATCH(LARGE('債券'!$BD$5:$BD$404,$A16),'債券'!$BD$5:$BD$404,0))="","",INDEX('債券'!$AP$5:$AP$404,MATCH(LARGE('債券'!$BD$5:$BD$404,$A16),'債券'!$BD$5:$BD$404,0)))) | M16: =IF(ABS(LARGE('債券'!$BD$5:$BD$404,$A16))>1E8,"",IF(INDEX('債券'!$AQ$5:$AQ$404,MATCH(LARGE('債券'!$BD$5:$BD$404,$A16),'債券'!$BD$5:$BD$404,0))="","",INDEX('債券'!$AQ$5:$AQ$404,MATCH(LARGE('債券'!$BD$5:$BD$404,$A16),'債券'!$BD$5:$BD$404,0)))) | N16: =IF(ABS(LARGE('債券'!$BD$5:$BD$404,$A16))>1E8,"",IF(INDEX('債券'!$AI$5:$AI$404,MATCH(LARGE('債券'!$BD$5:$BD$404,$A16),'債券'!$BD$5:$BD$404,0))="","",INDEX('債券'!$AI$5:$AI$404,MATCH(LARGE('債券'!$BD$5:$BD$404,$A16),'債券'!$BD$5:$BD$404,0))))
A17: 12 | B17: =IF(ABS(LARGE('債券'!$BD$5:$BD$404,$A17))>1E8,"",IF(INDEX('債券'!$A$5:$A$404,MATCH(LARGE('債券'!$BD$5:$BD$404,$A17),'債券'!$BD$5:$BD$404,0))="","",INDEX('債券'!$A$5:$A$404,MATCH(LARGE('債券'!$BD$5:$BD$404,$A17),'債券'!$BD$5:$BD$404,0)))) | C17: =IF(ABS(LARGE('債券'!$BD$5:$BD$404,$A17))>1E8,"",IF(INDEX('債券'!$C$5:$C$404,MATCH(LARGE('債券'!$BD$5:$BD$404,$A17),'債券'!$BD$5:$BD$404,0))="","",INDEX('債券'!$C$5:$C$404,MATCH(LARGE('債券'!$BD$5:$BD$404,$A17),'債券'!$BD$5:$BD$404,0)))) | D17: =IF(ABS(LARGE('債券'!$BD$5:$BD$404,$A17))>1E8,"",IF(INDEX('債券'!$S$5:$S$404,MATCH(LARGE('債券'!$BD$5:$BD$404,$A17),'債券'!$BD$5:$BD$404,0))="","",INDEX('債券'!$S$5:$S$404,MATCH(LARGE('債券'!$BD$5:$BD$404,$A17),'債券'!$BD$5:$BD$404,0)))) | E17: =IF(ABS(LARGE('債券'!$BD$5:$BD$404,$A17))>1E8,"",IF(INDEX('債券'!$G$5:$G$404,MATCH(LARGE('債券'!$BD$5:$BD$404,$A17),'債券'!$BD$5:$BD$404,0))="","",INDEX('債券'!$G$5:$G$404,MATCH(LARGE('債券'!$BD$5:$BD$404,$A17),'債券'!$BD$5:$BD$404,0)))) | F17: =IF(ABS(LARGE('債券'!$BD$5:$BD$404,$A17))>1E8,"",IF(INDEX('債券'!$U$5:$U$404,MATCH(LARGE('債券'!$BD$5:$BD$404,$A17),'債券'!$BD$5:$BD$404,0))="","",INDEX('債券'!$U$5:$U$404,MATCH(LARGE('債券'!$BD$5:$BD$404,$A17),'債券'!$BD$5:$BD$404,0)))) | G17: =IF(ABS(LARGE('債券'!$BD$5:$BD$404,$A17))>1E8,"",IF(INDEX('債券'!$N$5:$N$404,MATCH(LARGE('債券'!$BD$5:$BD$404,$A17),'債券'!$BD$5:$BD$404,0))="","",INDEX('債券'!$N$5:$N$404,MATCH(LARGE('債券'!$BD$5:$BD$404,$A17),'債券'!$BD$5:$BD$404,0)))) | H17: =IF(ABS(LARGE('債券'!$BD$5:$BD$404,$A17))>1E8,"",IF(INDEX('債券'!$Z$5:$Z$404,MATCH(LARGE('債券'!$BD$5:$BD$404,$A17),'債券'!$BD$5:$BD$404,0))="","",INDEX('債券'!$Z$5:$Z$404,MATCH(LARGE('債券'!$BD$5:$BD$404,$A17),'債券'!$BD$5:$BD$404,0)))) | I17: =IF(ABS(LARGE('債券'!$BD$5:$BD$404,$A17))>1E8,"",IF(INDEX('債券'!$AF$5:$AF$404,MATCH(LARGE('債券'!$BD$5:$BD$404,$A17),'債券'!$BD$5:$BD$404,0))="","",INDEX('債券'!$AF$5:$AF$404,MATCH(LARGE('債券'!$BD$5:$BD$404,$A17),'債券'!$BD$5:$BD$404,0)))) | J17: =IF(ABS(LARGE('債券'!$BD$5:$BD$404,$A17))>1E8,"",IF(INDEX('債券'!$AM$5:$AM$404,MATCH(LARGE('債券'!$BD$5:$BD$404,$A17),'債券'!$BD$5:$BD$404,0))="","",INDEX('債券'!$AM$5:$AM$404,MATCH(LARGE('債券'!$BD$5:$BD$404,$A17),'債券'!$BD$5:$BD$404,0)))) | K17: =IF(ABS(LARGE('債券'!$BD$5:$BD$404,$A17))>1E8,"",IF(INDEX('債券'!$AO$5:$AO$404,MATCH(LARGE('債券'!$BD$5:$BD$404,$A17),'債券'!$BD$5:$BD$404,0))="","",INDEX('債券'!$AO$5:$AO$404,MATCH(LARGE('債券'!$BD$5:$BD$404,$A17),'債券'!$BD$5:$BD$404,0)))) | L17: =IF(ABS(LARGE('債券'!$BD$5:$BD$404,$A17))>1E8,"",IF(INDEX('債券'!$AP$5:$AP$404,MATCH(LARGE('債券'!$BD$5:$BD$404,$A17),'債券'!$BD$5:$BD$404,0))="","",INDEX('債券'!$AP$5:$AP$404,MATCH(LARGE('債券'!$BD$5:$BD$404,$A17),'債券'!$BD$5:$BD$404,0)))) | M17: =IF(ABS(LARGE('債券'!$BD$5:$BD$404,$A17))>1E8,"",IF(INDEX('債券'!$AQ$5:$AQ$404,MATCH(LARGE('債券'!$BD$5:$BD$404,$A17),'債券'!$BD$5:$BD$404,0))="","",INDEX('債券'!$AQ$5:$AQ$404,MATCH(LARGE('債券'!$BD$5:$BD$404,$A17),'債券'!$BD$5:$BD$404,0)))) | N17: =IF(ABS(LARGE('債券'!$BD$5:$BD$404,$A17))>1E8,"",IF(INDEX('債券'!$AI$5:$AI$404,MATCH(LARGE('債券'!$BD$5:$BD$404,$A17),'債券'!$BD$5:$BD$404,0))="","",INDEX('債券'!$AI$5:$AI$404,MATCH(LARGE('債券'!$BD$5:$BD$404,$A17),'債券'!$BD$5:$BD$404,0))))
... A25: 20 | B25: =IF(ABS(LARGE('債券'!$BD$5:$BD$404,$A25))>1E8,"",IF(INDEX('債券'!$A$5:$A$404,MATCH(LARGE('債券'!$BD$5:$BD$404,$A25),'債券'!$BD$5:$BD$404,0))="","",INDEX('債券'!$A$5:$A$404,MATCH(LARGE('債券'!$BD$5:$BD$404,$A25),'債券'!$BD$5:$BD$404,0)))) | C25: =IF(ABS(LARGE('債券'!$BD$5:$BD$404,$A25))>1E8,"",IF(INDEX('債券'!$C$5:$C$404,MATCH(LARGE('債券'!$BD$5:$BD$404,$A25),'債券'!$BD$5:$BD$404,0))="","",INDEX('債券'!$C$5:$C$404,MATCH(LARGE('債券'!$BD$5:$BD$404,$A25),'債券'!$BD$5:$BD$404,0)))) | D25: =IF(ABS(LARGE('債券'!$BD$5:$BD$404,$A25))>1E8,"",IF(INDEX('債券'!$S$5:$S$404,MATCH(LARGE('債券'!$BD$5:$BD$404,$A25),'債券'!$BD$5:$BD$404,0))="","",INDEX('債券'!$S$5:$S$404,MATCH(LARGE('債券'!$BD$5:$BD$404,$A25),'債券'!$BD$5:$BD$404,0)))) | E25: =IF(ABS(LARGE('債券'!$BD$5:$BD$404,$A25))>1E8,"",IF(INDEX('債券'!$G$5:$G$404,MATCH(LARGE('債券'!$BD$5:$BD$404,$A25),'債券'!$BD$5:$BD$404,0))="","",INDEX('債券'!$G$5:$G$404,MATCH(LARGE('債券'!$BD$5:$BD$404,$A25),'債券'!$BD$5:$BD$404,0)))) | F25: =IF(ABS(LARGE('債券'!$BD$5:$BD$404,$A25))>1E8,"",IF(INDEX('債券'!$U$5:$U$404,MATCH(LARGE('債券'!$BD$5:$BD$404,$A25),'債券'!$BD$5:$BD$404,0))="","",INDEX('債券'!$U$5:$U$404,MATCH(LARGE('債券'!$BD$5:$BD$404,$A25),'債券'!$BD$5:$BD$404,0)))) | G25: =IF(ABS(LARGE('債券'!$BD$5:$BD$404,$A25))>1E8,"",IF(INDEX('債券'!$N$5:$N$404,MATCH(LARGE('債券'!$BD$5:$BD$404,$A25),'債券'!$BD$5:$BD$404,0))="","",INDEX('債券'!$N$5:$N$404,MATCH(LARGE('債券'!$BD$5:$BD$404,$A25),'債券'!$BD$5:$BD$404,0)))) | H25: =IF(ABS(LARGE('債券'!$BD$5:$BD$404,$A25))>1E8,"",IF(INDEX('債券'!$Z$5:$Z$404,MATCH(LARGE('債券'!$BD$5:$BD$404,$A25),'債券'!$BD$5:$BD$404,0))="","",INDEX('債券'!$Z$5:$Z$404,MATCH(LARGE('債券'!$BD$5:$BD$404,$A25),'債券'!$BD$5:$BD$404,0)))) | I25: =IF(ABS(LARGE('債券'!$BD$5:$BD$404,$A25))>1E8,"",IF(INDEX('債券'!$AF$5:$AF$404,MATCH(LARGE('債券'!$BD$5:$BD$404,$A25),'債券'!$BD$5:$BD$404,0))="","",INDEX('債券'!$AF$5:$AF$404,MATCH(LARGE('債券'!$BD$5:$BD$404,$A25),'債券'!$BD$5:$BD$404,0)))) | J25: =IF(ABS(LARGE('債券'!$BD$5:$BD$404,$A25))>1E8,"",IF(INDEX('債券'!$AM$5:$AM$404,MATCH(LARGE('債券'!$BD$5:$BD$404,$A25),'債券'!$BD$5:$BD$404,0))="","",INDEX('債券'!$AM$5:$AM$404,MATCH(LARGE('債券'!$BD$5:$BD$404,$A25),'債券'!$BD$5:$BD$404,0)))) | K25: =IF(ABS(LARGE('債券'!$BD$5:$BD$404,$A25))>1E8,"",IF(INDEX('債券'!$AO$5:$AO$404,MATCH(LARGE('債券'!$BD$5:$BD$404,$A25),'債券'!$BD$5:$BD$404,0))="","",INDEX('債券'!$AO$5:$AO$404,MATCH(LARGE('債券'!$BD$5:$BD$404,$A25),'債券'!$BD$5:$BD$404,0)))) | L25: =IF(ABS(LARGE('債券'!$BD$5:$BD$404,$A25))>1E8,"",IF(INDEX('債券'!$AP$5:$AP$404,MATCH(LARGE('債券'!$BD$5:$BD$404,$A25),'債券'!$BD$5:$BD$404,0))="","",INDEX('債券'!$AP$5:$AP$404,MATCH(LARGE('債券'!$BD$5:$BD$404,$A25),'債券'!$BD$5:$BD$404,0)))) | M25: =IF(ABS(LARGE('債券'!$BD$5:$BD$404,$A25))>1E8,"",IF(INDEX('債券'!$AQ$5:$AQ$404,MATCH(LARGE('債券'!$BD$5:$BD$404,$A25),'債券'!$BD$5:$BD$404,0))="","",INDEX('債券'!$AQ$5:$AQ$404,MATCH(LARGE('債券'!$BD$5:$BD$404,$A25),'債券'!$BD$5:$BD$404,0)))) | N25: =IF(ABS(LARGE('債券'!$BD$5:$BD$404,$A25))>1E8,"",IF(INDEX('債券'!$AI$5:$AI$404,MATCH(LARGE('債券'!$BD$5:$BD$404,$A25),'債券'!$BD$5:$BD$404,0))="","",INDEX('債券'!$AI$5:$AI$404,MATCH(LARGE('債券'!$BD$5:$BD$404,$A25),'債券'!$BD$5:$BD$404,0))))
A27: 偏貴／偏弱勢 前 20 名（減碼研究清單）
A28: 排名 | B28: 債券代碼 | C28: 債券簡稱 | D28: 分類 | E28: 評等 | F28: 剩餘年限 | G28: OAS (bp) | H28: DTS | I28: Carry z | J28: Value z | K28: Momentum z | L28: 股票動能 z | M28: 綜合分數 | N28: 相對發行人 曲線 (bp)
A29: 1 | B29: =IF(ABS(SMALL('債券'!$BE$5:$BE$404,$A29))>1E8,"",IF(INDEX('債券'!$A$5:$A$404,MATCH(SMALL('債券'!$BE$5:$BE$404,$A29),'債券'!$BE$5:$BE$404,0))="","",INDEX('債券'!$A$5:$A$404,MATCH(SMALL('債券'!$BE$5:$BE$404,$A29),'債券'!$BE$5:$BE$404,0)))) | C29: =IF(ABS(SMALL('債券'!$BE$5:$BE$404,$A29))>1E8,"",IF(INDEX('債券'!$C$5:$C$404,MATCH(SMALL('債券'!$BE$5:$BE$404,$A29),'債券'!$BE$5:$BE$404,0))="","",INDEX('債券'!$C$5:$C$404,MATCH(SMALL('債券'!$BE$5:$BE$404,$A29),'債券'!$BE$5:$BE$404,0)))) | D29: =IF(ABS(SMALL('債券'!$BE$5:$BE$404,$A29))>1E8,"",IF(INDEX('債券'!$S$5:$S$404,MATCH(SMALL('債券'!$BE$5:$BE$404,$A29),'債券'!$BE$5:$BE$404,0))="","",INDEX('債券'!$S$5:$S$404,MATCH(SMALL('債券'!$BE$5:$BE$404,$A29),'債券'!$BE$5:$BE$404,0)))) | E29: =IF(ABS(SMALL('債券'!$BE$5:$BE$404,$A29))>1E8,"",IF(INDEX('債券'!$G$5:$G$404,MATCH(SMALL('債券'!$BE$5:$BE$404,$A29),'債券'!$BE$5:$BE$404,0))="","",INDEX('債券'!$G$5:$G$404,MATCH(SMALL('債券'!$BE$5:$BE$404,$A29),'債券'!$BE$5:$BE$404,0)))) | F29: =IF(ABS(SMALL('債券'!$BE$5:$BE$404,$A29))>1E8,"",IF(INDEX('債券'!$U$5:$U$404,MATCH(SMALL('債券'!$BE$5:$BE$404,$A29),'債券'!$BE$5:$BE$404,0))="","",INDEX('債券'!$U$5:$U$404,MATCH(SMALL('債券'!$BE$5:$BE$404,$A29),'債券'!$BE$5:$BE$404,0)))) | G29: =IF(ABS(SMALL('債券'!$BE$5:$BE$404,$A29))>1E8,"",IF(INDEX('債券'!$N$5:$N$404,MATCH(SMALL('債券'!$BE$5:$BE$404,$A29),'債券'!$BE$5:$BE$404,0))="","",INDEX('債券'!$N$5:$N$404,MATCH(SMALL('債券'!$BE$5:$BE$404,$A29),'債券'!$BE$5:$BE$404,0)))) | H29: =IF(ABS(SMALL('債券'!$BE$5:$BE$404,$A29))>1E8,"",IF(INDEX('債券'!$Z$5:$Z$404,MATCH(SMALL('債券'!$BE$5:$BE$404,$A29),'債券'!$BE$5:$BE$404,0))="","",INDEX('債券'!$Z$5:$Z$404,MATCH(SMALL('債券'!$BE$5:$BE$404,$A29),'債券'!$BE$5:$BE$404,0)))) | I29: =IF(ABS(SMALL('債券'!$BE$5:$BE$404,$A29))>1E8,"",IF(INDEX('債券'!$AF$5:$AF$404,MATCH(SMALL('債券'!$BE$5:$BE$404,$A29),'債券'!$BE$5:$BE$404,0))="","",INDEX('債券'!$AF$5:$AF$404,MATCH(SMALL('債券'!$BE$5:$BE$404,$A29),'債券'!$BE$5:$BE$404,0)))) | J29: =IF(ABS(SMALL('債券'!$BE$5:$BE$404,$A29))>1E8,"",IF(INDEX('債券'!$AM$5:$AM$404,MATCH(SMALL('債券'!$BE$5:$BE$404,$A29),'債券'!$BE$5:$BE$404,0))="","",INDEX('債券'!$AM$5:$AM$404,MATCH(SMALL('債券'!$BE$5:$BE$404,$A29),'債券'!$BE$5:$BE$404,0)))) | K29: =IF(ABS(SMALL('債券'!$BE$5:$BE$404,$A29))>1E8,"",IF(INDEX('債券'!$AO$5:$AO$404,MATCH(SMALL('債券'!$BE$5:$BE$404,$A29),'債券'!$BE$5:$BE$404,0))="","",INDEX('債券'!$AO$5:$AO$404,MATCH(SMALL('債券'!$BE$5:$BE$404,$A29),'債券'!$BE$5:$BE$404,0)))) | L29: =IF(ABS(SMALL('債券'!$BE$5:$BE$404,$A29))>1E8,"",IF(INDEX('債券'!$AP$5:$AP$404,MATCH(SMALL('債券'!$BE$5:$BE$404,$A29),'債券'!$BE$5:$BE$404,0))="","",INDEX('債券'!$AP$5:$AP$404,MATCH(SMALL('債券'!$BE$5:$BE$404,$A29),'債券'!$BE$5:$BE$404,0)))) | M29: =IF(ABS(SMALL('債券'!$BE$5:$BE$404,$A29))>1E8,"",IF(INDEX('債券'!$AQ$5:$AQ$404,MATCH(SMALL('債券'!$BE$5:$BE$404,$A29),'債券'!$BE$5:$BE$404,0))="","",INDEX('債券'!$AQ$5:$AQ$404,MATCH(SMALL('債券'!$BE$5:$BE$404,$A29),'債券'!$BE$5:$BE$404,0)))) | N29: =IF(ABS(SMALL('債券'!$BE$5:$BE$404,$A29))>1E8,"",IF(INDEX('債券'!$AI$5:$AI$404,MATCH(SMALL('債券'!$BE$5:$BE$404,$A29),'債券'!$BE$5:$BE$404,0))="","",INDEX('債券'!$AI$5:$AI$404,MATCH(SMALL('債券'!$BE$5:$BE$404,$A29),'債券'!$BE$5:$BE$404,0))))
A30: 2 | B30: =IF(ABS(SMALL('債券'!$BE$5:$BE$404,$A30))>1E8,"",IF(INDEX('債券'!$A$5:$A$404,MATCH(SMALL('債券'!$BE$5:$BE$404,$A30),'債券'!$BE$5:$BE$404,0))="","",INDEX('債券'!$A$5:$A$404,MATCH(SMALL('債券'!$BE$5:$BE$404,$A30),'債券'!$BE$5:$BE$404,0)))) | C30: =IF(ABS(SMALL('債券'!$BE$5:$BE$404,$A30))>1E8,"",IF(INDEX('債券'!$C$5:$C$404,MATCH(SMALL('債券'!$BE$5:$BE$404,$A30),'債券'!$BE$5:$BE$404,0))="","",INDEX('債券'!$C$5:$C$404,MATCH(SMALL('債券'!$BE$5:$BE$404,$A30),'債券'!$BE$5:$BE$404,0)))) | D30: =IF(ABS(SMALL('債券'!$BE$5:$BE$404,$A30))>1E8,"",IF(INDEX('債券'!$S$5:$S$404,MATCH(SMALL('債券'!$BE$5:$BE$404,$A30),'債券'!$BE$5:$BE$404,0))="","",INDEX('債券'!$S$5:$S$404,MATCH(SMALL('債券'!$BE$5:$BE$404,$A30),'債券'!$BE$5:$BE$404,0)))) | E30: =IF(ABS(SMALL('債券'!$BE$5:$BE$404,$A30))>1E8,"",IF(INDEX('債券'!$G$5:$G$404,MATCH(SMALL('債券'!$BE$5:$BE$404,$A30),'債券'!$BE$5:$BE$404,0))="","",INDEX('債券'!$G$5:$G$404,MATCH(SMALL('債券'!$BE$5:$BE$404,$A30),'債券'!$BE$5:$BE$404,0)))) | F30: =IF(ABS(SMALL('債券'!$BE$5:$BE$404,$A30))>1E8,"",IF(INDEX('債券'!$U$5:$U$404,MATCH(SMALL('債券'!$BE$5:$BE$404,$A30),'債券'!$BE$5:$BE$404,0))="","",INDEX('債券'!$U$5:$U$404,MATCH(SMALL('債券'!$BE$5:$BE$404,$A30),'債券'!$BE$5:$BE$404,0)))) | G30: =IF(ABS(SMALL('債券'!$BE$5:$BE$404,$A30))>1E8,"",IF(INDEX('債券'!$N$5:$N$404,MATCH(SMALL('債券'!$BE$5:$BE$404,$A30),'債券'!$BE$5:$BE$404,0))="","",INDEX('債券'!$N$5:$N$404,MATCH(SMALL('債券'!$BE$5:$BE$404,$A30),'債券'!$BE$5:$BE$404,0)))) | H30: =IF(ABS(SMALL('債券'!$BE$5:$BE$404,$A30))>1E8,"",IF(INDEX('債券'!$Z$5:$Z$404,MATCH(SMALL('債券'!$BE$5:$BE$404,$A30),'債券'!$BE$5:$BE$404,0))="","",INDEX('債券'!$Z$5:$Z$404,MATCH(SMALL('債券'!$BE$5:$BE$404,$A30),'債券'!$BE$5:$BE$404,0)))) | I30: =IF(ABS(SMALL('債券'!$BE$5:$BE$404,$A30))>1E8,"",IF(INDEX('債券'!$AF$5:$AF$404,MATCH(SMALL('債券'!$BE$5:$BE$404,$A30),'債券'!$BE$5:$BE$404,0))="","",INDEX('債券'!$AF$5:$AF$404,MATCH(SMALL('債券'!$BE$5:$BE$404,$A30),'債券'!$BE$5:$BE$404,0)))) | J30: =IF(ABS(SMALL('債券'!$BE$5:$BE$404,$A30))>1E8,"",IF(INDEX('債券'!$AM$5:$AM$404,MATCH(SMALL('債券'!$BE$5:$BE$404,$A30),'債券'!$BE$5:$BE$404,0))="","",INDEX('債券'!$AM$5:$AM$404,MATCH(SMALL('債券'!$BE$5:$BE$404,$A30),'債券'!$BE$5:$BE$404,0)))) | K30: =IF(ABS(SMALL('債券'!$BE$5:$BE$404,$A30))>1E8,"",IF(INDEX('債券'!$AO$5:$AO$404,MATCH(SMALL('債券'!$BE$5:$BE$404,$A30),'債券'!$BE$5:$BE$404,0))="","",INDEX('債券'!$AO$5:$AO$404,MATCH(SMALL('債券'!$BE$5:$BE$404,$A30),'債券'!$BE$5:$BE$404,0)))) | L30: =IF(ABS(SMALL('債券'!$BE$5:$BE$404,$A30))>1E8,"",IF(INDEX('債券'!$AP$5:$AP$404,MATCH(SMALL('債券'!$BE$5:$BE$404,$A30),'債券'!$BE$5:$BE$404,0))="","",INDEX('債券'!$AP$5:$AP$404,MATCH(SMALL('債券'!$BE$5:$BE$404,$A30),'債券'!$BE$5:$BE$404,0)))) | M30: =IF(ABS(SMALL('債券'!$BE$5:$BE$404,$A30))>1E8,"",IF(INDEX('債券'!$AQ$5:$AQ$404,MATCH(SMALL('債券'!$BE$5:$BE$404,$A30),'債券'!$BE$5:$BE$404,0))="","",INDEX('債券'!$AQ$5:$AQ$404,MATCH(SMALL('債券'!$BE$5:$BE$404,$A30),'債券'!$BE$5:$BE$404,0)))) | N30: =IF(ABS(SMALL('債券'!$BE$5:$BE$404,$A30))>1E8,"",IF(INDEX('債券'!$AI$5:$AI$404,MATCH(SMALL('債券'!$BE$5:$BE$404,$A30),'債券'!$BE$5:$BE$404,0))="","",INDEX('債券'!$AI$5:$AI$404,MATCH(SMALL('債券'!$BE$5:$BE$404,$A30),'債券'!$BE$5:$BE$404,0))))
A31: 3 | B31: =IF(ABS(SMALL('債券'!$BE$5:$BE$404,$A31))>1E8,"",IF(INDEX('債券'!$A$5:$A$404,MATCH(SMALL('債券'!$BE$5:$BE$404,$A31),'債券'!$BE$5:$BE$404,0))="","",INDEX('債券'!$A$5:$A$404,MATCH(SMALL('債券'!$BE$5:$BE$404,$A31),'債券'!$BE$5:$BE$404,0)))) | C31: =IF(ABS(SMALL('債券'!$BE$5:$BE$404,$A31))>1E8,"",IF(INDEX('債券'!$C$5:$C$404,MATCH(SMALL('債券'!$BE$5:$BE$404,$A31),'債券'!$BE$5:$BE$404,0))="","",INDEX('債券'!$C$5:$C$404,MATCH(SMALL('債券'!$BE$5:$BE$404,$A31),'債券'!$BE$5:$BE$404,0)))) | D31: =IF(ABS(SMALL('債券'!$BE$5:$BE$404,$A31))>1E8,"",IF(INDEX('債券'!$S$5:$S$404,MATCH(SMALL('債券'!$BE$5:$BE$404,$A31),'債券'!$BE$5:$BE$404,0))="","",INDEX('債券'!$S$5:$S$404,MATCH(SMALL('債券'!$BE$5:$BE$404,$A31),'債券'!$BE$5:$BE$404,0)))) | E31: =IF(ABS(SMALL('債券'!$BE$5:$BE$404,$A31))>1E8,"",IF(INDEX('債券'!$G$5:$G$404,MATCH(SMALL('債券'!$BE$5:$BE$404,$A31),'債券'!$BE$5:$BE$404,0))="","",INDEX('債券'!$G$5:$G$404,MATCH(SMALL('債券'!$BE$5:$BE$404,$A31),'債券'!$BE$5:$BE$404,0)))) | F31: =IF(ABS(SMALL('債券'!$BE$5:$BE$404,$A31))>1E8,"",IF(INDEX('債券'!$U$5:$U$404,MATCH(SMALL('債券'!$BE$5:$BE$404,$A31),'債券'!$BE$5:$BE$404,0))="","",INDEX('債券'!$U$5:$U$404,MATCH(SMALL('債券'!$BE$5:$BE$404,$A31),'債券'!$BE$5:$BE$404,0)))) | G31: =IF(ABS(SMALL('債券'!$BE$5:$BE$404,$A31))>1E8,"",IF(INDEX('債券'!$N$5:$N$404,MATCH(SMALL('債券'!$BE$5:$BE$404,$A31),'債券'!$BE$5:$BE$404,0))="","",INDEX('債券'!$N$5:$N$404,MATCH(SMALL('債券'!$BE$5:$BE$404,$A31),'債券'!$BE$5:$BE$404,0)))) | H31: =IF(ABS(SMALL('債券'!$BE$5:$BE$404,$A31))>1E8,"",IF(INDEX('債券'!$Z$5:$Z$404,MATCH(SMALL('債券'!$BE$5:$BE$404,$A31),'債券'!$BE$5:$BE$404,0))="","",INDEX('債券'!$Z$5:$Z$404,MATCH(SMALL('債券'!$BE$5:$BE$404,$A31),'債券'!$BE$5:$BE$404,0)))) | I31: =IF(ABS(SMALL('債券'!$BE$5:$BE$404,$A31))>1E8,"",IF(INDEX('債券'!$AF$5:$AF$404,MATCH(SMALL('債券'!$BE$5:$BE$404,$A31),'債券'!$BE$5:$BE$404,0))="","",INDEX('債券'!$AF$5:$AF$404,MATCH(SMALL('債券'!$BE$5:$BE$404,$A31),'債券'!$BE$5:$BE$404,0)))) | J31: =IF(ABS(SMALL('債券'!$BE$5:$BE$404,$A31))>1E8,"",IF(INDEX('債券'!$AM$5:$AM$404,MATCH(SMALL('債券'!$BE$5:$BE$404,$A31),'債券'!$BE$5:$BE$404,0))="","",INDEX('債券'!$AM$5:$AM$404,MATCH(SMALL('債券'!$BE$5:$BE$404,$A31),'債券'!$BE$5:$BE$404,0)))) | K31: =IF(ABS(SMALL('債券'!$BE$5:$BE$404,$A31))>1E8,"",IF(INDEX('債券'!$AO$5:$AO$404,MATCH(SMALL('債券'!$BE$5:$BE$404,$A31),'債券'!$BE$5:$BE$404,0))="","",INDEX('債券'!$AO$5:$AO$404,MATCH(SMALL('債券'!$BE$5:$BE$404,$A31),'債券'!$BE$5:$BE$404,0)))) | L31: =IF(ABS(SMALL('債券'!$BE$5:$BE$404,$A31))>1E8,"",IF(INDEX('債券'!$AP$5:$AP$404,MATCH(SMALL('債券'!$BE$5:$BE$404,$A31),'債券'!$BE$5:$BE$404,0))="","",INDEX('債券'!$AP$5:$AP$404,MATCH(SMALL('債券'!$BE$5:$BE$404,$A31),'債券'!$BE$5:$BE$404,0)))) | M31: =IF(ABS(SMALL('債券'!$BE$5:$BE$404,$A31))>1E8,"",IF(INDEX('債券'!$AQ$5:$AQ$404,MATCH(SMALL('債券'!$BE$5:$BE$404,$A31),'債券'!$BE$5:$BE$404,0))="","",INDEX('債券'!$AQ$5:$AQ$404,MATCH(SMALL('債券'!$BE$5:$BE$404,$A31),'債券'!$BE$5:$BE$404,0)))) | N31: =IF(ABS(SMALL('債券'!$BE$5:$BE$404,$A31))>1E8,"",IF(INDEX('債券'!$AI$5:$AI$404,MATCH(SMALL('債券'!$BE$5:$BE$404,$A31),'債券'!$BE$5:$BE$404,0))="","",INDEX('債券'!$AI$5:$AI$404,MATCH(SMALL('債券'!$BE$5:$BE$404,$A31),'債券'!$BE$5:$BE$404,0))))
